{
  "name": "RRThunder",
  "diff": 1,
  "events": [
    {
      "GUID": "5204f890-5c42-4f8a-9c13-78deb9cbc84f",
      "ID": "4355",
      "Facing": "Right",
      "Health": "2",
      "X": "2",
      "Y": "0",
      "Beat": "9",
      "Time": "3.58209",
      "Spawn": "0",
      "Vibe": "False",
      "Burning": "False",
      "Mysterious": "False",
      "Event": "HitEnemy"
    },
    {
      "GUID": "5204f890-5c42-4f8a-9c13-78deb9cbc84f",
      "ID": "4355",
      "Facing": "Left",
      "Health": "1",
      "X": "2",
      "Y": "0",
      "Beat": "10",
      "Time": "4.029851",
      "Spawn": "0",
      "Vibe": "False",
      "Burning": "False",
      "Mysterious": "False",
      "Event": "HitEnemy"
    },
    {
      "GUID": "7a26392c-b407-4d36-8d73-dfbe14db18ea",
      "ID": "4355",
      "Facing": "Right",
      "Health": "2",
      "X": "1",
      "Y": "0",
      "Beat": "13",
      "Time": "5.373134",
      "Spawn": "4",
      "Vibe": "False",
      "Burning": "False",
      "Mysterious": "False",
      "Event": "HitEnemy"
    },
    {
      "GUID": "7a26392c-b407-4d36-8d73-dfbe14db18ea",
      "ID": "4355",
      "Facing": "Left",
      "Health": "1",
      "X": "1",
      "Y": "0",
      "Beat": "14",
      "Time": "5.820896",
      "Spawn": "4",
      "Vibe": "False",
      "Burning": "False",
      "Mysterious": "False",
      "Event": "HitEnemy"
    },
    {
      "GUID": "665ee6f0-cecd-4ded-86ab-f424675717a7",
      "ID": "4355",
      "Facing": "Right",
      "Health": "2",
      "X": "2",
      "Y": "0",
      "Beat": "17",
      "Time": "7.164179",
      "Spawn": "8",
      "Vibe": "False",
      "Burning": "False",
      "Mysterious": "False",
      "Event": "HitEnemy"
    },
    {
      "GUID": "665ee6f0-cecd-4ded-86ab-f424675717a7",
      "ID": "4355",
      "Facing": "Left",
      "Health": "1",
      "X": "2",
      "Y": "0",
      "Beat": "18",
      "Time": "7.61194",
      "Spawn": "8",
      "Vibe": "False",
      "Burning": "False",
      "Mysterious": "False",
      "Event": "HitEnemy"
    },
    {
      "GUID": "542dbb44-9430-414b-bdad-0e826e967cb0",
      "ID": "1722",
      "Facing": "Right",
      "Health": "1",
      "X": "0",
      "Y": "0",
      "Beat": "21",
      "Time": "8.955224",
      "Spawn": "12",
      "Vibe": "False",
      "Burning": "False",
      "Mysterious": "False",
      "Event": "HitEnemy"
    },
    {
      "GUID": "9840b466-62cd-4719-abc5-6d3b89048524",
      "ID": "1722",
      "Facing": "Right",
      "Health": "1",
      "X": "0",
      "Y": "0",
      "Beat": "23",
      "Time": "9.850746",
      "Spawn": "14",
      "Vibe": "False",
      "Burning": "False",
      "Mysterious": "False",
      "Event": "HitEnemy"
    },
    {
      "GUID": "3294dd3d-c367-450a-a70e-c45a5a8789ea",
      "ID": "929",
      "Facing": "Left",
      "Health": "1",
      "X": "1",
      "Y": "3",
      "Beat": "24.96799",
      "Time": "10.73193",
      "Spawn": "19",
      "Vibe": "False",
      "Burning": "False",
      "Mysterious": "False",
      "Event": "BlademasterPrepare"
    },
    {
      "GUID": "b5aea6b0-1f4c-4c63-b546-819d31ff9621",
      "ID": "1722",
      "Facing": "Right",
      "Health": "1",
      "X": "1",
      "Y": "0",
      "Beat": "25",
      "Time": "10.74627",
      "Spawn": "16",
      "Vibe": "False",
      "Burning": "False",
      "Mysterious": "False",
      "Event": "HitEnemy"
    },
    {
      "GUID": "3294dd3d-c367-450a-a70e-c45a5a8789ea",
      "ID": "929",
      "Facing": "Left",
      "Health": "1",
      "X": "1",
      "Y": "0",
      "Beat": "27",
      "Time": "11.64179",
      "Spawn": "19",
      "Vibe": "False",
      "Burning": "False",
      "Mysterious": "False",
      "Event": "HitEnemy"
    },
    {
      "GUID": "f319d3cb-319d-4b29-9b74-000a6a9620fe",
      "ID": "1722",
      "Facing": "Right",
      "Health": "1",
      "X": "0",
      "Y": "0",
      "Beat": "29",
      "Time": "12.53731",
      "Spawn": "20",
      "Vibe": "False",
      "Burning": "False",
      "Mysterious": "False",
      "Event": "HitEnemy"
    },
    {
      "GUID": "c763e282-8749-4b00-a5f6-e678f07713f1",
      "ID": "7358",
      "Facing": "Left",
      "Health": "1",
      "X": "0",
      "Y": "0",
      "Beat": "31",
      "Time": "13.43284",
      "Spawn": "22",
      "Vibe": "False",
      "Burning": "False",
      "Mysterious": "False",
      "Event": "HitEnemy"
    },
    {
      "GUID": "ade9f023-ff7b-496c-b296-56e93078a44a",
      "ID": "929",
      "Facing": "Left",
      "Health": "1",
      "X": "1",
      "Y": "3",
      "Beat": "32.97549",
      "Time": "14.31738",
      "Spawn": "27",
      "Vibe": "False",
      "Burning": "False",
      "Mysterious": "False",
      "Event": "BlademasterPrepare"
    },
    {
      "GUID": "6e795524-6196-4d49-a1cb-cf78117ed182",
      "ID": "1722",
      "Facing": "Right",
      "Health": "1",
      "X": "1",
      "Y": "0",
      "Beat": "33",
      "Time": "14.32836",
      "Spawn": "24",
      "Vibe": "False",
      "Burning": "False",
      "Mysterious": "False",
      "Event": "HitEnemy"
    },
    {
      "GUID": "ade9f023-ff7b-496c-b296-56e93078a44a",
      "ID": "929",
      "Facing": "Left",
      "Health": "1",
      "X": "1",
      "Y": "0",
      "Beat": "35",
      "Time": "15.22388",
      "Spawn": "27",
      "Vibe": "False",
      "Burning": "False",
      "Mysterious": "False",
      "Event": "HitEnemy"
    },
    {
      "GUID": "faff6654-35a7-4be2-96e7-0b1f4ec854f8",
      "ID": "1722",
      "Facing": "Right",
      "Health": "1",
      "X": "0",
      "Y": "0",
      "Beat": "37",
      "Time": "16.1194",
      "Spawn": "28",
      "Vibe": "False",
      "Burning": "False",
      "Mysterious": "False",
      "Event": "HitEnemy"
    },
    {
      "GUID": "f4c8ead6-fc33-4d91-b7c2-fac7ddb50379",
      "ID": "1722",
      "Facing": "Right",
      "Health": "1",
      "X": "0",
      "Y": "0",
      "Beat": "39",
      "Time": "17.01493",
      "Spawn": "30",
      "Vibe": "False",
      "Burning": "False",
      "Mysterious": "False",
      "Event": "HitEnemy"
    },
    {
      "GUID": "f486866b-a6b2-4fc1-a3cf-1b48b98031be",
      "ID": "929",
      "Facing": "Left",
      "Health": "1",
      "X": "1",
      "Y": "3",
      "Beat": "40.97972",
      "Time": "17.90137",
      "Spawn": "35",
      "Vibe": "False",
      "Burning": "False",
      "Mysterious": "False",
      "Event": "BlademasterPrepare"
    },
    {
      "GUID": "73ff9cd1-edec-48d0-bd3e-07238595caaa",
      "ID": "1722",
      "Facing": "Right",
      "Health": "1",
      "X": "1",
      "Y": "0",
      "Beat": "41",
      "Time": "17.91045",
      "Spawn": "32",
      "Vibe": "False",
      "Burning": "False",
      "Mysterious": "False",
      "Event": "HitEnemy"
    },
    {
      "GUID": "f486866b-a6b2-4fc1-a3cf-1b48b98031be",
      "ID": "929",
      "Facing": "Left",
      "Health": "1",
      "X": "1",
      "Y": "0",
      "Beat": "43",
      "Time": "18.80597",
      "Spawn": "35",
      "Vibe": "False",
      "Burning": "False",
      "Mysterious": "False",
      "Event": "HitEnemy"
    },
    {
      "GUID": "f60bdd91-a23f-4f27-93b0-c13d89dad265",
      "ID": "1722",
      "Facing": "Right",
      "Health": "1",
      "X": "0",
      "Y": "0",
      "Beat": "45",
      "Time": "19.70149",
      "Spawn": "36",
      "Vibe": "False",
      "Burning": "False",
      "Mysterious": "False",
      "Event": "HitEnemy"
    },
    {
      "GUID": "e931d1c2-a780-49e3-8d31-7d51b916fa74",
      "ID": "7358",
      "Facing": "Left",
      "Health": "1",
      "X": "0",
      "Y": "0",
      "Beat": "47",
      "Time": "20.59702",
      "Spawn": "38",
      "Vibe": "False",
      "Burning": "False",
      "Mysterious": "False",
      "Event": "HitEnemy"
    },
    {
      "GUID": "eb9759f9-ca44-42b0-ad79-e6de3d744ea8",
      "ID": "929",
      "Facing": "Left",
      "Health": "1",
      "X": "1",
      "Y": "3",
      "Beat": "48.98068",
      "Time": "21.48389",
      "Spawn": "43",
      "Vibe": "False",
      "Burning": "False",
      "Mysterious": "False",
      "Event": "BlademasterPrepare"
    },
    {
      "GUID": "6d78ed8d-4b35-4cb3-8d2d-637ea688a13a",
      "ID": "1722",
      "Facing": "Right",
      "Health": "1",
      "X": "1",
      "Y": "0",
      "Beat": "49",
      "Time": "21.49254",
      "Spawn": "40",
      "Vibe": "False",
      "Burning": "False",
      "Mysterious": "False",
      "Event": "HitEnemy"
    },
    {
      "GUID": "eb9759f9-ca44-42b0-ad79-e6de3d744ea8",
      "ID": "929",
      "Facing": "Left",
      "Health": "1",
      "X": "1",
      "Y": "0",
      "Beat": "51",
      "Time": "22.38806",
      "Spawn": "43",
      "Vibe": "False",
      "Burning": "False",
      "Mysterious": "False",
      "Event": "HitEnemy"
    },
    {
      "GUID": "b1a2f06b-a623-4792-9b44-0153fc4d7f0b",
      "ID": "1722",
      "Facing": "Right",
      "Health": "1",
      "X": "2",
      "Y": "0",
      "Beat": "53",
      "Time": "23.28358",
      "Spawn": "44",
      "Vibe": "False",
      "Burning": "False",
      "Mysterious": "False",
      "Event": "HitEnemy"
    },
    {
      "GUID": "e2505061-304f-4efd-b455-c51445cc3547",
      "ID": "1722",
      "Facing": "Right",
      "Health": "1",
      "X": "2",
      "Y": "0",
      "Beat": "55",
      "Time": "24.1791",
      "Spawn": "46",
      "Vibe": "False",
      "Burning": "False",
      "Mysterious": "False",
      "Event": "HitEnemy"
    },
    {
      "GUID": "8eadfc9d-e526-432a-a4f4-f9f00d7ebae7",
      "ID": "929",
      "Facing": "Left",
      "Health": "1",
      "X": "1",
      "Y": "3",
      "Beat": "56.97891",
      "Time": "25.06519",
      "Spawn": "51",
      "Vibe": "False",
      "Burning": "False",
      "Mysterious": "False",
      "Event": "BlademasterPrepare"
    },
    {
      "GUID": "438a4fb7-0c4d-410e-bb1b-5c68511f19fe",
      "ID": "1722",
      "Facing": "Right",
      "Health": "1",
      "X": "1",
      "Y": "0",
      "Beat": "57",
      "Time": "25.07463",
      "Spawn": "48",
      "Vibe": "False",
      "Burning": "False",
      "Mysterious": "False",
      "Event": "HitEnemy"
    },
    {
      "GUID": "8eadfc9d-e526-432a-a4f4-f9f00d7ebae7",
      "ID": "929",
      "Facing": "Left",
      "Health": "1",
      "X": "1",
      "Y": "0",
      "Beat": "59",
      "Time": "25.97015",
      "Spawn": "51",
      "Vibe": "False",
      "Burning": "False",
      "Mysterious": "False",
      "Event": "HitEnemy"
    },
    {
      "GUID": "2a3a1f02-36f5-44b7-9092-699082496412",
      "ID": "1722",
      "Facing": "Right",
      "Health": "1",
      "X": "2",
      "Y": "0",
      "Beat": "61",
      "Time": "26.86567",
      "Spawn": "52",
      "Vibe": "False",
      "Burning": "False",
      "Mysterious": "False",
      "Event": "HitEnemy"
    },
    {
      "GUID": "d2c7de6c-f1e0-470a-9a94-cc8ad926d7b5",
      "ID": "7358",
      "Facing": "Left",
      "Health": "1",
      "X": "2",
      "Y": "0",
      "Beat": "63",
      "Time": "27.76119",
      "Spawn": "54",
      "Vibe": "False",
      "Burning": "False",
      "Mysterious": "False",
      "Event": "HitEnemy"
    },
    {
      "GUID": "6feccfeb-6532-4c19-b5ac-f315e7bc2c4d",
      "ID": "929",
      "Facing": "Left",
      "Health": "1",
      "X": "1",
      "Y": "3",
      "Beat": "64.98641",
      "Time": "28.65063",
      "Spawn": "59",
      "Vibe": "False",
      "Burning": "False",
      "Mysterious": "False",
      "Event": "BlademasterPrepare"
    },
    {
      "GUID": "9a22e6d8-252d-4fc1-a342-8e93c7e1bd00",
      "ID": "1722",
      "Facing": "Right",
      "Health": "1",
      "X": "1",
      "Y": "0",
      "Beat": "65",
      "Time": "28.65672",
      "Spawn": "56",
      "Vibe": "False",
      "Burning": "False",
      "Mysterious": "False",
      "Event": "HitEnemy"
    },
    {
      "GUID": "6feccfeb-6532-4c19-b5ac-f315e7bc2c4d",
      "ID": "929",
      "Facing": "Left",
      "Health": "1",
      "X": "1",
      "Y": "0",
      "Beat": "67",
      "Time": "29.55224",
      "Spawn": "59",
      "Vibe": "False",
      "Burning": "False",
      "Mysterious": "False",
      "Event": "HitEnemy"
    },
    {
      "GUID": "0af585ef-0b91-476e-94d2-09e0dedd0ccb",
      "ID": "1722",
      "Facing": "Right",
      "Health": "1",
      "X": "2",
      "Y": "0",
      "Beat": "69",
      "Time": "30.44776",
      "Spawn": "60",
      "Vibe": "False",
      "Burning": "False",
      "Mysterious": "False",
      "Event": "HitEnemy"
    },
    {
      "GUID": "ff903434-565e-46dc-8253-74fea7877152",
      "ID": "1722",
      "Facing": "Right",
      "Health": "1",
      "X": "2",
      "Y": "0",
      "Beat": "71",
      "Time": "31.34328",
      "Spawn": "62",
      "Vibe": "False",
      "Burning": "False",
      "Mysterious": "False",
      "Event": "HitEnemy"
    },
    {
      "GUID": "01a1b5b1-9175-45aa-a19a-da0d0f00c927",
      "ID": "929",
      "Facing": "Left",
      "Health": "1",
      "X": "1",
      "Y": "3",
      "Beat": "72.99283",
      "Time": "32.2356",
      "Spawn": "67",
      "Vibe": "False",
      "Burning": "False",
      "Mysterious": "False",
      "Event": "BlademasterPrepare"
    },
    {
      "GUID": "466fb034-a8f7-4818-84a9-668a5caa4b02",
      "ID": "1722",
      "Facing": "Right",
      "Health": "1",
      "X": "1",
      "Y": "0",
      "Beat": "73",
      "Time": "32.23881",
      "Spawn": "64",
      "Vibe": "False",
      "Burning": "False",
      "Mysterious": "False",
      "Event": "HitEnemy"
    },
    {
      "GUID": "01a1b5b1-9175-45aa-a19a-da0d0f00c927",
      "ID": "929",
      "Facing": "Left",
      "Health": "1",
      "X": "1",
      "Y": "0",
      "Beat": "75",
      "Time": "33.13433",
      "Spawn": "67",
      "Vibe": "False",
      "Burning": "False",
      "Mysterious": "False",
      "Event": "HitEnemy"
    },
    {
      "GUID": "21aeb8dc-417c-4daf-8507-fdd247d1aae0",
      "ID": "1722",
      "Facing": "Right",
      "Health": "1",
      "X": "2",
      "Y": "0",
      "Beat": "77",
      "Time": "34.02985",
      "Spawn": "68",
      "Vibe": "False",
      "Burning": "False",
      "Mysterious": "False",
      "Event": "HitEnemy"
    },
    {
      "GUID": "516b8657-da15-413e-baaa-e44c1086f19e",
      "ID": "7358",
      "Facing": "Left",
      "Health": "1",
      "X": "2",
      "Y": "0",
      "Beat": "79",
      "Time": "34.92537",
      "Spawn": "70",
      "Vibe": "False",
      "Burning": "False",
      "Mysterious": "False",
      "Event": "HitEnemy"
    },
    {
      "GUID": "95b9e5be-6b5e-4544-8e90-ca4c57f010b2",
      "ID": "929",
      "Facing": "Left",
      "Health": "1",
      "X": "1",
      "Y": "3",
      "Beat": "80.99324",
      "Time": "35.81787",
      "Spawn": "75",
      "Vibe": "False",
      "Burning": "False",
      "Mysterious": "False",
      "Event": "BlademasterPrepare"
    },
    {
      "GUID": "4707d5ae-4ac1-4f02-8004-d3dbf3077990",
      "ID": "1722",
      "Facing": "Right",
      "Health": "1",
      "X": "1",
      "Y": "0",
      "Beat": "81",
      "Time": "35.8209",
      "Spawn": "72",
      "Vibe": "False",
      "Burning": "False",
      "Mysterious": "False",
      "Event": "HitEnemy"
    },
    {
      "GUID": "95b9e5be-6b5e-4544-8e90-ca4c57f010b2",
      "ID": "929",
      "Facing": "Left",
      "Health": "1",
      "X": "1",
      "Y": "0",
      "Beat": "83",
      "Time": "36.71642",
      "Spawn": "75",
      "Vibe": "False",
      "Burning": "False",
      "Mysterious": "False",
      "Event": "HitEnemy"
    },
    {
      "GUID": "1421efd5-a8f5-4274-aba1-9012ff1758bc",
      "ID": "1722",
      "Facing": "Right",
      "Health": "1",
      "X": "2",
      "Y": "0",
      "Beat": "85",
      "Time": "37.61194",
      "Spawn": "76",
      "Vibe": "False",
      "Burning": "False",
      "Mysterious": "False",
      "Event": "HitEnemy"
    },
    {
      "GUID": "0547bc05-2b24-49e4-bc4a-92453b6062e1",
      "ID": "1722",
      "Facing": "Right",
      "Health": "1",
      "X": "0",
      "Y": "0",
      "Beat": "85",
      "Time": "37.61194",
      "Spawn": "76",
      "Vibe": "False",
      "Burning": "False",
      "Mysterious": "False",
      "Event": "HitEnemy"
    },
    {
      "GUID": "4d1df35e-f3cc-419c-b3e8-75c659d75524",
      "ID": "911",
      "Facing": "Right",
      "Health": "3",
      "X": "1",
      "Y": "0",
      "Beat": "86",
      "Time": "38.0597",
      "Spawn": "77",
      "Vibe": "True",
      "Burning": "False",
      "Mysterious": "False",
      "Event": "HitEnemy"
    },
    {
      "GUID": "4d1df35e-f3cc-419c-b3e8-75c659d75524",
      "ID": "911",
      "Facing": "Left",
      "Health": "2",
      "X": "2",
      "Y": "0",
      "Beat": "87",
      "Time": "38.50746",
      "Spawn": "77",
      "Vibe": "True",
      "Burning": "False",
      "Mysterious": "False",
      "Event": "HitEnemy"
    },
    {
      "GUID": "4d1df35e-f3cc-419c-b3e8-75c659d75524",
      "ID": "911",
      "Facing": "Right",
      "Health": "1",
      "X": "1",
      "Y": "0",
      "Beat": "88",
      "Time": "38.95522",
      "Spawn": "77",
      "Vibe": "True",
      "Burning": "False",
      "Mysterious": "False",
      "Event": "HitEnemy"
    },
    {
      "GUID": "ad73fff7-c9b3-43b0-8dce-2fb8ddf5b711",
      "ID": "1722",
      "Facing": "Right",
      "Health": "1",
      "X": "0",
      "Y": "0",
      "Beat": "89",
      "Time": "39.40298",
      "Spawn": "80",
      "Vibe": "True",
      "Burning": "False",
      "Mysterious": "False",
      "Event": "HitEnemy"
    },
    {
      "GUID": "0363d282-ab0a-4417-aaca-bb0bbae7f18d",
      "ID": "1722",
      "Facing": "Right",
      "Health": "1",
      "X": "1",
      "Y": "0",
      "Beat": "91",
      "Time": "40.29851",
      "Spawn": "82",
      "Vibe": "True",
      "Burning": "False",
      "Mysterious": "False",
      "Event": "HitEnemy"
    },
    {
      "GUID": "f5f1dda6-b24b-4852-97cd-4baf2ab3453f",
      "ID": "1722",
      "Facing": "Right",
      "Health": "1",
      "X": "2",
      "Y": "0",
      "Beat": "93",
      "Time": "41.19403",
      "Spawn": "84",
      "Vibe": "True",
      "Burning": "False",
      "Mysterious": "False",
      "Event": "HitEnemy"
    },
    {
      "GUID": "24fecee5-1acd-43a2-9bdc-369e81778054",
      "ID": "1722",
      "Facing": "Right",
      "Health": "1",
      "X": "0",
      "Y": "0",
      "Beat": "95",
      "Time": "42.08955",
      "Spawn": "86",
      "Vibe": "True",
      "Burning": "False",
      "Mysterious": "False",
      "Event": "HitEnemy"
    },
    {
      "GUID": "cd7e6b04-4c18-4c14-9a9d-4890deae4abc",
      "ID": "1722",
      "Facing": "Right",
      "Health": "1",
      "X": "1",
      "Y": "0",
      "Beat": "97",
      "Time": "42.98507",
      "Spawn": "88",
      "Vibe": "True",
      "Burning": "False",
      "Mysterious": "False",
      "Event": "HitEnemy"
    },
    {
      "GUID": "ee9dd437-d854-4663-8649-373784e688b4",
      "ID": "1722",
      "Facing": "Right",
      "Health": "1",
      "X": "2",
      "Y": "0",
      "Beat": "99",
      "Time": "43.8806",
      "Spawn": "90",
      "Vibe": "True",
      "Burning": "False",
      "Mysterious": "False",
      "Event": "HitEnemy"
    },
    {
      "GUID": "44ade7c1-d915-473f-931a-fb47a73f458c",
      "ID": "1722",
      "Facing": "Right",
      "Health": "1",
      "X": "0",
      "Y": "0",
      "Beat": "101",
      "Time": "44.77612",
      "Spawn": "92",
      "Vibe": "True",
      "Burning": "False",
      "Mysterious": "False",
      "Event": "HitEnemy"
    },
    {
      "Event": "VCS",
      "Beat": "101.0164",
      "Time": "44.78345"
    },
    {
      "GUID": "6f07450f-8d11-4024-b260-d594f5780477",
      "ID": "1722",
      "Facing": "Right",
      "Health": "1",
      "X": "1",
      "Y": "0",
      "Beat": "103",
      "Time": "45.67164",
      "Spawn": "94",
      "Vibe": "False",
      "Burning": "False",
      "Mysterious": "False",
      "Event": "HitEnemy"
    },
    {
      "GUID": "2f6f31d7-3174-40aa-9ca2-705e713b5867",
      "ID": "1722",
      "Facing": "Right",
      "Health": "1",
      "X": "2",
      "Y": "0",
      "Beat": "105",
      "Time": "46.56717",
      "Spawn": "96",
      "Vibe": "False",
      "Burning": "False",
      "Mysterious": "False",
      "Event": "HitEnemy"
    },
    {
      "GUID": "b96865bd-34e1-4462-909d-053e33cbdb4b",
      "ID": "1722",
      "Facing": "Right",
      "Health": "1",
      "X": "0",
      "Y": "0",
      "Beat": "107",
      "Time": "47.46269",
      "Spawn": "98",
      "Vibe": "False",
      "Burning": "False",
      "Mysterious": "False",
      "Event": "HitEnemy"
    },
    {
      "GUID": "af8a2926-1d79-4924-98ae-33f5d2d57756",
      "ID": "1722",
      "Facing": "Right",
      "Health": "1",
      "X": "1",
      "Y": "0",
      "Beat": "109",
      "Time": "48.35821",
      "Spawn": "100",
      "Vibe": "False",
      "Burning": "False",
      "Mysterious": "False",
      "Event": "HitEnemy"
    },
    {
      "GUID": "c2fb53ee-85e4-40f1-bfc9-5407d4fc02c5",
      "ID": "1722",
      "Facing": "Right",
      "Health": "1",
      "X": "2",
      "Y": "0",
      "Beat": "111",
      "Time": "49.25373",
      "Spawn": "102",
      "Vibe": "False",
      "Burning": "False",
      "Mysterious": "False",
      "Event": "HitEnemy"
    },
    {
      "GUID": "42d88c9d-5782-4162-b06d-e5179a10e3af",
      "ID": "1722",
      "Facing": "Right",
      "Health": "1",
      "X": "0",
      "Y": "0",
      "Beat": "113",
      "Time": "50.14925",
      "Spawn": "104",
      "Vibe": "False",
      "Burning": "False",
      "Mysterious": "False",
      "Event": "HitEnemy"
    },
    {
      "GUID": "02a14ad7-db79-4db7-878f-49dd1e0b70c8",
      "ID": "1722",
      "Facing": "Right",
      "Health": "1",
      "X": "1",
      "Y": "0",
      "Beat": "115",
      "Time": "51.04478",
      "Spawn": "106",
      "Vibe": "False",
      "Burning": "False",
      "Mysterious": "False",
      "Event": "HitEnemy"
    },
    {
      "GUID": "008c6d28-9667-42da-b40a-c4dd33def910",
      "ID": "1722",
      "Facing": "Right",
      "Health": "1",
      "X": "2",
      "Y": "0",
      "Beat": "117",
      "Time": "51.9403",
      "Spawn": "108",
      "Vibe": "False",
      "Burning": "False",
      "Mysterious": "False",
      "Event": "HitEnemy"
    },
    {
      "GUID": "f1300ced-4881-494c-b98a-f11e3155222e",
      "ID": "1722",
      "Facing": "Right",
      "Health": "1",
      "X": "0",
      "Y": "0",
      "Beat": "117",
      "Time": "51.9403",
      "Spawn": "108",
      "Vibe": "False",
      "Burning": "False",
      "Mysterious": "False",
      "Event": "HitEnemy"
    },
    {
      "GUID": "ff99f089-86f4-4871-9f38-8458333dcf5e",
      "ID": "911",
      "Facing": "Left",
      "Health": "3",
      "X": "1",
      "Y": "0",
      "Beat": "118",
      "Time": "52.38806",
      "Spawn": "109",
      "Vibe": "False",
      "Burning": "False",
      "Mysterious": "False",
      "Event": "HitEnemy"
    },
    {
      "GUID": "ff99f089-86f4-4871-9f38-8458333dcf5e",
      "ID": "911",
      "Facing": "Right",
      "Health": "2",
      "X": "0",
      "Y": "0",
      "Beat": "119",
      "Time": "52.83582",
      "Spawn": "109",
      "Vibe": "False",
      "Burning": "False",
      "Mysterious": "False",
      "Event": "HitEnemy"
    },
    {
      "GUID": "ff99f089-86f4-4871-9f38-8458333dcf5e",
      "ID": "911",
      "Facing": "Left",
      "Health": "1",
      "X": "1",
      "Y": "0",
      "Beat": "120",
      "Time": "53.28358",
      "Spawn": "109",
      "Vibe": "False",
      "Burning": "False",
      "Mysterious": "False",
      "Event": "HitEnemy"
    },
    {
      "GUID": "400f768c-2233-45d1-be31-cc6b9b572108",
      "ID": "1722",
      "Facing": "Right",
      "Health": "1",
      "X": "2",
      "Y": "0",
      "Beat": "121",
      "Time": "53.73134",
      "Spawn": "112",
      "Vibe": "False",
      "Burning": "False",
      "Mysterious": "False",
      "Event": "HitEnemy"
    },
    {
      "GUID": "a05bd027-dfbf-44d2-a208-da5eb301315c",
      "ID": "1722",
      "Facing": "Right",
      "Health": "1",
      "X": "1",
      "Y": "0",
      "Beat": "123",
      "Time": "54.62687",
      "Spawn": "114",
      "Vibe": "False",
      "Burning": "False",
      "Mysterious": "False",
      "Event": "HitEnemy"
    },
    {
      "GUID": "0f8fb5cb-9125-47ed-99b2-50a67967c213",
      "ID": "1722",
      "Facing": "Right",
      "Health": "1",
      "X": "0",
      "Y": "0",
      "Beat": "125",
      "Time": "55.52239",
      "Spawn": "116",
      "Vibe": "False",
      "Burning": "False",
      "Mysterious": "False",
      "Event": "HitEnemy"
    },
    {
      "GUID": "f526fa1a-6758-4fc7-bef6-8a6454758b72",
      "ID": "1722",
      "Facing": "Right",
      "Health": "1",
      "X": "2",
      "Y": "0",
      "Beat": "127",
      "Time": "56.41791",
      "Spawn": "118",
      "Vibe": "False",
      "Burning": "False",
      "Mysterious": "False",
      "Event": "HitEnemy"
    },
    {
      "GUID": "bde8a8fd-28cc-4a4f-8a3a-2a84fb6a3db0",
      "ID": "1722",
      "Facing": "Right",
      "Health": "1",
      "X": "1",
      "Y": "0",
      "Beat": "129",
      "Time": "57.31343",
      "Spawn": "120",
      "Vibe": "False",
      "Burning": "False",
      "Mysterious": "False",
      "Event": "HitEnemy"
    },
    {
      "GUID": "e49288f6-10cd-4a17-acc5-6d81dde17f4e",
      "ID": "1722",
      "Facing": "Right",
      "Health": "1",
      "X": "0",
      "Y": "0",
      "Beat": "131",
      "Time": "58.20895",
      "Spawn": "122",
      "Vibe": "False",
      "Burning": "False",
      "Mysterious": "False",
      "Event": "HitEnemy"
    },
    {
      "GUID": "58de9f63-9182-4a11-880d-60acc3e43147",
      "ID": "1722",
      "Facing": "Right",
      "Health": "1",
      "X": "2",
      "Y": "0",
      "Beat": "133",
      "Time": "59.10448",
      "Spawn": "124",
      "Vibe": "False",
      "Burning": "False",
      "Mysterious": "False",
      "Event": "HitEnemy"
    },
    {
      "GUID": "57a88867-37e7-45d6-b2a8-c6d87ae75a8b",
      "ID": "1722",
      "Facing": "Right",
      "Health": "1",
      "X": "1",
      "Y": "0",
      "Beat": "135",
      "Time": "60",
      "Spawn": "126",
      "Vibe": "False",
      "Burning": "False",
      "Mysterious": "False",
      "Event": "HitEnemy"
    },
    {
      "GUID": "31cb9101-9214-41a3-91c9-13ecc0b8b4cf",
      "ID": "1722",
      "Facing": "Right",
      "Health": "1",
      "X": "0",
      "Y": "0",
      "Beat": "137",
      "Time": "60.89552",
      "Spawn": "128",
      "Vibe": "False",
      "Burning": "False",
      "Mysterious": "False",
      "Event": "HitEnemy"
    },
    {
      "GUID": "a08b0152-6234-4b03-b388-aa1c31dcd0f5",
      "ID": "1722",
      "Facing": "Right",
      "Health": "1",
      "X": "2",
      "Y": "0",
      "Beat": "139",
      "Time": "61.79105",
      "Spawn": "130",
      "Vibe": "False",
      "Burning": "False",
      "Mysterious": "False",
      "Event": "HitEnemy"
    },
    {
      "GUID": "334dc82d-e9ab-4ea2-a86c-4b7e1e212ec2",
      "ID": "1722",
      "Facing": "Right",
      "Health": "1",
      "X": "1",
      "Y": "0",
      "Beat": "141",
      "Time": "62.68657",
      "Spawn": "132",
      "Vibe": "False",
      "Burning": "False",
      "Mysterious": "False",
      "Event": "HitEnemy"
    },
    {
      "GUID": "17375a98-4d33-4959-a750-905a96f4c482",
      "ID": "1722",
      "Facing": "Right",
      "Health": "1",
      "X": "0",
      "Y": "0",
      "Beat": "143",
      "Time": "63.58209",
      "Spawn": "134",
      "Vibe": "False",
      "Burning": "False",
      "Mysterious": "False",
      "Event": "HitEnemy"
    },
    {
      "GUID": "04c238d4-939f-4790-9438-41314f72b66e",
      "ID": "1722",
      "Facing": "Right",
      "Health": "1",
      "X": "2",
      "Y": "0",
      "Beat": "145",
      "Time": "64.47762",
      "Spawn": "136",
      "Vibe": "False",
      "Burning": "False",
      "Mysterious": "False",
      "Event": "HitEnemy"
    },
    {
      "GUID": "10ad4e37-94dc-49b1-a4fe-a65f9cce4fad",
      "ID": "1722",
      "Facing": "Right",
      "Health": "1",
      "X": "1",
      "Y": "0",
      "Beat": "147",
      "Time": "65.37313",
      "Spawn": "138",
      "Vibe": "False",
      "Burning": "False",
      "Mysterious": "False",
      "Event": "HitEnemy"
    },
    {
      "GUID": "6b356aed-b5b4-425c-80db-cf4bde0dbfed",
      "ID": "1722",
      "Facing": "Right",
      "Health": "1",
      "X": "0",
      "Y": "0",
      "Beat": "149",
      "Time": "66.26865",
      "Spawn": "140",
      "Vibe": "False",
      "Burning": "False",
      "Mysterious": "False",
      "Event": "HitEnemy"
    },
    {
      "GUID": "ce810013-ad1d-422c-92c0-3cdda21e2b56",
      "ID": "1722",
      "Facing": "Right",
      "Health": "1",
      "X": "2",
      "Y": "0",
      "Beat": "151",
      "Time": "67.16418",
      "Spawn": "142",
      "Vibe": "False",
      "Burning": "False",
      "Mysterious": "False",
      "Event": "HitEnemy"
    },
    {
      "GUID": "977c8ead-e832-43b4-9d68-640de5d45fc6",
      "ID": "1722",
      "Facing": "Right",
      "Health": "1",
      "X": "1",
      "Y": "0",
      "Beat": "153",
      "Time": "68.0597",
      "Spawn": "144",
      "Vibe": "False",
      "Burning": "False",
      "Mysterious": "False",
      "Event": "HitEnemy"
    },
    {
      "GUID": "7e0537ea-cc70-4781-a561-78f1a85aa804",
      "ID": "1722",
      "Facing": "Right",
      "Health": "1",
      "X": "0",
      "Y": "0",
      "Beat": "155",
      "Time": "68.95522",
      "Spawn": "146",
      "Vibe": "False",
      "Burning": "False",
      "Mysterious": "False",
      "Event": "HitEnemy"
    },
    {
      "GUID": "6c44da9e-f21b-4b5d-9b7a-d1fe9d07c965",
      "ID": "1722",
      "Facing": "Right",
      "Health": "1",
      "X": "2",
      "Y": "0",
      "Beat": "157",
      "Time": "69.85075",
      "Spawn": "148",
      "Vibe": "False",
      "Burning": "False",
      "Mysterious": "False",
      "Event": "HitEnemy"
    },
    {
      "GUID": "ce03427d-521d-41df-99c0-e3f596cb6fa4",
      "ID": "1722",
      "Facing": "Right",
      "Health": "1",
      "X": "1",
      "Y": "0",
      "Beat": "159",
      "Time": "70.74627",
      "Spawn": "150",
      "Vibe": "False",
      "Burning": "False",
      "Mysterious": "False",
      "Event": "HitEnemy"
    },
    {
      "GUID": "fd36285a-2b56-40a0-97b4-01e2cfc2e4bd",
      "ID": "1722",
      "Facing": "Right",
      "Health": "1",
      "X": "0",
      "Y": "0",
      "Beat": "161",
      "Time": "71.64179",
      "Spawn": "152",
      "Vibe": "False",
      "Burning": "False",
      "Mysterious": "False",
      "Event": "HitEnemy"
    },
    {
      "GUID": "52ba2a0f-ca3c-416a-9aa0-3957b12f2a18",
      "ID": "1722",
      "Facing": "Right",
      "Health": "1",
      "X": "2",
      "Y": "0",
      "Beat": "163",
      "Time": "72.53732",
      "Spawn": "154",
      "Vibe": "False",
      "Burning": "False",
      "Mysterious": "False",
      "Event": "HitEnemy"
    },
    {
      "GUID": "c888c7af-acd0-462a-8f91-83f14d2462d7",
      "ID": "1722",
      "Facing": "Right",
      "Health": "1",
      "X": "1",
      "Y": "0",
      "Beat": "165",
      "Time": "73.43284",
      "Spawn": "156",
      "Vibe": "False",
      "Burning": "False",
      "Mysterious": "False",
      "Event": "HitEnemy"
    },
    {
      "GUID": "bc1bce39-c170-4714-a7ea-f3772fbc4aa0",
      "ID": "3211",
      "Facing": "Left",
      "Health": "4",
      "X": "0",
      "Y": "0",
      "Beat": "167",
      "Time": "74.32836",
      "Spawn": "158",
      "Vibe": "False",
      "Burning": "False",
      "Mysterious": "False",
      "Event": "HitEnemy"
    },
    {
      "GUID": "bc1bce39-c170-4714-a7ea-f3772fbc4aa0",
      "ID": "3211",
      "Facing": "Left",
      "Health": "3",
      "X": "0",
      "Y": "0",
      "Beat": "168",
      "Time": "74.77612",
      "Spawn": "158",
      "Vibe": "False",
      "Burning": "False",
      "Mysterious": "False",
      "Event": "HitEnemy"
    },
    {
      "GUID": "bc1bce39-c170-4714-a7ea-f3772fbc4aa0",
      "ID": "3211",
      "Facing": "Left",
      "Health": "2",
      "X": "0",
      "Y": "0",
      "Beat": "169",
      "Time": "75.22388",
      "Spawn": "158",
      "Vibe": "False",
      "Burning": "False",
      "Mysterious": "False",
      "Event": "HitEnemy"
    },
    {
      "GUID": "bc1bce39-c170-4714-a7ea-f3772fbc4aa0",
      "ID": "3211",
      "Facing": "Left",
      "Health": "1",
      "X": "0",
      "Y": "0",
      "Beat": "170",
      "Time": "75.67164",
      "Spawn": "158",
      "Vibe": "False",
      "Burning": "False",
      "Mysterious": "False",
      "Event": "HitEnemy"
    },
    {
      "GUID": "9b5674cd-0c32-4c40-b411-994ed4ffcf06",
      "ID": "4355",
      "Facing": "Right",
      "Health": "2",
      "X": "1",
      "Y": "0",
      "Beat": "173",
      "Time": "77.01492",
      "Spawn": "164",
      "Vibe": "False",
      "Burning": "False",
      "Mysterious": "False",
      "Event": "HitEnemy"
    },
    {
      "GUID": "9b5674cd-0c32-4c40-b411-994ed4ffcf06",
      "ID": "4355",
      "Facing": "Left",
      "Health": "1",
      "X": "1",
      "Y": "0",
      "Beat": "174",
      "Time": "77.46268",
      "Spawn": "164",
      "Vibe": "False",
      "Burning": "False",
      "Mysterious": "False",
      "Event": "HitEnemy"
    },
    {
      "GUID": "9822ef7a-27ea-477b-9bf2-bc6bea66251c",
      "ID": "4355",
      "Facing": "Right",
      "Health": "2",
      "X": "2",
      "Y": "0",
      "Beat": "177",
      "Time": "78.80597",
      "Spawn": "168",
      "Vibe": "False",
      "Burning": "False",
      "Mysterious": "False",
      "Event": "HitEnemy"
    },
    {
      "GUID": "9822ef7a-27ea-477b-9bf2-bc6bea66251c",
      "ID": "4355",
      "Facing": "Left",
      "Health": "1",
      "X": "2",
      "Y": "0",
      "Beat": "178",
      "Time": "79.25373",
      "Spawn": "168",
      "Vibe": "False",
      "Burning": "False",
      "Mysterious": "False",
      "Event": "HitEnemy"
    },
    {
      "GUID": "041b48e7-6c8f-4a2c-ab40-221c3d3f32ca",
      "ID": "4355",
      "Facing": "Right",
      "Health": "2",
      "X": "1",
      "Y": "0",
      "Beat": "181",
      "Time": "80.59702",
      "Spawn": "172",
      "Vibe": "False",
      "Burning": "False",
      "Mysterious": "False",
      "Event": "HitEnemy"
    },
    {
      "GUID": "041b48e7-6c8f-4a2c-ab40-221c3d3f32ca",
      "ID": "4355",
      "Facing": "Left",
      "Health": "1",
      "X": "1",
      "Y": "0",
      "Beat": "182",
      "Time": "81.04478",
      "Spawn": "172",
      "Vibe": "False",
      "Burning": "False",
      "Mysterious": "False",
      "Event": "HitEnemy"
    },
    {
      "GUID": "ba28efad-5ff0-4070-bf35-b5ed5dcce563",
      "ID": "4355",
      "Facing": "Right",
      "Health": "2",
      "X": "2",
      "Y": "0",
      "Beat": "185",
      "Time": "82.38806",
      "Spawn": "176",
      "Vibe": "False",
      "Burning": "False",
      "Mysterious": "False",
      "Event": "HitEnemy"
    },
    {
      "GUID": "ba28efad-5ff0-4070-bf35-b5ed5dcce563",
      "ID": "4355",
      "Facing": "Left",
      "Health": "1",
      "X": "2",
      "Y": "0",
      "Beat": "186",
      "Time": "82.83582",
      "Spawn": "176",
      "Vibe": "False",
      "Burning": "False",
      "Mysterious": "False",
      "Event": "HitEnemy"
    },
    {
      "GUID": "771763c9-682f-4cc0-929e-168cb2818aa9",
      "ID": "4355",
      "Facing": "Right",
      "Health": "2",
      "X": "1",
      "Y": "0",
      "Beat": "189",
      "Time": "84.17911",
      "Spawn": "180",
      "Vibe": "True",
      "Burning": "False",
      "Mysterious": "False",
      "Event": "HitEnemy"
    },
    {
      "GUID": "771763c9-682f-4cc0-929e-168cb2818aa9",
      "ID": "4355",
      "Facing": "Left",
      "Health": "1",
      "X": "1",
      "Y": "0",
      "Beat": "190",
      "Time": "84.62687",
      "Spawn": "180",
      "Vibe": "True",
      "Burning": "False",
      "Mysterious": "False",
      "Event": "HitEnemy"
    },
    {
      "GUID": "4920d6b7-eb8e-48d5-a16c-fd3faf348a95",
      "ID": "4355",
      "Facing": "Right",
      "Health": "2",
      "X": "2",
      "Y": "0",
      "Beat": "193",
      "Time": "85.97015",
      "Spawn": "184",
      "Vibe": "True",
      "Burning": "False",
      "Mysterious": "False",
      "Event": "HitEnemy"
    },
    {
      "GUID": "4920d6b7-eb8e-48d5-a16c-fd3faf348a95",
      "ID": "4355",
      "Facing": "Left",
      "Health": "1",
      "X": "2",
      "Y": "0",
      "Beat": "194",
      "Time": "86.41791",
      "Spawn": "184",
      "Vibe": "True",
      "Burning": "False",
      "Mysterious": "False",
      "Event": "HitEnemy"
    },
    {
      "GUID": "5e695f4c-8521-4e5d-9253-1d60d9b5e5bc",
      "ID": "1722",
      "Facing": "Right",
      "Health": "1",
      "X": "1",
      "Y": "0",
      "Beat": "197",
      "Time": "87.76119",
      "Spawn": "188",
      "Vibe": "True",
      "Burning": "False",
      "Mysterious": "False",
      "Event": "HitEnemy"
    },
    {
      "GUID": "a6609ed6-3ce2-4483-9183-e71f9dfb91df",
      "ID": "1722",
      "Facing": "Right",
      "Health": "1",
      "X": "0",
      "Y": "0",
      "Beat": "199",
      "Time": "88.65672",
      "Spawn": "190",
      "Vibe": "True",
      "Burning": "False",
      "Mysterious": "False",
      "Event": "HitEnemy"
    },
    {
      "GUID": "d46c4591-5d2c-4bde-91aa-7298cbf3ee35",
      "ID": "1722",
      "Facing": "Right",
      "Health": "1",
      "X": "1",
      "Y": "0",
      "Beat": "201",
      "Time": "89.55224",
      "Spawn": "192",
      "Vibe": "True",
      "Burning": "False",
      "Mysterious": "False",
      "Event": "HitEnemy"
    },
    {
      "GUID": "fd7ec033-3e01-4f79-a89e-d25b9891715c",
      "ID": "1722",
      "Facing": "Right",
      "Health": "1",
      "X": "2",
      "Y": "0",
      "Beat": "203",
      "Time": "90.44776",
      "Spawn": "194",
      "Vibe": "True",
      "Burning": "False",
      "Mysterious": "False",
      "Event": "HitEnemy"
    },
    {
      "GUID": "f5688d0f-6cf4-445d-9784-453c7f58b1c4",
      "ID": "1722",
      "Facing": "Right",
      "Health": "1",
      "X": "0",
      "Y": "0",
      "Beat": "203",
      "Time": "90.44776",
      "Spawn": "194",
      "Vibe": "True",
      "Burning": "False",
      "Mysterious": "False",
      "Event": "HitEnemy"
    },
    {
      "Event": "VCS",
      "Beat": "203.0027",
      "Time": "90.44897"
    },
    {
      "GUID": "2b144d02-1809-4a4a-91f4-fc9bd92a56f7",
      "ID": "4355",
      "Facing": "Right",
      "Health": "2",
      "X": "1",
      "Y": "0",
      "Beat": "205",
      "Time": "91.34328",
      "Spawn": "196",
      "Vibe": "False",
      "Burning": "False",
      "Mysterious": "False",
      "Event": "HitEnemy"
    },
    {
      "GUID": "49485482-3aaf-42ff-ac3d-7e814fc3fa41",
      "ID": "929",
      "Facing": "Left",
      "Health": "1",
      "X": "1",
      "Y": "3",
      "Beat": "205.9825",
      "Time": "91.7832",
      "Spawn": "200",
      "Vibe": "False",
      "Burning": "False",
      "Mysterious": "False",
      "Event": "BlademasterPrepare"
    },
    {
      "GUID": "2b144d02-1809-4a4a-91f4-fc9bd92a56f7",
      "ID": "4355",
      "Facing": "Left",
      "Health": "1",
      "X": "1",
      "Y": "0",
      "Beat": "206",
      "Time": "91.79105",
      "Spawn": "196",
      "Vibe": "False",
      "Burning": "False",
      "Mysterious": "False",
      "Event": "HitEnemy"
    },
    {
      "GUID": "49485482-3aaf-42ff-ac3d-7e814fc3fa41",
      "ID": "929",
      "Facing": "Left",
      "Health": "1",
      "X": "1",
      "Y": "0",
      "Beat": "208",
      "Time": "92.68657",
      "Spawn": "200",
      "Vibe": "False",
      "Burning": "False",
      "Mysterious": "False",
      "Event": "HitEnemy"
    },
    {
      "GUID": "6c862630-c6f6-4f98-b9fc-31ce6044355a",
      "ID": "4355",
      "Facing": "Right",
      "Health": "2",
      "X": "0",
      "Y": "0",
      "Beat": "209",
      "Time": "93.13433",
      "Spawn": "200",
      "Vibe": "False",
      "Burning": "False",
      "Mysterious": "False",
      "Event": "HitEnemy"
    },
    {
      "GUID": "6c862630-c6f6-4f98-b9fc-31ce6044355a",
      "ID": "4355",
      "Facing": "Left",
      "Health": "1",
      "X": "0",
      "Y": "0",
      "Beat": "210",
      "Time": "93.58209",
      "Spawn": "200",
      "Vibe": "False",
      "Burning": "False",
      "Mysterious": "False",
      "Event": "HitEnemy"
    },
    {
      "GUID": "bcee1387-7c3b-4764-87ab-1de3fe3abf48",
      "ID": "1722",
      "Facing": "Right",
      "Health": "1",
      "X": "0",
      "Y": "0",
      "Beat": "212",
      "Time": "94.47762",
      "Spawn": "203",
      "Vibe": "False",
      "Burning": "False",
      "Mysterious": "False",
      "Event": "HitEnemy"
    },
    {
      "GUID": "fd0f9fa6-b217-421f-bc51-f7b223efce67",
      "ID": "4355",
      "Facing": "Right",
      "Health": "2",
      "X": "1",
      "Y": "0",
      "Beat": "213",
      "Time": "94.92538",
      "Spawn": "204",
      "Vibe": "False",
      "Burning": "False",
      "Mysterious": "False",
      "Event": "HitEnemy"
    },
    {
      "GUID": "c72e0e49-7565-4a8f-8c5b-4b8b0d52ccd8",
      "ID": "929",
      "Facing": "Left",
      "Health": "1",
      "X": "1",
      "Y": "3",
      "Beat": "213.9818",
      "Time": "95.36499",
      "Spawn": "208",
      "Vibe": "False",
      "Burning": "False",
      "Mysterious": "False",
      "Event": "BlademasterPrepare"
    },
    {
      "GUID": "fd0f9fa6-b217-421f-bc51-f7b223efce67",
      "ID": "4355",
      "Facing": "Left",
      "Health": "1",
      "X": "1",
      "Y": "0",
      "Beat": "214",
      "Time": "95.37313",
      "Spawn": "204",
      "Vibe": "False",
      "Burning": "False",
      "Mysterious": "False",
      "Event": "HitEnemy"
    },
    {
      "GUID": "c72e0e49-7565-4a8f-8c5b-4b8b0d52ccd8",
      "ID": "929",
      "Facing": "Left",
      "Health": "1",
      "X": "1",
      "Y": "0",
      "Beat": "216",
      "Time": "96.26865",
      "Spawn": "208",
      "Vibe": "False",
      "Burning": "False",
      "Mysterious": "False",
      "Event": "HitEnemy"
    },
    {
      "GUID": "aa1ffd00-a46b-46a5-b627-291d6b527200",
      "ID": "4355",
      "Facing": "Right",
      "Health": "2",
      "X": "0",
      "Y": "0",
      "Beat": "217",
      "Time": "96.71642",
      "Spawn": "208",
      "Vibe": "False",
      "Burning": "False",
      "Mysterious": "False",
      "Event": "HitEnemy"
    },
    {
      "GUID": "aa1ffd00-a46b-46a5-b627-291d6b527200",
      "ID": "4355",
      "Facing": "Left",
      "Health": "1",
      "X": "0",
      "Y": "0",
      "Beat": "218",
      "Time": "97.16418",
      "Spawn": "208",
      "Vibe": "False",
      "Burning": "False",
      "Mysterious": "False",
      "Event": "HitEnemy"
    },
    {
      "GUID": "c765f276-5aef-4d49-b501-fbe2dca643a7",
      "ID": "1722",
      "Facing": "Right",
      "Health": "1",
      "X": "0",
      "Y": "0",
      "Beat": "220",
      "Time": "98.0597",
      "Spawn": "211",
      "Vibe": "False",
      "Burning": "False",
      "Mysterious": "False",
      "Event": "HitEnemy"
    },
    {
      "GUID": "e2929078-d572-4283-8fa5-8f743957ac81",
      "ID": "4355",
      "Facing": "Right",
      "Health": "2",
      "X": "1",
      "Y": "0",
      "Beat": "221",
      "Time": "98.50746",
      "Spawn": "212",
      "Vibe": "False",
      "Burning": "False",
      "Mysterious": "False",
      "Event": "HitEnemy"
    },
    {
      "GUID": "03dc77a7-b4e3-46e6-ac6a-b7843b4b89a0",
      "ID": "929",
      "Facing": "Left",
      "Health": "1",
      "X": "1",
      "Y": "3",
      "Beat": "221.9866",
      "Time": "98.94922",
      "Spawn": "216",
      "Vibe": "False",
      "Burning": "False",
      "Mysterious": "False",
      "Event": "BlademasterPrepare"
    },
    {
      "GUID": "e2929078-d572-4283-8fa5-8f743957ac81",
      "ID": "4355",
      "Facing": "Left",
      "Health": "1",
      "X": "1",
      "Y": "0",
      "Beat": "222",
      "Time": "98.95522",
      "Spawn": "212",
      "Vibe": "False",
      "Burning": "False",
      "Mysterious": "False",
      "Event": "HitEnemy"
    },
    {
      "GUID": "03dc77a7-b4e3-46e6-ac6a-b7843b4b89a0",
      "ID": "929",
      "Facing": "Left",
      "Health": "1",
      "X": "1",
      "Y": "0",
      "Beat": "224",
      "Time": "99.85075",
      "Spawn": "216",
      "Vibe": "False",
      "Burning": "False",
      "Mysterious": "False",
      "Event": "HitEnemy"
    },
    {
      "GUID": "a831736f-f214-4d25-aa5b-b0295cba7818",
      "ID": "4355",
      "Facing": "Right",
      "Health": "2",
      "X": "0",
      "Y": "0",
      "Beat": "225",
      "Time": "100.2985",
      "Spawn": "216",
      "Vibe": "False",
      "Burning": "False",
      "Mysterious": "False",
      "Event": "HitEnemy"
    },
    {
      "GUID": "a831736f-f214-4d25-aa5b-b0295cba7818",
      "ID": "4355",
      "Facing": "Left",
      "Health": "1",
      "X": "0",
      "Y": "0",
      "Beat": "226",
      "Time": "100.7463",
      "Spawn": "216",
      "Vibe": "False",
      "Burning": "False",
      "Mysterious": "False",
      "Event": "HitEnemy"
    },
    {
      "GUID": "a870a501-cfed-4d89-83e5-51b5085ab888",
      "ID": "1722",
      "Facing": "Right",
      "Health": "1",
      "X": "0",
      "Y": "0",
      "Beat": "228",
      "Time": "101.6418",
      "Spawn": "219",
      "Vibe": "False",
      "Burning": "False",
      "Mysterious": "False",
      "Event": "HitEnemy"
    },
    {
      "GUID": "db8126d3-7372-480b-8c17-9d82fd87e2ad",
      "ID": "4355",
      "Facing": "Right",
      "Health": "2",
      "X": "1",
      "Y": "0",
      "Beat": "229",
      "Time": "102.0896",
      "Spawn": "220",
      "Vibe": "False",
      "Burning": "False",
      "Mysterious": "False",
      "Event": "HitEnemy"
    },
    {
      "GUID": "2c8c7ac5-ea45-40f9-8df9-eb5961714759",
      "ID": "929",
      "Facing": "Left",
      "Health": "1",
      "X": "1",
      "Y": "3",
      "Beat": "229.9919",
      "Time": "102.5337",
      "Spawn": "224",
      "Vibe": "False",
      "Burning": "False",
      "Mysterious": "False",
      "Event": "BlademasterPrepare"
    },
    {
      "GUID": "db8126d3-7372-480b-8c17-9d82fd87e2ad",
      "ID": "4355",
      "Facing": "Left",
      "Health": "1",
      "X": "1",
      "Y": "0",
      "Beat": "230",
      "Time": "102.5373",
      "Spawn": "220",
      "Vibe": "False",
      "Burning": "False",
      "Mysterious": "False",
      "Event": "HitEnemy"
    },
    {
      "GUID": "2c8c7ac5-ea45-40f9-8df9-eb5961714759",
      "ID": "929",
      "Facing": "Left",
      "Health": "1",
      "X": "1",
      "Y": "0",
      "Beat": "232",
      "Time": "103.4328",
      "Spawn": "224",
      "Vibe": "False",
      "Burning": "False",
      "Mysterious": "False",
      "Event": "HitEnemy"
    },
    {
      "GUID": "99a5d375-3931-46ef-b148-eb9e3696e14d",
      "ID": "4355",
      "Facing": "Right",
      "Health": "2",
      "X": "0",
      "Y": "0",
      "Beat": "233",
      "Time": "103.8806",
      "Spawn": "224",
      "Vibe": "False",
      "Burning": "False",
      "Mysterious": "False",
      "Event": "HitEnemy"
    },
    {
      "GUID": "99a5d375-3931-46ef-b148-eb9e3696e14d",
      "ID": "4355",
      "Facing": "Left",
      "Health": "1",
      "X": "0",
      "Y": "0",
      "Beat": "234",
      "Time": "104.3284",
      "Spawn": "224",
      "Vibe": "False",
      "Burning": "False",
      "Mysterious": "False",
      "Event": "HitEnemy"
    },
    {
      "GUID": "dbed6b6d-f848-4ee2-9dd0-8f45ab27581a",
      "ID": "8675309",
      "Facing": "Right",
      "Health": "2",
      "X": "1",
      "Y": "0",
      "Beat": "237",
      "Time": "105.6716",
      "Spawn": "228",
      "Vibe": "False",
      "Burning": "False",
      "Mysterious": "False",
      "Event": "HitEnemy"
    },
    {
      "GUID": "dbed6b6d-f848-4ee2-9dd0-8f45ab27581a",
      "ID": "8675309",
      "Facing": "Right",
      "Health": "1",
      "X": "2",
      "Y": "0",
      "Beat": "238",
      "Time": "106.1194",
      "Spawn": "228",
      "Vibe": "False",
      "Burning": "False",
      "Mysterious": "False",
      "Event": "HitEnemy"
    },
    {
      "GUID": "c6139120-ce73-47f6-8d47-b601284bfd62",
      "ID": "8675309",
      "Facing": "Right",
      "Health": "2",
      "X": "1",
      "Y": "0",
      "Beat": "241",
      "Time": "107.4627",
      "Spawn": "232",
      "Vibe": "False",
      "Burning": "False",
      "Mysterious": "False",
      "Event": "HitEnemy"
    },
    {
      "GUID": "c6139120-ce73-47f6-8d47-b601284bfd62",
      "ID": "8675309",
      "Facing": "Right",
      "Health": "1",
      "X": "2",
      "Y": "0",
      "Beat": "242",
      "Time": "107.9104",
      "Spawn": "232",
      "Vibe": "False",
      "Burning": "False",
      "Mysterious": "False",
      "Event": "HitEnemy"
    },
    {
      "GUID": "e5f21248-cb2b-4912-9f26-a3274203ed1e",
      "ID": "8675309",
      "Facing": "Right",
      "Health": "2",
      "X": "1",
      "Y": "0",
      "Beat": "245",
      "Time": "109.2537",
      "Spawn": "236",
      "Vibe": "False",
      "Burning": "False",
      "Mysterious": "False",
      "Event": "HitEnemy"
    },
    {
      "GUID": "e5f21248-cb2b-4912-9f26-a3274203ed1e",
      "ID": "8675309",
      "Facing": "Right",
      "Health": "1",
      "X": "2",
      "Y": "0",
      "Beat": "246",
      "Time": "109.7015",
      "Spawn": "236",
      "Vibe": "False",
      "Burning": "False",
      "Mysterious": "False",
      "Event": "HitEnemy"
    },
    {
      "GUID": "5cfd4a86-9542-42f0-8ac0-c3896ab8c3cd",
      "ID": "911",
      "Facing": "Left",
      "Health": "3",
      "X": "2",
      "Y": "0",
      "Beat": "249",
      "Time": "111.0448",
      "Spawn": "240",
      "Vibe": "False",
      "Burning": "False",
      "Mysterious": "False",
      "Event": "HitEnemy"
    },
    {
      "GUID": "5cfd4a86-9542-42f0-8ac0-c3896ab8c3cd",
      "ID": "911",
      "Facing": "Right",
      "Health": "2",
      "X": "1",
      "Y": "0",
      "Beat": "250",
      "Time": "111.4925",
      "Spawn": "240",
      "Vibe": "False",
      "Burning": "False",
      "Mysterious": "False",
      "Event": "HitEnemy"
    },
    {
      "GUID": "5cfd4a86-9542-42f0-8ac0-c3896ab8c3cd",
      "ID": "911",
      "Facing": "Left",
      "Health": "1",
      "X": "2",
      "Y": "0",
      "Beat": "251",
      "Time": "111.9403",
      "Spawn": "240",
      "Vibe": "False",
      "Burning": "False",
      "Mysterious": "False",
      "Event": "HitEnemy"
    },
    {
      "GUID": "3b62da39-eca8-42b9-a8fd-62751376d89a",
      "ID": "8675309",
      "Facing": "Right",
      "Health": "2",
      "X": "0",
      "Y": "0",
      "Beat": "253",
      "Time": "112.8358",
      "Spawn": "244",
      "Vibe": "False",
      "Burning": "False",
      "Mysterious": "False",
      "Event": "HitEnemy"
    },
    {
      "GUID": "3b62da39-eca8-42b9-a8fd-62751376d89a",
      "ID": "8675309",
      "Facing": "Right",
      "Health": "1",
      "X": "1",
      "Y": "0",
      "Beat": "254",
      "Time": "113.2836",
      "Spawn": "244",
      "Vibe": "False",
      "Burning": "False",
      "Mysterious": "False",
      "Event": "HitEnemy"
    },
    {
      "GUID": "328d0aa4-22f4-42c9-ab8a-795f9525ba1a",
      "ID": "8675309",
      "Facing": "Right",
      "Health": "2",
      "X": "0",
      "Y": "0",
      "Beat": "257",
      "Time": "114.6269",
      "Spawn": "248",
      "Vibe": "False",
      "Burning": "False",
      "Mysterious": "False",
      "Event": "HitEnemy"
    },
    {
      "GUID": "328d0aa4-22f4-42c9-ab8a-795f9525ba1a",
      "ID": "8675309",
      "Facing": "Right",
      "Health": "1",
      "X": "1",
      "Y": "0",
      "Beat": "258",
      "Time": "115.0746",
      "Spawn": "248",
      "Vibe": "False",
      "Burning": "False",
      "Mysterious": "False",
      "Event": "HitEnemy"
    },
    {
      "GUID": "6a113019-b439-4b72-9e7a-b0bf8dc8ab84",
      "ID": "8675309",
      "Facing": "Right",
      "Health": "2",
      "X": "0",
      "Y": "0",
      "Beat": "261",
      "Time": "116.4179",
      "Spawn": "252",
      "Vibe": "False",
      "Burning": "False",
      "Mysterious": "False",
      "Event": "HitEnemy"
    },
    {
      "GUID": "6a113019-b439-4b72-9e7a-b0bf8dc8ab84",
      "ID": "8675309",
      "Facing": "Right",
      "Health": "1",
      "X": "1",
      "Y": "0",
      "Beat": "262",
      "Time": "116.8657",
      "Spawn": "252",
      "Vibe": "False",
      "Burning": "False",
      "Mysterious": "False",
      "Event": "HitEnemy"
    },
    {
      "GUID": "95142e6c-71fa-441c-9a29-7a9c0a531c59",
      "ID": "8675309",
      "Facing": "Right",
      "Health": "2",
      "X": "0",
      "Y": "0",
      "Beat": "265",
      "Time": "118.209",
      "Spawn": "256",
      "Vibe": "False",
      "Burning": "False",
      "Mysterious": "False",
      "Event": "HitEnemy"
    },
    {
      "GUID": "95142e6c-71fa-441c-9a29-7a9c0a531c59",
      "ID": "8675309",
      "Facing": "Right",
      "Health": "1",
      "X": "1",
      "Y": "0",
      "Beat": "266",
      "Time": "118.6567",
      "Spawn": "256",
      "Vibe": "False",
      "Burning": "False",
      "Mysterious": "False",
      "Event": "HitEnemy"
    },
    {
      "GUID": "314f1ccb-e3ed-4362-a57f-bb935568036d",
      "ID": "8675309",
      "Facing": "Left",
      "Health": "2",
      "X": "2",
      "Y": "0",
      "Beat": "268",
      "Time": "119.5522",
      "Spawn": "259",
      "Vibe": "False",
      "Burning": "False",
      "Mysterious": "False",
      "Event": "HitEnemy"
    },
    {
      "GUID": "314f1ccb-e3ed-4362-a57f-bb935568036d",
      "ID": "8675309",
      "Facing": "Left",
      "Health": "1",
      "X": "1",
      "Y": "0",
      "Beat": "269",
      "Time": "120",
      "Spawn": "259",
      "Vibe": "False",
      "Burning": "False",
      "Mysterious": "False",
      "Event": "HitEnemy"
    },
    {
      "GUID": "0e79e666-b689-43c4-adb4-e40f0fbcd5ad",
      "ID": "8675309",
      "Facing": "Left",
      "Health": "2",
      "X": "2",
      "Y": "0",
      "Beat": "272",
      "Time": "121.3433",
      "Spawn": "263",
      "Vibe": "False",
      "Burning": "False",
      "Mysterious": "False",
      "Event": "HitEnemy"
    },
    {
      "GUID": "0e79e666-b689-43c4-adb4-e40f0fbcd5ad",
      "ID": "8675309",
      "Facing": "Left",
      "Health": "1",
      "X": "1",
      "Y": "0",
      "Beat": "273",
      "Time": "121.791",
      "Spawn": "263",
      "Vibe": "False",
      "Burning": "False",
      "Mysterious": "False",
      "Event": "HitEnemy"
    },
    {
      "GUID": "6efaa8d8-1e4d-4b33-8a0a-2ea087e863e5",
      "ID": "8675309",
      "Facing": "Left",
      "Health": "2",
      "X": "1",
      "Y": "0",
      "Beat": "275",
      "Time": "122.6866",
      "Spawn": "266",
      "Vibe": "False",
      "Burning": "False",
      "Mysterious": "False",
      "Event": "HitEnemy"
    },
    {
      "GUID": "6efaa8d8-1e4d-4b33-8a0a-2ea087e863e5",
      "ID": "8675309",
      "Facing": "Left",
      "Health": "1",
      "X": "0",
      "Y": "0",
      "Beat": "276",
      "Time": "123.1343",
      "Spawn": "266",
      "Vibe": "False",
      "Burning": "False",
      "Mysterious": "False",
      "Event": "HitEnemy"
    },
    {
      "GUID": "281b8397-7f20-48be-a39d-51ee3e8adf8e",
      "ID": "7358",
      "Facing": "Left",
      "Health": "1",
      "X": "1",
      "Y": "0",
      "Beat": "278",
      "Time": "124.0299",
      "Spawn": "269",
      "Vibe": "False",
      "Burning": "False",
      "Mysterious": "False",
      "Event": "HitEnemy"
    },
    {
      "GUID": "887210f0-6997-418c-b202-e0e4838b0473",
      "ID": "1722",
      "Facing": "Right",
      "Health": "1",
      "X": "2",
      "Y": "0",
      "Beat": "280",
      "Time": "124.9254",
      "Spawn": "271",
      "Vibe": "False",
      "Burning": "False",
      "Mysterious": "False",
      "Event": "HitEnemy"
    },
    {
      "GUID": "0021b1f6-53f1-4fd7-9795-9368e3293521",
      "ID": "7358",
      "Facing": "Left",
      "Health": "1",
      "X": "1",
      "Y": "0",
      "Beat": "281",
      "Time": "125.3731",
      "Spawn": "272",
      "Vibe": "False",
      "Burning": "False",
      "Mysterious": "False",
      "Event": "HitEnemy"
    },
    {
      "GUID": "34973499-f8c9-4b63-9db0-946f71934458",
      "ID": "1722",
      "Facing": "Right",
      "Health": "1",
      "X": "0",
      "Y": "0",
      "Beat": "283",
      "Time": "126.2687",
      "Spawn": "274",
      "Vibe": "False",
      "Burning": "False",
      "Mysterious": "False",
      "Event": "HitEnemy"
    },
    {
      "GUID": "09c0b30a-d059-4cea-9561-7a8e9a8b65d7",
      "ID": "1722",
      "Facing": "Right",
      "Health": "1",
      "X": "1",
      "Y": "0",
      "Beat": "285",
      "Time": "127.1642",
      "Spawn": "276",
      "Vibe": "False",
      "Burning": "False",
      "Mysterious": "False",
      "Event": "HitEnemy"
    },
    {
      "GUID": "49995862-765f-491b-98eb-2ea647c81442",
      "ID": "1722",
      "Facing": "Right",
      "Health": "1",
      "X": "2",
      "Y": "0",
      "Beat": "289",
      "Time": "128.9552",
      "Spawn": "280",
      "Vibe": "False",
      "Burning": "False",
      "Mysterious": "False",
      "Event": "HitEnemy"
    },
    {
      "GUID": "159f73d9-5655-44bf-a54e-8276d548ec4c",
      "ID": "1722",
      "Facing": "Right",
      "Health": "1",
      "X": "1",
      "Y": "0",
      "Beat": "291",
      "Time": "129.8508",
      "Spawn": "282",
      "Vibe": "False",
      "Burning": "False",
      "Mysterious": "False",
      "Event": "HitEnemy"
    },
    {
      "GUID": "8f99f0f5-cc06-47a8-b9e8-e7df1c5aafbf",
      "ID": "1722",
      "Facing": "Right",
      "Health": "1",
      "X": "0",
      "Y": "0",
      "Beat": "293",
      "Time": "130.7463",
      "Spawn": "284",
      "Vibe": "False",
      "Burning": "False",
      "Mysterious": "False",
      "Event": "HitEnemy"
    },
    {
      "GUID": "0630a221-6466-4aa3-bd68-d7b612498418",
      "ID": "8675309",
      "Facing": "Left",
      "Health": "2",
      "X": "1",
      "Y": "0",
      "Beat": "297",
      "Time": "132.5373",
      "Spawn": "288",
      "Vibe": "False",
      "Burning": "False",
      "Mysterious": "False",
      "Event": "HitEnemy"
    },
    {
      "GUID": "0630a221-6466-4aa3-bd68-d7b612498418",
      "ID": "8675309",
      "Facing": "Left",
      "Health": "1",
      "X": "0",
      "Y": "0",
      "Beat": "298",
      "Time": "132.9851",
      "Spawn": "288",
      "Vibe": "False",
      "Burning": "False",
      "Mysterious": "False",
      "Event": "HitEnemy"
    },
    {
      "GUID": "629250e0-fe2e-4177-a72f-084ea17f5d28",
      "ID": "8675309",
      "Facing": "Right",
      "Health": "2",
      "X": "0",
      "Y": "0",
      "Beat": "300",
      "Time": "133.8806",
      "Spawn": "291",
      "Vibe": "False",
      "Burning": "False",
      "Mysterious": "False",
      "Event": "HitEnemy"
    },
    {
      "GUID": "629250e0-fe2e-4177-a72f-084ea17f5d28",
      "ID": "8675309",
      "Facing": "Right",
      "Health": "1",
      "X": "1",
      "Y": "0",
      "Beat": "301",
      "Time": "134.3284",
      "Spawn": "291",
      "Vibe": "False",
      "Burning": "False",
      "Mysterious": "False",
      "Event": "HitEnemy"
    },
    {
      "GUID": "fc6091b7-86cd-4809-b2c9-1164c4f5aff3",
      "ID": "1722",
      "Facing": "Right",
      "Health": "1",
      "X": "0",
      "Y": "0",
      "Beat": "303",
      "Time": "135.2239",
      "Spawn": "294",
      "Vibe": "False",
      "Burning": "False",
      "Mysterious": "False",
      "Event": "HitEnemy"
    },
    {
      "GUID": "88af9900-73de-41e8-855b-181319a14f81",
      "ID": "1722",
      "Facing": "Right",
      "Health": "1",
      "X": "1",
      "Y": "0",
      "Beat": "305",
      "Time": "136.1194",
      "Spawn": "296",
      "Vibe": "False",
      "Burning": "False",
      "Mysterious": "False",
      "Event": "HitEnemy"
    },
    {
      "GUID": "14d64307-70b3-4df2-9761-db63afedc9f9",
      "ID": "1722",
      "Facing": "Right",
      "Health": "1",
      "X": "2",
      "Y": "0",
      "Beat": "307",
      "Time": "137.0149",
      "Spawn": "298",
      "Vibe": "False",
      "Burning": "False",
      "Mysterious": "False",
      "Event": "HitEnemy"
    },
    {
      "GUID": "e4e8e330-1473-485b-9e24-764b19588a4f",
      "ID": "1722",
      "Facing": "Right",
      "Health": "1",
      "X": "1",
      "Y": "0",
      "Beat": "309",
      "Time": "137.9104",
      "Spawn": "300",
      "Vibe": "False",
      "Burning": "False",
      "Mysterious": "False",
      "Event": "HitEnemy"
    },
    {
      "GUID": "66de7900-a753-4221-98f4-19ad112c60d2",
      "ID": "1722",
      "Facing": "Right",
      "Health": "1",
      "X": "0",
      "Y": "0",
      "Beat": "311",
      "Time": "138.806",
      "Spawn": "302",
      "Vibe": "False",
      "Burning": "False",
      "Mysterious": "False",
      "Event": "HitEnemy"
    },
    {
      "GUID": "f8c50b91-5d2e-48b0-a5a4-9111bc0d0967",
      "ID": "4355",
      "Facing": "Right",
      "Health": "2",
      "X": "1",
      "Y": "0",
      "Beat": "313",
      "Time": "139.7015",
      "Spawn": "304",
      "Vibe": "True",
      "Burning": "False",
      "Mysterious": "False",
      "Event": "HitEnemy"
    },
    {
      "GUID": "f693848b-711c-47fd-bea3-a1bdc5d8703a",
      "ID": "929",
      "Facing": "Left",
      "Health": "1",
      "X": "1",
      "Y": "3",
      "Beat": "313.9976",
      "Time": "140.1482",
      "Spawn": "308",
      "Vibe": "True",
      "Burning": "False",
      "Mysterious": "False",
      "Event": "BlademasterPrepare"
    },
    {
      "GUID": "f8c50b91-5d2e-48b0-a5a4-9111bc0d0967",
      "ID": "4355",
      "Facing": "Left",
      "Health": "1",
      "X": "1",
      "Y": "0",
      "Beat": "314",
      "Time": "140.1492",
      "Spawn": "304",
      "Vibe": "True",
      "Burning": "False",
      "Mysterious": "False",
      "Event": "HitEnemy"
    },
    {
      "GUID": "f693848b-711c-47fd-bea3-a1bdc5d8703a",
      "ID": "929",
      "Facing": "Left",
      "Health": "1",
      "X": "1",
      "Y": "0",
      "Beat": "316",
      "Time": "141.0448",
      "Spawn": "308",
      "Vibe": "True",
      "Burning": "False",
      "Mysterious": "False",
      "Event": "HitEnemy"
    },
    {
      "GUID": "ff4109fc-bb4e-4e09-a755-d9a6a4bfadc0",
      "ID": "4355",
      "Facing": "Right",
      "Health": "2",
      "X": "2",
      "Y": "0",
      "Beat": "317",
      "Time": "141.4925",
      "Spawn": "308",
      "Vibe": "True",
      "Burning": "False",
      "Mysterious": "False",
      "Event": "HitEnemy"
    },
    {
      "GUID": "ff4109fc-bb4e-4e09-a755-d9a6a4bfadc0",
      "ID": "4355",
      "Facing": "Left",
      "Health": "1",
      "X": "2",
      "Y": "0",
      "Beat": "318",
      "Time": "141.9403",
      "Spawn": "308",
      "Vibe": "True",
      "Burning": "False",
      "Mysterious": "False",
      "Event": "HitEnemy"
    },
    {
      "GUID": "c2f47fe2-bdae-45ee-959e-f27c14a37ae6",
      "ID": "1722",
      "Facing": "Right",
      "Health": "1",
      "X": "2",
      "Y": "0",
      "Beat": "320",
      "Time": "142.8358",
      "Spawn": "311",
      "Vibe": "True",
      "Burning": "False",
      "Mysterious": "False",
      "Event": "HitEnemy"
    },
    {
      "GUID": "f5aeb857-e59d-4715-92ec-3763635e2857",
      "ID": "4355",
      "Facing": "Right",
      "Health": "2",
      "X": "1",
      "Y": "0",
      "Beat": "321",
      "Time": "143.2836",
      "Spawn": "312",
      "Vibe": "True",
      "Burning": "False",
      "Mysterious": "False",
      "Event": "HitEnemy"
    },
    {
      "GUID": "14d368b5-a283-47a7-9724-f17222c67f6e",
      "ID": "929",
      "Facing": "Left",
      "Health": "1",
      "X": "1",
      "Y": "3",
      "Beat": "321.9648",
      "Time": "143.7156",
      "Spawn": "316",
      "Vibe": "True",
      "Burning": "False",
      "Mysterious": "False",
      "Event": "BlademasterPrepare"
    },
    {
      "GUID": "f5aeb857-e59d-4715-92ec-3763635e2857",
      "ID": "4355",
      "Facing": "Left",
      "Health": "1",
      "X": "1",
      "Y": "0",
      "Beat": "322",
      "Time": "143.7313",
      "Spawn": "312",
      "Vibe": "True",
      "Burning": "False",
      "Mysterious": "False",
      "Event": "HitEnemy"
    },
    {
      "GUID": "14d368b5-a283-47a7-9724-f17222c67f6e",
      "ID": "929",
      "Facing": "Left",
      "Health": "1",
      "X": "1",
      "Y": "0",
      "Beat": "324",
      "Time": "144.6269",
      "Spawn": "316",
      "Vibe": "True",
      "Burning": "False",
      "Mysterious": "False",
      "Event": "HitEnemy"
    },
    {
      "GUID": "96ef7038-64e3-4c98-8e19-36e276875b69",
      "ID": "4355",
      "Facing": "Right",
      "Health": "2",
      "X": "2",
      "Y": "0",
      "Beat": "325",
      "Time": "145.0746",
      "Spawn": "316",
      "Vibe": "True",
      "Burning": "False",
      "Mysterious": "False",
      "Event": "HitEnemy"
    },
    {
      "GUID": "96ef7038-64e3-4c98-8e19-36e276875b69",
      "ID": "4355",
      "Facing": "Left",
      "Health": "1",
      "X": "2",
      "Y": "0",
      "Beat": "326",
      "Time": "145.5224",
      "Spawn": "316",
      "Vibe": "True",
      "Burning": "False",
      "Mysterious": "False",
      "Event": "HitEnemy"
    },
    {
      "Event": "VCS",
      "Beat": "326.0263",
      "Time": "145.5342"
    },
    {
      "GUID": "adad2d13-425f-450c-8559-428b7a7384fc",
      "ID": "1722",
      "Facing": "Right",
      "Health": "1",
      "X": "2",
      "Y": "0",
      "Beat": "328",
      "Time": "146.4179",
      "Spawn": "319",
      "Vibe": "False",
      "Burning": "False",
      "Mysterious": "False",
      "Event": "HitEnemy"
    },
    {
      "GUID": "128cdc86-8f1e-4939-9111-b7274f299e33",
      "ID": "4355",
      "Facing": "Right",
      "Health": "2",
      "X": "1",
      "Y": "0",
      "Beat": "329",
      "Time": "146.8657",
      "Spawn": "320",
      "Vibe": "False",
      "Burning": "False",
      "Mysterious": "False",
      "Event": "HitEnemy"
    },
    {
      "GUID": "76ecf28d-2251-42de-b312-bbaedb0b5f1b",
      "ID": "929",
      "Facing": "Left",
      "Health": "1",
      "X": "1",
      "Y": "3",
      "Beat": "329.9701",
      "Time": "147.3",
      "Spawn": "324",
      "Vibe": "False",
      "Burning": "False",
      "Mysterious": "False",
      "Event": "BlademasterPrepare"
    },
    {
      "GUID": "128cdc86-8f1e-4939-9111-b7274f299e33",
      "ID": "4355",
      "Facing": "Left",
      "Health": "1",
      "X": "1",
      "Y": "0",
      "Beat": "330",
      "Time": "147.3134",
      "Spawn": "320",
      "Vibe": "False",
      "Burning": "False",
      "Mysterious": "False",
      "Event": "HitEnemy"
    },
    {
      "GUID": "76ecf28d-2251-42de-b312-bbaedb0b5f1b",
      "ID": "929",
      "Facing": "Left",
      "Health": "1",
      "X": "1",
      "Y": "0",
      "Beat": "332",
      "Time": "148.209",
      "Spawn": "324",
      "Vibe": "False",
      "Burning": "False",
      "Mysterious": "False",
      "Event": "HitEnemy"
    },
    {
      "GUID": "85979395-ca40-4b28-a916-35dc127cb299",
      "ID": "4355",
      "Facing": "Right",
      "Health": "2",
      "X": "2",
      "Y": "0",
      "Beat": "333",
      "Time": "148.6567",
      "Spawn": "324",
      "Vibe": "False",
      "Burning": "False",
      "Mysterious": "False",
      "Event": "HitEnemy"
    },
    {
      "GUID": "85979395-ca40-4b28-a916-35dc127cb299",
      "ID": "4355",
      "Facing": "Left",
      "Health": "1",
      "X": "2",
      "Y": "0",
      "Beat": "334",
      "Time": "149.1045",
      "Spawn": "324",
      "Vibe": "False",
      "Burning": "False",
      "Mysterious": "False",
      "Event": "HitEnemy"
    },
    {
      "GUID": "ede52d6e-17a2-4527-80df-ab52aa1b9c19",
      "ID": "1722",
      "Facing": "Right",
      "Health": "1",
      "X": "2",
      "Y": "0",
      "Beat": "336",
      "Time": "150",
      "Spawn": "327",
      "Vibe": "False",
      "Burning": "False",
      "Mysterious": "False",
      "Event": "HitEnemy"
    },
    {
      "GUID": "6065529c-85b9-4829-a8af-1ea7cbe8b4ce",
      "ID": "4355",
      "Facing": "Right",
      "Health": "2",
      "X": "1",
      "Y": "0",
      "Beat": "337",
      "Time": "150.4478",
      "Spawn": "328",
      "Vibe": "False",
      "Burning": "False",
      "Mysterious": "False",
      "Event": "HitEnemy"
    },
    {
      "GUID": "7a266160-10b2-4d78-afe8-330e2a87c336",
      "ID": "929",
      "Facing": "Left",
      "Health": "1",
      "X": "1",
      "Y": "3",
      "Beat": "337.9771",
      "Time": "150.8853",
      "Spawn": "332",
      "Vibe": "False",
      "Burning": "False",
      "Mysterious": "False",
      "Event": "BlademasterPrepare"
    },
    {
      "GUID": "6065529c-85b9-4829-a8af-1ea7cbe8b4ce",
      "ID": "4355",
      "Facing": "Left",
      "Health": "1",
      "X": "1",
      "Y": "0",
      "Beat": "338",
      "Time": "150.8955",
      "Spawn": "328",
      "Vibe": "False",
      "Burning": "False",
      "Mysterious": "False",
      "Event": "HitEnemy"
    },
    {
      "GUID": "7a266160-10b2-4d78-afe8-330e2a87c336",
      "ID": "929",
      "Facing": "Left",
      "Health": "1",
      "X": "1",
      "Y": "0",
      "Beat": "340",
      "Time": "151.791",
      "Spawn": "332",
      "Vibe": "False",
      "Burning": "False",
      "Mysterious": "False",
      "Event": "HitEnemy"
    },
    {
      "GUID": "2985f8dd-f1d9-4614-b91c-f4b4f38d046d",
      "ID": "4355",
      "Facing": "Right",
      "Health": "2",
      "X": "2",
      "Y": "0",
      "Beat": "341",
      "Time": "152.2388",
      "Spawn": "332",
      "Vibe": "False",
      "Burning": "False",
      "Mysterious": "False",
      "Event": "HitEnemy"
    },
    {
      "GUID": "2985f8dd-f1d9-4614-b91c-f4b4f38d046d",
      "ID": "4355",
      "Facing": "Left",
      "Health": "1",
      "X": "2",
      "Y": "0",
      "Beat": "342",
      "Time": "152.6866",
      "Spawn": "332",
      "Vibe": "False",
      "Burning": "False",
      "Mysterious": "False",
      "Event": "HitEnemy"
    },
    {
      "GUID": "0c6593f5-bcc5-4492-8038-6ed1290bc160",
      "ID": "1722",
      "Facing": "Right",
      "Health": "1",
      "X": "0",
      "Y": "0",
      "Beat": "345",
      "Time": "154.0298",
      "Spawn": "336",
      "Vibe": "False",
      "Burning": "False",
      "Mysterious": "False",
      "Event": "HitEnemy"
    },
    {
      "GUID": "91e16bfb-6cbf-43a4-9a30-b2019caac20d",
      "ID": "7358",
      "Facing": "Left",
      "Health": "1",
      "X": "0",
      "Y": "0",
      "Beat": "347",
      "Time": "154.9254",
      "Spawn": "338",
      "Vibe": "False",
      "Burning": "False",
      "Mysterious": "False",
      "Event": "HitEnemy"
    },
    {
      "GUID": "1d531923-cf22-4b5d-aad0-d16f62f8ece6",
      "ID": "929",
      "Facing": "Left",
      "Health": "1",
      "X": "1",
      "Y": "3",
      "Beat": "348.9927",
      "Time": "155.8176",
      "Spawn": "343",
      "Vibe": "False",
      "Burning": "False",
      "Mysterious": "False",
      "Event": "BlademasterPrepare"
    },
    {
      "GUID": "89452341-6ab6-4bbd-a1c5-497a10ccdf93",
      "ID": "1722",
      "Facing": "Right",
      "Health": "1",
      "X": "1",
      "Y": "0",
      "Beat": "349",
      "Time": "155.8209",
      "Spawn": "340",
      "Vibe": "False",
      "Burning": "False",
      "Mysterious": "False",
      "Event": "HitEnemy"
    },
    {
      "GUID": "1d531923-cf22-4b5d-aad0-d16f62f8ece6",
      "ID": "929",
      "Facing": "Left",
      "Health": "1",
      "X": "1",
      "Y": "0",
      "Beat": "351",
      "Time": "156.7164",
      "Spawn": "343",
      "Vibe": "False",
      "Burning": "False",
      "Mysterious": "False",
      "Event": "HitEnemy"
    },
    {
      "GUID": "7038c34d-b6d6-4e02-a199-ecb6b2cb00fc",
      "ID": "1722",
      "Facing": "Right",
      "Health": "1",
      "X": "0",
      "Y": "0",
      "Beat": "353",
      "Time": "157.6119",
      "Spawn": "344",
      "Vibe": "False",
      "Burning": "False",
      "Mysterious": "False",
      "Event": "HitEnemy"
    },
    {
      "GUID": "007e70ed-0a21-470b-9b51-5910158b41a4",
      "ID": "1722",
      "Facing": "Right",
      "Health": "1",
      "X": "0",
      "Y": "0",
      "Beat": "355",
      "Time": "158.5075",
      "Spawn": "346",
      "Vibe": "False",
      "Burning": "False",
      "Mysterious": "False",
      "Event": "HitEnemy"
    },
    {
      "GUID": "d26d0762-e87d-489f-a781-abe0ae2b67b5",
      "ID": "929",
      "Facing": "Left",
      "Health": "1",
      "X": "1",
      "Y": "3",
      "Beat": "356.9882",
      "Time": "159.3977",
      "Spawn": "351",
      "Vibe": "False",
      "Burning": "False",
      "Mysterious": "False",
      "Event": "BlademasterPrepare"
    },
    {
      "GUID": "c4866ad2-1734-48d5-9607-34858200625a",
      "ID": "1722",
      "Facing": "Right",
      "Health": "1",
      "X": "1",
      "Y": "0",
      "Beat": "357",
      "Time": "159.403",
      "Spawn": "348",
      "Vibe": "False",
      "Burning": "False",
      "Mysterious": "False",
      "Event": "HitEnemy"
    },
    {
      "GUID": "d26d0762-e87d-489f-a781-abe0ae2b67b5",
      "ID": "929",
      "Facing": "Left",
      "Health": "1",
      "X": "1",
      "Y": "0",
      "Beat": "359",
      "Time": "160.2985",
      "Spawn": "351",
      "Vibe": "False",
      "Burning": "False",
      "Mysterious": "False",
      "Event": "HitEnemy"
    },
    {
      "GUID": "ac801180-d3ee-4203-91df-6cd1661c9161",
      "ID": "1722",
      "Facing": "Right",
      "Health": "1",
      "X": "0",
      "Y": "0",
      "Beat": "361",
      "Time": "161.194",
      "Spawn": "352",
      "Vibe": "True",
      "Burning": "False",
      "Mysterious": "False",
      "Event": "HitEnemy"
    },
    {
      "GUID": "62e440c0-d059-4c51-b645-92bf910487ea",
      "ID": "7358",
      "Facing": "Left",
      "Health": "1",
      "X": "0",
      "Y": "0",
      "Beat": "363",
      "Time": "162.0896",
      "Spawn": "354",
      "Vibe": "True",
      "Burning": "False",
      "Mysterious": "False",
      "Event": "HitEnemy"
    },
    {
      "GUID": "9bc71b38-4f29-4d59-b019-4e1201648c65",
      "ID": "929",
      "Facing": "Left",
      "Health": "1",
      "X": "1",
      "Y": "3",
      "Beat": "364.9946",
      "Time": "162.9827",
      "Spawn": "359",
      "Vibe": "True",
      "Burning": "False",
      "Mysterious": "False",
      "Event": "BlademasterPrepare"
    },
    {
      "GUID": "4f1bf500-f39d-498d-b0d3-70a40673c36f",
      "ID": "1722",
      "Facing": "Right",
      "Health": "1",
      "X": "1",
      "Y": "0",
      "Beat": "365",
      "Time": "162.9851",
      "Spawn": "356",
      "Vibe": "True",
      "Burning": "False",
      "Mysterious": "False",
      "Event": "HitEnemy"
    },
    {
      "GUID": "9bc71b38-4f29-4d59-b019-4e1201648c65",
      "ID": "929",
      "Facing": "Left",
      "Health": "1",
      "X": "1",
      "Y": "0",
      "Beat": "367",
      "Time": "163.8806",
      "Spawn": "359",
      "Vibe": "True",
      "Burning": "False",
      "Mysterious": "False",
      "Event": "HitEnemy"
    },
    {
      "GUID": "06e431da-a520-4826-8f3a-9b72d040140b",
      "ID": "1722",
      "Facing": "Right",
      "Health": "1",
      "X": "0",
      "Y": "0",
      "Beat": "369",
      "Time": "164.7761",
      "Spawn": "360",
      "Vibe": "True",
      "Burning": "False",
      "Mysterious": "False",
      "Event": "HitEnemy"
    },
    {
      "GUID": "62c86be7-16eb-4a6f-bb59-cad297f74e9c",
      "ID": "1722",
      "Facing": "Right",
      "Health": "1",
      "X": "0",
      "Y": "0",
      "Beat": "371",
      "Time": "165.6716",
      "Spawn": "362",
      "Vibe": "True",
      "Burning": "False",
      "Mysterious": "False",
      "Event": "HitEnemy"
    },
    {
      "GUID": "bb7bff06-4911-4d9b-abfa-6ed8fbd50a4f",
      "ID": "4355",
      "Facing": "Right",
      "Health": "2",
      "X": "1",
      "Y": "0",
      "Beat": "374",
      "Time": "167.0149",
      "Spawn": "365",
      "Vibe": "True",
      "Burning": "False",
      "Mysterious": "False",
      "Event": "HitEnemy"
    },
    {
      "GUID": "bb7bff06-4911-4d9b-abfa-6ed8fbd50a4f",
      "ID": "4355",
      "Facing": "Left",
      "Health": "1",
      "X": "1",
      "Y": "0",
      "Beat": "375",
      "Time": "167.4627",
      "Spawn": "365",
      "Vibe": "True",
      "Burning": "False",
      "Mysterious": "False",
      "Event": "HitEnemy"
    },
    {
      "GUID": "6d0c8a69-2d2a-4519-b269-50111250dc5b",
      "ID": "1722",
      "Facing": "Right",
      "Health": "1",
      "X": "2",
      "Y": "0",
      "Beat": "377",
      "Time": "168.3582",
      "Spawn": "368",
      "Vibe": "True",
      "Burning": "False",
      "Mysterious": "False",
      "Event": "HitEnemy"
    },
    {
      "GUID": "5204882b-32b6-4fe4-a122-7e320174fabe",
      "ID": "1722",
      "Facing": "Right",
      "Health": "1",
      "X": "1",
      "Y": "0",
      "Beat": "378",
      "Time": "168.806",
      "Spawn": "369",
      "Vibe": "True",
      "Burning": "False",
      "Mysterious": "False",
      "Event": "HitEnemy"
    },
    {
      "GUID": "117939db-141b-4a1d-a86f-9737b91b0785",
      "ID": "1722",
      "Facing": "Right",
      "Health": "1",
      "X": "0",
      "Y": "0",
      "Beat": "379",
      "Time": "169.2537",
      "Spawn": "370",
      "Vibe": "True",
      "Burning": "False",
      "Mysterious": "False",
      "Event": "HitEnemy"
    },
    {
      "GUID": "c8700fde-89cb-44a3-b4a2-be60c31806a1",
      "ID": "1722",
      "Facing": "Right",
      "Health": "1",
      "X": "1",
      "Y": "0",
      "Beat": "380",
      "Time": "169.7015",
      "Spawn": "371",
      "Vibe": "True",
      "Burning": "False",
      "Mysterious": "False",
      "Event": "HitEnemy"
    },
    {
      "Event": "VCS",
      "Beat": "380.0325",
      "Time": "169.7161"
    },
    {
      "GUID": "753aa7cf-b1ae-4441-b99d-106c26d2a6aa",
      "ID": "8675309",
      "Facing": "Left",
      "Health": "2",
      "X": "2",
      "Y": "0",
      "Beat": "381",
      "Time": "170.1492",
      "Spawn": "372",
      "Vibe": "False",
      "Burning": "False",
      "Mysterious": "False",
      "Event": "HitEnemy"
    },
    {
      "GUID": "753aa7cf-b1ae-4441-b99d-106c26d2a6aa",
      "ID": "8675309",
      "Facing": "Left",
      "Health": "1",
      "X": "1",
      "Y": "0",
      "Beat": "382",
      "Time": "170.597",
      "Spawn": "372",
      "Vibe": "False",
      "Burning": "False",
      "Mysterious": "False",
      "Event": "HitEnemy"
    },
    {
      "GUID": "3e1211fa-a84e-4c72-a791-0acdc0b5451e",
      "ID": "8675309",
      "Facing": "Left",
      "Health": "2",
      "X": "1",
      "Y": "0",
      "Beat": "384",
      "Time": "171.4925",
      "Spawn": "375",
      "Vibe": "False",
      "Burning": "False",
      "Mysterious": "False",
      "Event": "HitEnemy"
    },
    {
      "GUID": "3e1211fa-a84e-4c72-a791-0acdc0b5451e",
      "ID": "8675309",
      "Facing": "Left",
      "Health": "1",
      "X": "0",
      "Y": "0",
      "Beat": "385",
      "Time": "171.9403",
      "Spawn": "375",
      "Vibe": "False",
      "Burning": "False",
      "Mysterious": "False",
      "Event": "HitEnemy"
    },
    {
      "GUID": "6641291f-7a2c-4b8b-8ce1-e7997ac02ae0",
      "ID": "8675309",
      "Facing": "Left",
      "Health": "2",
      "X": "1",
      "Y": "0",
      "Beat": "387",
      "Time": "172.8358",
      "Spawn": "378",
      "Vibe": "False",
      "Burning": "False",
      "Mysterious": "False",
      "Event": "HitEnemy"
    },
    {
      "GUID": "6641291f-7a2c-4b8b-8ce1-e7997ac02ae0",
      "ID": "8675309",
      "Facing": "Left",
      "Health": "1",
      "X": "0",
      "Y": "0",
      "Beat": "388",
      "Time": "173.2836",
      "Spawn": "378",
      "Vibe": "False",
      "Burning": "False",
      "Mysterious": "False",
      "Event": "HitEnemy"
    },
    {
      "GUID": "5a12a4b1-1bf9-47a0-82fa-20b121a99e43",
      "ID": "7358",
      "Facing": "Left",
      "Health": "1",
      "X": "1",
      "Y": "0",
      "Beat": "390",
      "Time": "174.1791",
      "Spawn": "381",
      "Vibe": "False",
      "Burning": "False",
      "Mysterious": "False",
      "Event": "HitEnemy"
    },
    {
      "GUID": "2a531829-ca91-47df-9100-a3ce469efe0a",
      "ID": "1722",
      "Facing": "Right",
      "Health": "1",
      "X": "2",
      "Y": "0",
      "Beat": "392",
      "Time": "175.0746",
      "Spawn": "383",
      "Vibe": "False",
      "Burning": "False",
      "Mysterious": "False",
      "Event": "HitEnemy"
    },
    {
      "GUID": "edc94f10-7c59-4f3e-aa3a-b95241ce48c3",
      "ID": "7358",
      "Facing": "Left",
      "Health": "1",
      "X": "1",
      "Y": "0",
      "Beat": "393",
      "Time": "175.5224",
      "Spawn": "384",
      "Vibe": "False",
      "Burning": "False",
      "Mysterious": "False",
      "Event": "HitEnemy"
    },
    {
      "GUID": "d2c60aba-aad2-4c39-9aa6-78c469a59533",
      "ID": "1722",
      "Facing": "Right",
      "Health": "1",
      "X": "0",
      "Y": "0",
      "Beat": "395",
      "Time": "176.4179",
      "Spawn": "386",
      "Vibe": "False",
      "Burning": "False",
      "Mysterious": "False",
      "Event": "HitEnemy"
    },
    {
      "GUID": "3e72f3c3-f3c1-49fc-b77e-016bf3e2c7a0",
      "ID": "1722",
      "Facing": "Right",
      "Health": "1",
      "X": "1",
      "Y": "0",
      "Beat": "397",
      "Time": "177.3134",
      "Spawn": "388",
      "Vibe": "False",
      "Burning": "False",
      "Mysterious": "False",
      "Event": "HitEnemy"
    },
    {
      "GUID": "7305d2a0-2307-4d0d-896a-17c18561ced6",
      "ID": "1722",
      "Facing": "Right",
      "Health": "1",
      "X": "2",
      "Y": "0",
      "Beat": "401",
      "Time": "179.1045",
      "Spawn": "392",
      "Vibe": "False",
      "Burning": "False",
      "Mysterious": "False",
      "Event": "HitEnemy"
    },
    {
      "GUID": "5bbf8913-b9e3-4b74-b52f-480fb8fbd3ce",
      "ID": "1722",
      "Facing": "Right",
      "Health": "1",
      "X": "1",
      "Y": "0",
      "Beat": "403",
      "Time": "180",
      "Spawn": "394",
      "Vibe": "False",
      "Burning": "False",
      "Mysterious": "False",
      "Event": "HitEnemy"
    },
    {
      "GUID": "314d9d03-991c-45f1-80bd-922e9e5b1389",
      "ID": "1722",
      "Facing": "Right",
      "Health": "1",
      "X": "0",
      "Y": "0",
      "Beat": "405",
      "Time": "180.8955",
      "Spawn": "396",
      "Vibe": "False",
      "Burning": "False",
      "Mysterious": "False",
      "Event": "HitEnemy"
    },
    {
      "GUID": "346876ff-5965-4a33-9f28-170c33e42fa4",
      "ID": "8675309",
      "Facing": "Left",
      "Health": "2",
      "X": "1",
      "Y": "0",
      "Beat": "409",
      "Time": "182.6866",
      "Spawn": "400",
      "Vibe": "False",
      "Burning": "False",
      "Mysterious": "False",
      "Event": "HitEnemy"
    },
    {
      "GUID": "346876ff-5965-4a33-9f28-170c33e42fa4",
      "ID": "8675309",
      "Facing": "Left",
      "Health": "1",
      "X": "0",
      "Y": "0",
      "Beat": "410",
      "Time": "183.1343",
      "Spawn": "400",
      "Vibe": "False",
      "Burning": "False",
      "Mysterious": "False",
      "Event": "HitEnemy"
    },
    {
      "GUID": "fcbd86bd-96e6-4489-a58d-8def843d9495",
      "ID": "8675309",
      "Facing": "Right",
      "Health": "2",
      "X": "0",
      "Y": "0",
      "Beat": "413",
      "Time": "184.4776",
      "Spawn": "404",
      "Vibe": "False",
      "Burning": "False",
      "Mysterious": "False",
      "Event": "HitEnemy"
    },
    {
      "GUID": "fcbd86bd-96e6-4489-a58d-8def843d9495",
      "ID": "8675309",
      "Facing": "Right",
      "Health": "1",
      "X": "1",
      "Y": "0",
      "Beat": "414",
      "Time": "184.9254",
      "Spawn": "404",
      "Vibe": "False",
      "Burning": "False",
      "Mysterious": "False",
      "Event": "HitEnemy"
    },
    {
      "GUID": "e952a15a-6725-48a2-8e0a-5bd90c40ea8b",
      "ID": "8675309",
      "Facing": "Right",
      "Health": "2",
      "X": "0",
      "Y": "0",
      "Beat": "416",
      "Time": "185.8209",
      "Spawn": "407",
      "Vibe": "False",
      "Burning": "False",
      "Mysterious": "False",
      "Event": "HitEnemy"
    },
    {
      "GUID": "e952a15a-6725-48a2-8e0a-5bd90c40ea8b",
      "ID": "8675309",
      "Facing": "Right",
      "Health": "1",
      "X": "1",
      "Y": "0",
      "Beat": "417",
      "Time": "186.2687",
      "Spawn": "407",
      "Vibe": "False",
      "Burning": "False",
      "Mysterious": "False",
      "Event": "HitEnemy"
    },
    {
      "GUID": "b58f096d-8faf-48bd-a01f-45c9bf54253c",
      "ID": "1722",
      "Facing": "Right",
      "Health": "1",
      "X": "0",
      "Y": "0",
      "Beat": "418",
      "Time": "186.7164",
      "Spawn": "409",
      "Vibe": "False",
      "Burning": "False",
      "Mysterious": "False",
      "Event": "HitEnemy"
    },
    {
      "GUID": "a5168232-d9c3-432e-88fc-2042b795b732",
      "ID": "1722",
      "Facing": "Right",
      "Health": "1",
      "X": "1",
      "Y": "0",
      "Beat": "419",
      "Time": "187.1642",
      "Spawn": "410",
      "Vibe": "False",
      "Burning": "False",
      "Mysterious": "False",
      "Event": "HitEnemy"
    },
    {
      "GUID": "fbbf2a77-8174-4f61-99bf-d2f317a8e52c",
      "ID": "1722",
      "Facing": "Right",
      "Health": "1",
      "X": "2",
      "Y": "0",
      "Beat": "420",
      "Time": "187.6119",
      "Spawn": "411",
      "Vibe": "False",
      "Burning": "False",
      "Mysterious": "False",
      "Event": "HitEnemy"
    },
    {
      "GUID": "65616e3c-e4af-4d84-a03a-aed3c65e9f3c",
      "ID": "1722",
      "Facing": "Right",
      "Health": "1",
      "X": "1",
      "Y": "0",
      "Beat": "421",
      "Time": "188.0597",
      "Spawn": "412",
      "Vibe": "False",
      "Burning": "False",
      "Mysterious": "False",
      "Event": "HitEnemy"
    },
    {
      "GUID": "78c9ebbd-b6ed-43e4-b985-e356a4894c12",
      "ID": "4355",
      "Facing": "Right",
      "Health": "2",
      "X": "0",
      "Y": "0",
      "Beat": "424",
      "Time": "189.403",
      "Spawn": "415",
      "Vibe": "False",
      "Burning": "False",
      "Mysterious": "False",
      "Event": "HitEnemy"
    },
    {
      "GUID": "78c9ebbd-b6ed-43e4-b985-e356a4894c12",
      "ID": "4355",
      "Facing": "Left",
      "Health": "1",
      "X": "0",
      "Y": "0",
      "Beat": "425",
      "Time": "189.8508",
      "Spawn": "415",
      "Vibe": "False",
      "Burning": "False",
      "Mysterious": "False",
      "Event": "HitEnemy"
    },
    {
      "GUID": "0584cb46-27b8-41cd-b558-2d36759f499c",
      "ID": "4355",
      "Facing": "Right",
      "Health": "2",
      "X": "1",
      "Y": "0",
      "Beat": "429",
      "Time": "191.6418",
      "Spawn": "420",
      "Vibe": "False",
      "Burning": "False",
      "Mysterious": "False",
      "Event": "HitEnemy"
    },
    {
      "GUID": "9313036f-b4f9-4ca6-a038-fc5dd6b82b94",
      "ID": "929",
      "Facing": "Left",
      "Health": "1",
      "X": "1",
      "Y": "3",
      "Beat": "429.9881",
      "Time": "192.0842",
      "Spawn": "424",
      "Vibe": "False",
      "Burning": "False",
      "Mysterious": "False",
      "Event": "BlademasterPrepare"
    },
    {
      "GUID": "0584cb46-27b8-41cd-b558-2d36759f499c",
      "ID": "4355",
      "Facing": "Left",
      "Health": "1",
      "X": "1",
      "Y": "0",
      "Beat": "430",
      "Time": "192.0896",
      "Spawn": "420",
      "Vibe": "False",
      "Burning": "False",
      "Mysterious": "False",
      "Event": "HitEnemy"
    },
    {
      "GUID": "9313036f-b4f9-4ca6-a038-fc5dd6b82b94",
      "ID": "929",
      "Facing": "Left",
      "Health": "1",
      "X": "1",
      "Y": "0",
      "Beat": "432",
      "Time": "192.9851",
      "Spawn": "424",
      "Vibe": "False",
      "Burning": "False",
      "Mysterious": "False",
      "Event": "HitEnemy"
    },
    {
      "GUID": "b3d3d190-9f17-4b84-940a-af63c509c695",
      "ID": "4355",
      "Facing": "Right",
      "Health": "2",
      "X": "0",
      "Y": "0",
      "Beat": "433",
      "Time": "193.4328",
      "Spawn": "424",
      "Vibe": "False",
      "Burning": "False",
      "Mysterious": "False",
      "Event": "HitEnemy"
    },
    {
      "GUID": "b3d3d190-9f17-4b84-940a-af63c509c695",
      "ID": "4355",
      "Facing": "Left",
      "Health": "1",
      "X": "0",
      "Y": "0",
      "Beat": "434",
      "Time": "193.8806",
      "Spawn": "424",
      "Vibe": "False",
      "Burning": "False",
      "Mysterious": "False",
      "Event": "HitEnemy"
    },
    {
      "GUID": "193ecef6-1fd0-4165-a57d-4aed615039ad",
      "ID": "1722",
      "Facing": "Right",
      "Health": "1",
      "X": "0",
      "Y": "0",
      "Beat": "436",
      "Time": "194.7761",
      "Spawn": "427",
      "Vibe": "False",
      "Burning": "False",
      "Mysterious": "False",
      "Event": "HitEnemy"
    },
    {
      "GUID": "a7ab6ad7-9dee-4792-bb5b-d87f0e4a0b61",
      "ID": "4355",
      "Facing": "Right",
      "Health": "2",
      "X": "1",
      "Y": "0",
      "Beat": "437",
      "Time": "195.2239",
      "Spawn": "428",
      "Vibe": "False",
      "Burning": "False",
      "Mysterious": "False",
      "Event": "HitEnemy"
    },
    {
      "GUID": "6bd67e02-6f14-4249-a1b1-08479919b0a1",
      "ID": "929",
      "Facing": "Left",
      "Health": "1",
      "X": "1",
      "Y": "3",
      "Beat": "437.994",
      "Time": "195.6689",
      "Spawn": "432",
      "Vibe": "False",
      "Burning": "False",
      "Mysterious": "False",
      "Event": "BlademasterPrepare"
    },
    {
      "GUID": "a7ab6ad7-9dee-4792-bb5b-d87f0e4a0b61",
      "ID": "4355",
      "Facing": "Left",
      "Health": "1",
      "X": "1",
      "Y": "0",
      "Beat": "438",
      "Time": "195.6716",
      "Spawn": "428",
      "Vibe": "False",
      "Burning": "False",
      "Mysterious": "False",
      "Event": "HitEnemy"
    },
    {
      "GUID": "6bd67e02-6f14-4249-a1b1-08479919b0a1",
      "ID": "929",
      "Facing": "Left",
      "Health": "1",
      "X": "1",
      "Y": "0",
      "Beat": "440",
      "Time": "196.5672",
      "Spawn": "432",
      "Vibe": "False",
      "Burning": "False",
      "Mysterious": "False",
      "Event": "HitEnemy"
    },
    {
      "GUID": "1053f3bf-2f5a-408b-b1ee-f945bfb206c5",
      "ID": "4355",
      "Facing": "Right",
      "Health": "2",
      "X": "0",
      "Y": "0",
      "Beat": "441",
      "Time": "197.0149",
      "Spawn": "432",
      "Vibe": "False",
      "Burning": "False",
      "Mysterious": "False",
      "Event": "HitEnemy"
    },
    {
      "GUID": "1053f3bf-2f5a-408b-b1ee-f945bfb206c5",
      "ID": "4355",
      "Facing": "Left",
      "Health": "1",
      "X": "0",
      "Y": "0",
      "Beat": "442",
      "Time": "197.4627",
      "Spawn": "432",
      "Vibe": "False",
      "Burning": "False",
      "Mysterious": "False",
      "Event": "HitEnemy"
    },
    {
      "GUID": "fe424744-e2e7-4380-a8f7-661a313d23d3",
      "ID": "1722",
      "Facing": "Right",
      "Health": "1",
      "X": "0",
      "Y": "0",
      "Beat": "444",
      "Time": "198.3582",
      "Spawn": "435",
      "Vibe": "False",
      "Burning": "False",
      "Mysterious": "False",
      "Event": "HitEnemy"
    },
    {
      "GUID": "7419d42f-4848-4cae-9621-72ebedf17832",
      "ID": "4355",
      "Facing": "Right",
      "Health": "2",
      "X": "1",
      "Y": "0",
      "Beat": "445",
      "Time": "198.806",
      "Spawn": "436",
      "Vibe": "False",
      "Burning": "False",
      "Mysterious": "False",
      "Event": "HitEnemy"
    },
    {
      "GUID": "75726df0-f3d8-439b-931e-fbc750be6b0b",
      "ID": "929",
      "Facing": "Left",
      "Health": "1",
      "X": "1",
      "Y": "3",
      "Beat": "445.9895",
      "Time": "199.249",
      "Spawn": "440",
      "Vibe": "False",
      "Burning": "False",
      "Mysterious": "False",
      "Event": "BlademasterPrepare"
    },
    {
      "GUID": "7419d42f-4848-4cae-9621-72ebedf17832",
      "ID": "4355",
      "Facing": "Left",
      "Health": "1",
      "X": "1",
      "Y": "0",
      "Beat": "446",
      "Time": "199.2537",
      "Spawn": "436",
      "Vibe": "False",
      "Burning": "False",
      "Mysterious": "False",
      "Event": "HitEnemy"
    },
    {
      "GUID": "75726df0-f3d8-439b-931e-fbc750be6b0b",
      "ID": "929",
      "Facing": "Left",
      "Health": "1",
      "X": "1",
      "Y": "0",
      "Beat": "448",
      "Time": "200.1492",
      "Spawn": "440",
      "Vibe": "False",
      "Burning": "False",
      "Mysterious": "False",
      "Event": "HitEnemy"
    },
    {
      "GUID": "f0f1e0cf-9261-40fd-ab02-3665234ac8a5",
      "ID": "4355",
      "Facing": "Right",
      "Health": "2",
      "X": "0",
      "Y": "0",
      "Beat": "449",
      "Time": "200.597",
      "Spawn": "440",
      "Vibe": "False",
      "Burning": "False",
      "Mysterious": "False",
      "Event": "HitEnemy"
    },
    {
      "GUID": "f0f1e0cf-9261-40fd-ab02-3665234ac8a5",
      "ID": "4355",
      "Facing": "Left",
      "Health": "1",
      "X": "0",
      "Y": "0",
      "Beat": "450",
      "Time": "201.0448",
      "Spawn": "440",
      "Vibe": "False",
      "Burning": "False",
      "Mysterious": "False",
      "Event": "HitEnemy"
    },
    {
      "GUID": "1c7a674f-c619-49fa-8589-3bd2cbd503ed",
      "ID": "1722",
      "Facing": "Right",
      "Health": "1",
      "X": "0",
      "Y": "0",
      "Beat": "452",
      "Time": "201.9403",
      "Spawn": "443",
      "Vibe": "False",
      "Burning": "False",
      "Mysterious": "False",
      "Event": "HitEnemy"
    },
    {
      "GUID": "3fbcedc1-26f8-4ded-9f3a-c0f317d2963e",
      "ID": "4355",
      "Facing": "Right",
      "Health": "2",
      "X": "1",
      "Y": "0",
      "Beat": "453",
      "Time": "202.3881",
      "Spawn": "444",
      "Vibe": "False",
      "Burning": "False",
      "Mysterious": "False",
      "Event": "HitEnemy"
    }
  ]
}