{"beatDivisions":12,"playbackOffset":0,"coalTrapSpeedUpFactorOverride":0,"inputMappingOverrideJson":"","cameraZoomLevel":0,"name":"Glass_Cages_med_zfix","defaultBossStance":0,"events":[{"startBeatNumber":3,"endBeatNumber":4,"audioEvents":[],"track":3,"clipin":0,"group":0,"type":"SpawnEnemy","dataPairs":[{"_eventDataKey":"EnemyId","_eventDataValue":"1722"},{"_eventDataKey":"ShouldStartFacingRight","_eventDataValue":"True"},{"_eventDataKey":"ShouldClampToSubdivisions","_eventDataValue":"True"}]},{"startBeatNumber":3.5,"endBeatNumber":4.5,"track":2,"clipin":0,"group":0,"type":"SpawnEnemy","dataPairs":[{"_eventDataKey":"EnemyId","_eventDataValue":"1722"},{"_eventDataKey":"ShouldClampToSubdivisions","_eventDataValue":"True"}]},{"startBeatNumber":4.5,"endBeatNumber":6.5,"track":2,"clipin":0,"group":0,"type":"SpawnEnemy","dataPairs":[{"_eventDataKey":"EnemyId","_eventDataValue":"4355"},{"_eventDataKey":"ShouldClampToSubdivisions","_eventDataValue":"True"}]},{"startBeatNumber":5,"endBeatNumber":6,"track":1,"clipin":0,"group":0,"type":"SpawnEnemy","dataPairs":[{"_eventDataKey":"EnemyId","_eventDataValue":"1722"},{"_eventDataKey":"ShouldClampToSubdivisions","_eventDataValue":"True"}]},{"startBeatNumber":6.5,"endBeatNumber":7.5,"track":1,"clipin":0,"group":0,"type":"SpawnEnemy","dataPairs":[{"_eventDataKey":"EnemyId","_eventDataValue":"1722"},{"_eventDataKey":"ShouldClampToSubdivisions","_eventDataValue":"True"}]},{"startBeatNumber":7.5,"endBeatNumber":8.5,"track":3,"clipin":0,"group":0,"type":"SpawnEnemy","dataPairs":[{"_eventDataKey":"EnemyId","_eventDataValue":"1722"},{"_eventDataKey":"ShouldClampToSubdivisions","_eventDataValue":"True"}]},{"startBeatNumber":8,"endBeatNumber":10,"track":1,"clipin":0,"group":0,"type":"SpawnEnemy","dataPairs":[{"_eventDataKey":"EnemyId","_eventDataValue":"4355"},{"_eventDataKey":"ShouldClampToSubdivisions","_eventDataValue":"True"}]},{"startBeatNumber":8,"endBeatNumber":9,"track":2,"clipin":0,"group":0,"type":"SpawnEnemy","dataPairs":[{"_eventDataKey":"EnemyId","_eventDataValue":"1722"},{"_eventDataKey":"ShouldClampToSubdivisions","_eventDataValue":"True"}]},{"startBeatNumber":9,"endBeatNumber":10,"track":3,"clipin":0,"group":0,"type":"SpawnEnemy","dataPairs":[{"_eventDataKey":"EnemyId","_eventDataValue":"1722"},{"_eventDataKey":"ShouldClampToSubdivisions","_eventDataValue":"True"}]},{"startBeatNumber":10,"endBeatNumber":12,"track":1,"clipin":0,"group":0,"type":"SpawnEnemy","dataPairs":[{"_eventDataKey":"EnemyId","_eventDataValue":"4355"},{"_eventDataKey":"ShouldClampToSubdivisions","_eventDataValue":"True"}]},{"startBeatNumber":10,"endBeatNumber":11,"track":2,"clipin":0,"group":0,"type":"SpawnEnemy","dataPairs":[{"_eventDataKey":"EnemyId","_eventDataValue":"1722"},{"_eventDataKey":"ShouldClampToSubdivisions","_eventDataValue":"True"}]},{"startBeatNumber":11.5,"endBeatNumber":12.5,"track":2,"clipin":0,"group":0,"type":"SpawnEnemy","dataPairs":[{"_eventDataKey":"EnemyId","_eventDataValue":"1722"},{"_eventDataKey":"ShouldClampToSubdivisions","_eventDataValue":"True"}]},{"startBeatNumber":12,"endBeatNumber":13,"track":3,"clipin":0,"group":0,"type":"SpawnEnemy","dataPairs":[{"_eventDataKey":"EnemyId","_eventDataValue":"1722"},{"_eventDataKey":"ShouldClampToSubdivisions","_eventDataValue":"True"}]},{"startBeatNumber":12.5,"endBeatNumber":14.5,"track":2,"clipin":0,"group":0,"type":"SpawnEnemy","dataPairs":[{"_eventDataKey":"EnemyId","_eventDataValue":"4355"},{"_eventDataKey":"ShouldClampToSubdivisions","_eventDataValue":"True"}]},{"startBeatNumber":13,"endBeatNumber":14,"track":1,"clipin":0,"group":0,"type":"SpawnEnemy","dataPairs":[{"_eventDataKey":"EnemyId","_eventDataValue":"1722"},{"_eventDataKey":"ShouldClampToSubdivisions","_eventDataValue":"True"}]},{"startBeatNumber":14.5,"endBeatNumber":15.5,"track":1,"clipin":0,"group":0,"type":"SpawnEnemy","dataPairs":[{"_eventDataKey":"EnemyId","_eventDataValue":"1722"},{"_eventDataKey":"ShouldClampToSubdivisions","_eventDataValue":"True"}]},{"startBeatNumber":15.5,"endBeatNumber":17.5,"track":2,"clipin":0,"group":0,"type":"SpawnEnemy","dataPairs":[{"_eventDataKey":"EnemyId","_eventDataValue":"4355"},{"_eventDataKey":"ShouldClampToSubdivisions","_eventDataValue":"True"}]},{"startBeatNumber":16,"endBeatNumber":17,"track":1,"clipin":0,"group":0,"type":"SpawnEnemy","dataPairs":[{"_eventDataKey":"EnemyId","_eventDataValue":"1722"},{"_eventDataKey":"ShouldClampToSubdivisions","_eventDataValue":"True"}]},{"startBeatNumber":18,"endBeatNumber":19,"track":3,"clipin":0,"group":0,"type":"SpawnEnemy","dataPairs":[{"_eventDataKey":"EnemyId","_eventDataValue":"1722"},{"_eventDataKey":"ShouldClampToSubdivisions","_eventDataValue":"True"}]},{"startBeatNumber":19,"endBeatNumber":20,"track":1,"clipin":0,"group":0,"type":"SpawnEnemy","dataPairs":[{"_eventDataKey":"EnemyId","_eventDataValue":"1722"},{"_eventDataKey":"ShouldClampToSubdivisions","_eventDataValue":"True"}]},{"startBeatNumber":19.5,"endBeatNumber":20.5,"track":2,"clipin":0,"group":0,"type":"SpawnEnemy","dataPairs":[{"_eventDataKey":"EnemyId","_eventDataValue":"1722"},{"_eventDataKey":"ShouldClampToSubdivisions","_eventDataValue":"True"}]},{"startBeatNumber":20,"endBeatNumber":21,"track":3,"clipin":0,"group":0,"type":"SpawnEnemy","dataPairs":[{"_eventDataKey":"EnemyId","_eventDataValue":"1722"},{"_eventDataKey":"ShouldClampToSubdivisions","_eventDataValue":"True"}]},{"startBeatNumber":20.5,"endBeatNumber":22.5,"track":2,"clipin":0,"group":0,"type":"SpawnEnemy","dataPairs":[{"_eventDataKey":"EnemyId","_eventDataValue":"4355"},{"_eventDataKey":"ShouldClampToSubdivisions","_eventDataValue":"True"}]},{"startBeatNumber":21,"endBeatNumber":22,"track":1,"clipin":0,"group":0,"type":"SpawnEnemy","dataPairs":[{"_eventDataKey":"EnemyId","_eventDataValue":"1722"},{"_eventDataKey":"ShouldClampToSubdivisions","_eventDataValue":"True"}]},{"startBeatNumber":22.5,"endBeatNumber":23.5,"track":1,"clipin":0,"group":0,"type":"SpawnEnemy","dataPairs":[{"_eventDataKey":"EnemyId","_eventDataValue":"1722"},{"_eventDataKey":"ShouldClampToSubdivisions","_eventDataValue":"True"}]},{"startBeatNumber":23.5,"endBeatNumber":24.5,"track":2,"clipin":0,"group":0,"type":"SpawnEnemy","dataPairs":[{"_eventDataKey":"EnemyId","_eventDataValue":"1722"},{"_eventDataKey":"ShouldClampToSubdivisions","_eventDataValue":"True"}]},{"startBeatNumber":24,"endBeatNumber":25,"track":1,"clipin":0,"group":0,"type":"SpawnEnemy","dataPairs":[{"_eventDataKey":"EnemyId","_eventDataValue":"1722"},{"_eventDataKey":"ShouldClampToSubdivisions","_eventDataValue":"True"}]},{"startBeatNumber":24,"endBeatNumber":26,"track":3,"clipin":0,"group":0,"type":"SpawnEnemy","dataPairs":[{"_eventDataKey":"EnemyId","_eventDataValue":"4355"},{"_eventDataKey":"ShouldClampToSubdivisions","_eventDataValue":"True"}]},{"startBeatNumber":26,"endBeatNumber":28,"track":1,"clipin":0,"group":0,"type":"SpawnEnemy","dataPairs":[{"_eventDataKey":"EnemyId","_eventDataValue":"4355"},{"_eventDataKey":"ShouldClampToSubdivisions","_eventDataValue":"True"}]},{"startBeatNumber":26,"endBeatNumber":27,"audioEvents":[],"track":3,"clipin":0,"group":0,"type":"SpawnEnemy","dataPairs":[{"_eventDataKey":"EnemyId","_eventDataValue":"1722"},{"_eventDataKey":"ShouldStartFacingRight","_eventDataValue":"True"},{"_eventDataKey":"ShouldClampToSubdivisions","_eventDataValue":"True"}]},{"startBeatNumber":27,"endBeatNumber":28,"audioEvents":[],"track":2,"clipin":0,"group":0,"type":"SpawnEnemy","dataPairs":[{"_eventDataKey":"EnemyId","_eventDataValue":"4355"},{"_eventDataKey":"ShouldStartFacingRight","_eventDataValue":"True"},{"_eventDataKey":"ShouldClampToSubdivisions","_eventDataValue":"True"}]},{"startBeatNumber":28,"endBeatNumber":29,"track":1,"clipin":0,"group":0,"type":"SpawnEnemy","dataPairs":[{"_eventDataKey":"EnemyId","_eventDataValue":"1722"},{"_eventDataKey":"ShouldClampToSubdivisions","_eventDataValue":"True"}]},{"startBeatNumber":28,"endBeatNumber":29,"audioEvents":[],"track":3,"clipin":0,"group":0,"type":"SpawnEnemy","dataPairs":[{"_eventDataKey":"EnemyId","_eventDataValue":"1722"},{"_eventDataKey":"ShouldStartFacingRight","_eventDataValue":"True"},{"_eventDataKey":"ShouldClampToSubdivisions","_eventDataValue":"True"}]},{"startBeatNumber":29,"endBeatNumber":30,"track":3,"clipin":0,"group":0,"type":"SpawnEnemy","dataPairs":[{"_eventDataKey":"EnemyId","_eventDataValue":"1722"},{"_eventDataKey":"ShouldClampToSubdivisions","_eventDataValue":"True"}]},{"startBeatNumber":30,"endBeatNumber":31,"track":2,"clipin":0,"group":0,"type":"SpawnEnemy","dataPairs":[{"_eventDataKey":"EnemyId","_eventDataValue":"1722"},{"_eventDataKey":"ShouldClampToSubdivisions","_eventDataValue":"True"}]},{"startBeatNumber":32,"endBeatNumber":33,"track":1,"clipin":0,"group":0,"type":"SpawnEnemy","dataPairs":[{"_eventDataKey":"EnemyId","_eventDataValue":"1722"},{"_eventDataKey":"ShouldClampToSubdivisions","_eventDataValue":"True"}]},{"startBeatNumber":33,"endBeatNumber":34,"track":3,"clipin":0,"group":0,"type":"SpawnEnemy","dataPairs":[{"_eventDataKey":"EnemyId","_eventDataValue":"1722"},{"_eventDataKey":"ShouldClampToSubdivisions","_eventDataValue":"True"}]},{"startBeatNumber":34,"endBeatNumber":35,"track":2,"clipin":0,"group":0,"type":"SpawnEnemy","dataPairs":[{"_eventDataKey":"EnemyId","_eventDataValue":"1722"},{"_eventDataKey":"ShouldClampToSubdivisions","_eventDataValue":"True"}]},{"startBeatNumber":34,"endBeatNumber":35,"track":2,"clipin":0,"group":0,"type":"SpawnTrap","dataPairs":[{"_eventDataKey":"TrapDirection","_eventDataValue":"2"},{"_eventDataKey":"TrapTypeToSpawn","_eventDataValue":"Bounce"},{"_eventDataKey":"TrapDropRow","_eventDataValue":"2"},{"_eventDataKey":"TrapHealthInBeats","_eventDataValue":"7"}]},{"startBeatNumber":36,"endBeatNumber":37,"track":3,"clipin":0,"group":0,"type":"SpawnEnemy","dataPairs":[{"_eventDataKey":"EnemyId","_eventDataValue":"1722"},{"_eventDataKey":"ShouldClampToSubdivisions","_eventDataValue":"True"}]},{"startBeatNumber":37,"endBeatNumber":38,"track":1,"clipin":0,"group":0,"type":"SpawnEnemy","dataPairs":[{"_eventDataKey":"EnemyId","_eventDataValue":"1722"},{"_eventDataKey":"ShouldClampToSubdivisions","_eventDataValue":"True"}]},{"startBeatNumber":38,"endBeatNumber":39,"track":2,"clipin":0,"group":0,"type":"SpawnEnemy","dataPairs":[{"_eventDataKey":"EnemyId","_eventDataValue":"1722"},{"_eventDataKey":"ShouldClampToSubdivisions","_eventDataValue":"True"}]},{"startBeatNumber":40,"endBeatNumber":41,"track":3,"clipin":0,"group":0,"type":"SpawnEnemy","dataPairs":[{"_eventDataKey":"EnemyId","_eventDataValue":"1722"},{"_eventDataKey":"ShouldClampToSubdivisions","_eventDataValue":"True"}]},{"startBeatNumber":41,"endBeatNumber":42,"track":1,"clipin":0,"group":0,"type":"SpawnEnemy","dataPairs":[{"_eventDataKey":"EnemyId","_eventDataValue":"1722"},{"_eventDataKey":"ShouldClampToSubdivisions","_eventDataValue":"True"}]},{"startBeatNumber":42,"endBeatNumber":43,"track":2,"clipin":0,"group":0,"type":"SpawnEnemy","dataPairs":[{"_eventDataKey":"EnemyId","_eventDataValue":"1722"},{"_eventDataKey":"ShouldClampToSubdivisions","_eventDataValue":"True"}]},{"startBeatNumber":43,"endBeatNumber":44,"track":2,"clipin":0,"group":0,"type":"SpawnTrap","dataPairs":[{"_eventDataKey":"TrapDirection","_eventDataValue":"1"},{"_eventDataKey":"TrapTypeToSpawn","_eventDataValue":"Bounce"},{"_eventDataKey":"TrapDropRow","_eventDataValue":"2"},{"_eventDataKey":"TrapHealthInBeats","_eventDataValue":"7"}]},{"startBeatNumber":44,"endBeatNumber":45,"track":3,"clipin":0,"group":0,"type":"SpawnEnemy","dataPairs":[{"_eventDataKey":"EnemyId","_eventDataValue":"1722"},{"_eventDataKey":"ShouldClampToSubdivisions","_eventDataValue":"True"}]},{"startBeatNumber":44.5,"endBeatNumber":46.5,"track":2,"clipin":0,"group":0,"type":"SpawnEnemy","dataPairs":[{"_eventDataKey":"EnemyId","_eventDataValue":"4355"},{"_eventDataKey":"ShouldClampToSubdivisions","_eventDataValue":"True"}]},{"startBeatNumber":45,"endBeatNumber":46,"track":1,"clipin":0,"group":0,"type":"SpawnEnemy","dataPairs":[{"_eventDataKey":"EnemyId","_eventDataValue":"1722"},{"_eventDataKey":"ShouldClampToSubdivisions","_eventDataValue":"True"}]},{"startBeatNumber":46.5,"endBeatNumber":47.5,"track":1,"clipin":0,"group":0,"type":"SpawnEnemy","dataPairs":[{"_eventDataKey":"EnemyId","_eventDataValue":"1722"},{"_eventDataKey":"ShouldClampToSubdivisions","_eventDataValue":"True"}]},{"startBeatNumber":47.5,"endBeatNumber":49.5,"track":2,"clipin":0,"group":0,"type":"SpawnEnemy","dataPairs":[{"_eventDataKey":"EnemyId","_eventDataValue":"4355"},{"_eventDataKey":"ShouldClampToSubdivisions","_eventDataValue":"True"}]},{"startBeatNumber":48,"endBeatNumber":49,"track":1,"clipin":0,"group":0,"type":"SpawnEnemy","dataPairs":[{"_eventDataKey":"EnemyId","_eventDataValue":"1722"},{"_eventDataKey":"ShouldClampToSubdivisions","_eventDataValue":"True"}]},{"startBeatNumber":51,"endBeatNumber":52,"track":3,"clipin":0,"group":0,"type":"SpawnEnemy","dataPairs":[{"_eventDataKey":"EnemyId","_eventDataValue":"1722"},{"_eventDataKey":"ShouldClampToSubdivisions","_eventDataValue":"True"}]},{"startBeatNumber":51.5,"endBeatNumber":52.5,"track":2,"clipin":0,"group":0,"type":"SpawnEnemy","dataPairs":[{"_eventDataKey":"EnemyId","_eventDataValue":"1722"},{"_eventDataKey":"ShouldClampToSubdivisions","_eventDataValue":"True"}]},{"startBeatNumber":53.5,"endBeatNumber":54.5,"track":1,"clipin":0,"group":0,"type":"SpawnEnemy","dataPairs":[{"_eventDataKey":"EnemyId","_eventDataValue":"1722"},{"_eventDataKey":"ShouldClampToSubdivisions","_eventDataValue":"True"}]},{"startBeatNumber":54.5,"endBeatNumber":55.5,"track":2,"clipin":0,"group":0,"type":"SpawnEnemy","dataPairs":[{"_eventDataKey":"EnemyId","_eventDataValue":"1722"},{"_eventDataKey":"ShouldClampToSubdivisions","_eventDataValue":"True"}]},{"startBeatNumber":56,"endBeatNumber":57,"track":3,"clipin":0,"group":0,"type":"SpawnEnemy","dataPairs":[{"_eventDataKey":"EnemyId","_eventDataValue":"1722"},{"_eventDataKey":"ShouldClampToSubdivisions","_eventDataValue":"True"}]},{"startBeatNumber":58,"endBeatNumber":59,"track":3,"clipin":0,"group":0,"type":"SpawnEnemy","dataPairs":[{"_eventDataKey":"EnemyId","_eventDataValue":"1722"},{"_eventDataKey":"ShouldClampToSubdivisions","_eventDataValue":"True"}]},{"startBeatNumber":59,"endBeatNumber":61,"track":3,"clipin":0,"group":0,"type":"SpawnEnemy","dataPairs":[{"_eventDataKey":"EnemyId","_eventDataValue":"4355"},{"_eventDataKey":"ShouldClampToSubdivisions","_eventDataValue":"True"}]},{"startBeatNumber":59.5,"endBeatNumber":60.5,"audioEvents":[],"track":2,"clipin":0,"group":0,"type":"SpawnEnemy","dataPairs":[{"_eventDataKey":"EnemyId","_eventDataValue":"1722"},{"_eventDataKey":"ShouldStartFacingRight","_eventDataValue":"True"},{"_eventDataKey":"ShouldClampToSubdivisions","_eventDataValue":"True"}]},{"startBeatNumber":60.5,"endBeatNumber":61.5,"audioEvents":[],"track":2,"clipin":0,"group":0,"type":"SpawnEnemy","dataPairs":[{"_eventDataKey":"EnemyId","_eventDataValue":"4355"},{"_eventDataKey":"ShouldStartFacingRight","_eventDataValue":"True"},{"_eventDataKey":"ShouldClampToSubdivisions","_eventDataValue":"True"}]},{"startBeatNumber":61,"endBeatNumber":62,"audioEvents":[],"track":1,"clipin":0,"group":0,"type":"SpawnEnemy","dataPairs":[{"_eventDataKey":"EnemyId","_eventDataValue":"1722"},{"_eventDataKey":"ShouldStartFacingRight","_eventDataValue":"True"},{"_eventDataKey":"ShouldClampToSubdivisions","_eventDataValue":"True"}]},{"startBeatNumber":63,"endBeatNumber":64,"track":1,"clipin":0,"group":0,"type":"SpawnEnemy","dataPairs":[{"_eventDataKey":"EnemyId","_eventDataValue":"1722"},{"_eventDataKey":"ShouldClampToSubdivisions","_eventDataValue":"True"}]},{"startBeatNumber":63.5,"endBeatNumber":64.5,"track":2,"clipin":0,"group":0,"type":"SpawnEnemy","dataPairs":[{"_eventDataKey":"EnemyId","_eventDataValue":"1722"},{"_eventDataKey":"ShouldClampToSubdivisions","_eventDataValue":"True"}]},{"startBeatNumber":64,"endBeatNumber":65,"track":3,"clipin":0,"group":0,"type":"SpawnEnemy","dataPairs":[{"_eventDataKey":"EnemyId","_eventDataValue":"1722"},{"_eventDataKey":"ShouldClampToSubdivisions","_eventDataValue":"True"}]},{"startBeatNumber":65.83334,"endBeatNumber":72.5,"track":1,"clipin":0,"group":0,"type":"StartVibeChain","dataPairs":[{"_eventDataKey":"RiftedVibeChainShift","_eventDataValue":"65.83333"}]},{"startBeatNumber":66,"endBeatNumber":67,"track":3,"clipin":0,"group":0,"type":"SpawnEnemy","dataPairs":[{"_eventDataKey":"EnemyId","_eventDataValue":"1722"},{"_eventDataKey":"ShouldClampToSubdivisions","_eventDataValue":"True"}]},{"startBeatNumber":67,"endBeatNumber":68,"track":2,"clipin":0,"group":0,"type":"SpawnEnemy","dataPairs":[{"_eventDataKey":"EnemyId","_eventDataValue":"1722"},{"_eventDataKey":"ShouldClampToSubdivisions","_eventDataValue":"True"}]},{"startBeatNumber":68,"endBeatNumber":69,"track":3,"clipin":0,"group":0,"type":"SpawnEnemy","dataPairs":[{"_eventDataKey":"EnemyId","_eventDataValue":"1722"},{"_eventDataKey":"ShouldClampToSubdivisions","_eventDataValue":"True"}]},{"startBeatNumber":68.5,"endBeatNumber":70.5,"track":2,"clipin":0,"group":0,"type":"SpawnEnemy","dataPairs":[{"_eventDataKey":"EnemyId","_eventDataValue":"4355"},{"_eventDataKey":"ShouldClampToSubdivisions","_eventDataValue":"True"}]},{"startBeatNumber":69,"endBeatNumber":70,"track":1,"clipin":0,"group":0,"type":"SpawnEnemy","dataPairs":[{"_eventDataKey":"EnemyId","_eventDataValue":"1722"},{"_eventDataKey":"ShouldClampToSubdivisions","_eventDataValue":"True"}]},{"startBeatNumber":70.5,"endBeatNumber":71.5,"track":1,"clipin":0,"group":0,"type":"SpawnEnemy","dataPairs":[{"_eventDataKey":"EnemyId","_eventDataValue":"1722"},{"_eventDataKey":"ShouldClampToSubdivisions","_eventDataValue":"True"}]},{"startBeatNumber":71.5,"endBeatNumber":72.5,"track":2,"clipin":0,"group":0,"type":"SpawnEnemy","dataPairs":[{"_eventDataKey":"EnemyId","_eventDataValue":"1722"},{"_eventDataKey":"ShouldClampToSubdivisions","_eventDataValue":"True"}]},{"startBeatNumber":76,"endBeatNumber":77,"track":2,"clipin":0,"group":0,"type":"SpawnEnemy","dataPairs":[{"_eventDataKey":"EnemyId","_eventDataValue":"1722"},{"_eventDataKey":"ShouldClampToSubdivisions","_eventDataValue":"True"}]},{"startBeatNumber":76,"endBeatNumber":77,"track":3,"clipin":0,"group":0,"type":"SpawnEnemy","dataPairs":[{"_eventDataKey":"EnemyId","_eventDataValue":"1722"},{"_eventDataKey":"ShouldClampToSubdivisions","_eventDataValue":"True"}]},{"startBeatNumber":78,"endBeatNumber":79,"track":1,"clipin":0,"group":0,"type":"SpawnEnemy","dataPairs":[{"_eventDataKey":"EnemyId","_eventDataValue":"1722"},{"_eventDataKey":"ShouldClampToSubdivisions","_eventDataValue":"True"}]},{"startBeatNumber":78,"endBeatNumber":79,"track":2,"clipin":0,"group":0,"type":"SpawnEnemy","dataPairs":[{"_eventDataKey":"EnemyId","_eventDataValue":"1722"},{"_eventDataKey":"ShouldClampToSubdivisions","_eventDataValue":"True"}]},{"startBeatNumber":79,"endBeatNumber":82,"track":3,"clipin":0,"group":0,"type":"SpawnTrap","dataPairs":[{"_eventDataKey":"TrapDirection","_eventDataValue":"2"},{"_eventDataKey":"TrapTypeToSpawn","_eventDataValue":"Bounce"},{"_eventDataKey":"TrapDropRow","_eventDataValue":"2"},{"_eventDataKey":"TrapHealthInBeats","_eventDataValue":"8"}]},{"startBeatNumber":79.83333,"endBeatNumber":80.83333,"track":1,"clipin":0,"group":0,"type":"SpawnEnemy","dataPairs":[{"_eventDataKey":"EnemyId","_eventDataValue":"1722"},{"_eventDataKey":"ShouldClampToSubdivisions","_eventDataValue":"False"}]},{"startBeatNumber":79.83333,"endBeatNumber":80.83333,"track":3,"clipin":0,"group":0,"type":"SpawnEnemy","dataPairs":[{"_eventDataKey":"EnemyId","_eventDataValue":"1722"},{"_eventDataKey":"ShouldClampToSubdivisions","_eventDataValue":"False"}]},{"startBeatNumber":80,"endBeatNumber":83,"track":2,"clipin":0,"group":0,"type":"SpawnTrap","dataPairs":[{"_eventDataKey":"TrapDirection","_eventDataValue":"2"},{"_eventDataKey":"TrapTypeToSpawn","_eventDataValue":"Bounce"},{"_eventDataKey":"TrapDropRow","_eventDataValue":"2"},{"_eventDataKey":"TrapHealthInBeats","_eventDataValue":"7"}]},{"startBeatNumber":81,"endBeatNumber":84,"track":1,"clipin":0,"group":0,"type":"SpawnTrap","dataPairs":[{"_eventDataKey":"TrapDirection","_eventDataValue":"2"},{"_eventDataKey":"TrapTypeToSpawn","_eventDataValue":"Bounce"},{"_eventDataKey":"TrapDropRow","_eventDataValue":"2"},{"_eventDataKey":"TrapHealthInBeats","_eventDataValue":"6"}]},{"startBeatNumber":82,"endBeatNumber":83,"track":1,"clipin":0,"group":0,"type":"SpawnEnemy","dataPairs":[{"_eventDataKey":"EnemyId","_eventDataValue":"8519"},{"_eventDataKey":"ShouldClampToSubdivisions","_eventDataValue":"True"}]},{"startBeatNumber":82,"endBeatNumber":83,"track":3,"clipin":0,"group":0,"type":"SpawnEnemy","dataPairs":[{"_eventDataKey":"EnemyId","_eventDataValue":"8519"},{"_eventDataKey":"ShouldClampToSubdivisions","_eventDataValue":"True"}]},{"startBeatNumber":84,"endBeatNumber":85,"track":1,"clipin":0,"group":0,"type":"SpawnEnemy","dataPairs":[{"_eventDataKey":"EnemyId","_eventDataValue":"1722"},{"_eventDataKey":"ShouldClampToSubdivisions","_eventDataValue":"True"}]},{"startBeatNumber":84,"endBeatNumber":85,"track":3,"clipin":0,"group":0,"type":"SpawnEnemy","dataPairs":[{"_eventDataKey":"EnemyId","_eventDataValue":"1722"},{"_eventDataKey":"ShouldClampToSubdivisions","_eventDataValue":"True"}]},{"startBeatNumber":86,"endBeatNumber":87,"track":2,"clipin":0,"group":0,"type":"SpawnEnemy","dataPairs":[{"_eventDataKey":"EnemyId","_eventDataValue":"1722"},{"_eventDataKey":"ShouldClampToSubdivisions","_eventDataValue":"True"}]},{"startBeatNumber":86,"endBeatNumber":87,"track":3,"clipin":0,"group":0,"type":"SpawnEnemy","dataPairs":[{"_eventDataKey":"EnemyId","_eventDataValue":"1722"},{"_eventDataKey":"ShouldClampToSubdivisions","_eventDataValue":"True"}]},{"startBeatNumber":87.83333,"endBeatNumber":88.83333,"track":1,"clipin":0,"group":0,"type":"SpawnEnemy","dataPairs":[{"_eventDataKey":"EnemyId","_eventDataValue":"1722"},{"_eventDataKey":"ShouldClampToSubdivisions","_eventDataValue":"False"}]},{"startBeatNumber":87.83333,"endBeatNumber":88.83333,"track":2,"clipin":0,"group":0,"type":"SpawnEnemy","dataPairs":[{"_eventDataKey":"EnemyId","_eventDataValue":"1722"},{"_eventDataKey":"ShouldClampToSubdivisions","_eventDataValue":"False"}]},{"startBeatNumber":88,"endBeatNumber":91,"track":1,"clipin":0,"group":0,"type":"SpawnTrap","dataPairs":[{"_eventDataKey":"TrapDirection","_eventDataValue":"1"},{"_eventDataKey":"TrapTypeToSpawn","_eventDataValue":"Bounce"},{"_eventDataKey":"TrapDropRow","_eventDataValue":"2"},{"_eventDataKey":"TrapHealthInBeats","_eventDataValue":"8"}]},{"startBeatNumber":88,"endBeatNumber":91,"track":2,"clipin":0,"group":0,"type":"SpawnTrap","dataPairs":[{"_eventDataKey":"TrapDirection","_eventDataValue":"1"},{"_eventDataKey":"TrapTypeToSpawn","_eventDataValue":"Bounce"},{"_eventDataKey":"TrapDropRow","_eventDataValue":"2"},{"_eventDataKey":"TrapHealthInBeats","_eventDataValue":"8"}]},{"startBeatNumber":88,"endBeatNumber":91,"track":3,"clipin":0,"group":0,"type":"SpawnTrap","dataPairs":[{"_eventDataKey":"TrapDirection","_eventDataValue":"1"},{"_eventDataKey":"TrapTypeToSpawn","_eventDataValue":"Bounce"},{"_eventDataKey":"TrapDropRow","_eventDataValue":"2"},{"_eventDataKey":"TrapHealthInBeats","_eventDataValue":"8"}]},{"startBeatNumber":90,"endBeatNumber":91,"track":1,"clipin":0,"group":0,"type":"SpawnEnemy","dataPairs":[{"_eventDataKey":"EnemyId","_eventDataValue":"8519"},{"_eventDataKey":"ShouldClampToSubdivisions","_eventDataValue":"True"}]},{"startBeatNumber":90,"endBeatNumber":91,"track":2,"clipin":0,"group":0,"type":"SpawnEnemy","dataPairs":[{"_eventDataKey":"EnemyId","_eventDataValue":"8519"},{"_eventDataKey":"ShouldClampToSubdivisions","_eventDataValue":"True"}]},{"startBeatNumber":91.83334,"endBeatNumber":96.83333,"track":1,"clipin":0,"group":0,"type":"StartVibeChain","dataPairs":[{"_eventDataKey":"RiftedVibeChainShift","_eventDataValue":"91.83333"}]},{"startBeatNumber":92,"endBeatNumber":93,"track":2,"clipin":0,"group":0,"type":"SpawnEnemy","dataPairs":[{"_eventDataKey":"EnemyId","_eventDataValue":"1722"},{"_eventDataKey":"ShouldClampToSubdivisions","_eventDataValue":"True"}]},{"startBeatNumber":92,"endBeatNumber":93,"track":3,"clipin":0,"group":0,"type":"SpawnEnemy","dataPairs":[{"_eventDataKey":"EnemyId","_eventDataValue":"1722"},{"_eventDataKey":"ShouldClampToSubdivisions","_eventDataValue":"True"}]},{"startBeatNumber":94,"endBeatNumber":95,"track":1,"clipin":0,"group":0,"type":"SpawnEnemy","dataPairs":[{"_eventDataKey":"EnemyId","_eventDataValue":"1722"},{"_eventDataKey":"ShouldClampToSubdivisions","_eventDataValue":"True"}]},{"startBeatNumber":94,"endBeatNumber":95,"track":2,"clipin":0,"group":0,"type":"SpawnEnemy","dataPairs":[{"_eventDataKey":"EnemyId","_eventDataValue":"1722"},{"_eventDataKey":"ShouldClampToSubdivisions","_eventDataValue":"True"}]},{"startBeatNumber":95.83333,"endBeatNumber":96.83333,"track":1,"clipin":0,"group":0,"type":"SpawnEnemy","dataPairs":[{"_eventDataKey":"EnemyId","_eventDataValue":"1722"},{"_eventDataKey":"ShouldClampToSubdivisions","_eventDataValue":"False"}]},{"startBeatNumber":95.83333,"endBeatNumber":96.83333,"track":3,"clipin":0,"group":0,"type":"SpawnEnemy","dataPairs":[{"_eventDataKey":"EnemyId","_eventDataValue":"1722"},{"_eventDataKey":"ShouldClampToSubdivisions","_eventDataValue":"False"}]},{"startBeatNumber":97,"endBeatNumber":100,"track":1,"clipin":0,"group":0,"type":"SpawnTrap","dataPairs":[{"_eventDataKey":"TrapDirection","_eventDataValue":"2"},{"_eventDataKey":"TrapTypeToSpawn","_eventDataValue":"Bounce"},{"_eventDataKey":"TrapDropRow","_eventDataValue":"2"},{"_eventDataKey":"TrapHealthInBeats","_eventDataValue":"8"}]},{"startBeatNumber":97,"endBeatNumber":100,"track":2,"clipin":0,"group":0,"type":"SpawnTrap","dataPairs":[{"_eventDataKey":"TrapDirection","_eventDataValue":"2"},{"_eventDataKey":"TrapTypeToSpawn","_eventDataValue":"Bounce"},{"_eventDataKey":"TrapDropRow","_eventDataValue":"2"},{"_eventDataKey":"TrapHealthInBeats","_eventDataValue":"8"}]},{"startBeatNumber":97,"endBeatNumber":100,"track":3,"clipin":0,"group":0,"type":"SpawnTrap","dataPairs":[{"_eventDataKey":"TrapDirection","_eventDataValue":"2"},{"_eventDataKey":"TrapTypeToSpawn","_eventDataValue":"Bounce"},{"_eventDataKey":"TrapDropRow","_eventDataValue":"2"},{"_eventDataKey":"TrapHealthInBeats","_eventDataValue":"8"}]},{"startBeatNumber":97.83333,"endBeatNumber":98.83333,"track":1,"clipin":0,"group":0,"type":"SpawnEnemy","dataPairs":[{"_eventDataKey":"EnemyId","_eventDataValue":"8519"},{"_eventDataKey":"ShouldClampToSubdivisions","_eventDataValue":"False"}]},{"startBeatNumber":97.83333,"endBeatNumber":98.83333,"track":2,"clipin":0,"group":0,"type":"SpawnEnemy","dataPairs":[{"_eventDataKey":"EnemyId","_eventDataValue":"8519"},{"_eventDataKey":"ShouldClampToSubdivisions","_eventDataValue":"False"}]},{"startBeatNumber":100,"endBeatNumber":101,"track":1,"clipin":0,"group":0,"type":"SpawnEnemy","dataPairs":[{"_eventDataKey":"EnemyId","_eventDataValue":"7358"},{"_eventDataKey":"ShouldClampToSubdivisions","_eventDataValue":"True"}]},{"startBeatNumber":101,"endBeatNumber":102,"track":2,"clipin":0,"group":0,"type":"SpawnEnemy","dataPairs":[{"_eventDataKey":"EnemyId","_eventDataValue":"1722"},{"_eventDataKey":"ShouldClampToSubdivisions","_eventDataValue":"True"}]},{"startBeatNumber":102,"endBeatNumber":103,"track":3,"clipin":0,"group":0,"type":"SpawnEnemy","dataPairs":[{"_eventDataKey":"EnemyId","_eventDataValue":"1722"},{"_eventDataKey":"ShouldClampToSubdivisions","_eventDataValue":"True"}]},{"startBeatNumber":103,"endBeatNumber":104,"track":2,"clipin":0,"group":0,"type":"SpawnEnemy","dataPairs":[{"_eventDataKey":"EnemyId","_eventDataValue":"1722"},{"_eventDataKey":"ShouldClampToSubdivisions","_eventDataValue":"True"}]},{"startBeatNumber":104,"endBeatNumber":105,"track":3,"clipin":0,"group":0,"type":"SpawnEnemy","dataPairs":[{"_eventDataKey":"EnemyId","_eventDataValue":"1722"},{"_eventDataKey":"ShouldClampToSubdivisions","_eventDataValue":"True"}]},{"startBeatNumber":105,"endBeatNumber":106,"track":2,"clipin":0,"group":0,"type":"SpawnEnemy","dataPairs":[{"_eventDataKey":"EnemyId","_eventDataValue":"1722"},{"_eventDataKey":"ShouldClampToSubdivisions","_eventDataValue":"True"}]},{"startBeatNumber":106,"endBeatNumber":107,"track":1,"clipin":0,"group":0,"type":"SpawnTrap","dataPairs":[{"_eventDataKey":"TrapDirection","_eventDataValue":"0"},{"_eventDataKey":"TrapTypeToSpawn","_eventDataValue":"Bounce"},{"_eventDataKey":"TrapDropRow","_eventDataValue":"2"},{"_eventDataKey":"TrapHealthInBeats","_eventDataValue":"6"}]},{"startBeatNumber":108,"endBeatNumber":109,"track":1,"clipin":0,"group":0,"type":"SpawnEnemy","dataPairs":[{"_eventDataKey":"EnemyId","_eventDataValue":"7358"},{"_eventDataKey":"ShouldClampToSubdivisions","_eventDataValue":"True"}]},{"startBeatNumber":109,"endBeatNumber":110,"track":2,"clipin":0,"group":0,"type":"SpawnEnemy","dataPairs":[{"_eventDataKey":"EnemyId","_eventDataValue":"1722"},{"_eventDataKey":"ShouldClampToSubdivisions","_eventDataValue":"True"}]},{"startBeatNumber":110,"endBeatNumber":111,"track":3,"clipin":0,"group":0,"type":"SpawnEnemy","dataPairs":[{"_eventDataKey":"EnemyId","_eventDataValue":"1722"},{"_eventDataKey":"ShouldClampToSubdivisions","_eventDataValue":"True"}]},{"startBeatNumber":111,"endBeatNumber":112,"track":2,"clipin":0,"group":0,"type":"SpawnEnemy","dataPairs":[{"_eventDataKey":"EnemyId","_eventDataValue":"1722"},{"_eventDataKey":"ShouldClampToSubdivisions","_eventDataValue":"True"}]},{"startBeatNumber":112,"endBeatNumber":113,"track":3,"clipin":0,"group":0,"type":"SpawnEnemy","dataPairs":[{"_eventDataKey":"EnemyId","_eventDataValue":"1722"},{"_eventDataKey":"ShouldClampToSubdivisions","_eventDataValue":"True"}]},{"startBeatNumber":113,"endBeatNumber":114,"track":2,"clipin":0,"group":0,"type":"SpawnEnemy","dataPairs":[{"_eventDataKey":"EnemyId","_eventDataValue":"1722"},{"_eventDataKey":"ShouldClampToSubdivisions","_eventDataValue":"True"}]},{"startBeatNumber":114,"endBeatNumber":115,"track":1,"clipin":0,"group":0,"type":"SpawnTrap","dataPairs":[{"_eventDataKey":"TrapDirection","_eventDataValue":"0"},{"_eventDataKey":"TrapTypeToSpawn","_eventDataValue":"Bounce"},{"_eventDataKey":"TrapDropRow","_eventDataValue":"2"},{"_eventDataKey":"TrapHealthInBeats","_eventDataValue":"6"}]},{"startBeatNumber":116,"endBeatNumber":117,"track":3,"clipin":0,"group":0,"type":"SpawnEnemy","dataPairs":[{"_eventDataKey":"EnemyId","_eventDataValue":"8519"},{"_eventDataKey":"ShouldClampToSubdivisions","_eventDataValue":"True"}]},{"startBeatNumber":118,"endBeatNumber":119,"track":2,"clipin":0,"group":0,"type":"SpawnEnemy","dataPairs":[{"_eventDataKey":"EnemyId","_eventDataValue":"8519"},{"_eventDataKey":"ShouldClampToSubdivisions","_eventDataValue":"True"}]},{"startBeatNumber":120,"endBeatNumber":121,"track":1,"clipin":0,"group":0,"type":"SpawnEnemy","dataPairs":[{"_eventDataKey":"EnemyId","_eventDataValue":"8519"},{"_eventDataKey":"ShouldClampToSubdivisions","_eventDataValue":"True"}]},{"startBeatNumber":122,"endBeatNumber":123,"track":3,"clipin":0,"group":0,"type":"SpawnEnemy","dataPairs":[{"_eventDataKey":"EnemyId","_eventDataValue":"1234"},{"_eventDataKey":"ShouldClampToSubdivisions","_eventDataValue":"True"}]},{"startBeatNumber":123,"endBeatNumber":124,"track":2,"clipin":0,"group":0,"type":"SpawnEnemy","dataPairs":[{"_eventDataKey":"EnemyId","_eventDataValue":"1234"},{"_eventDataKey":"ShouldClampToSubdivisions","_eventDataValue":"True"}]},{"startBeatNumber":124,"endBeatNumber":125,"track":1,"clipin":0,"group":0,"type":"SpawnEnemy","dataPairs":[{"_eventDataKey":"EnemyId","_eventDataValue":"1234"},{"_eventDataKey":"ShouldStartFacingRight","_eventDataValue":"True"},{"_eventDataKey":"ShouldClampToSubdivisions","_eventDataValue":"True"}]},{"startBeatNumber":126.5,"endBeatNumber":127.5,"audioEvents":[],"track":1,"clipin":0,"group":0,"type":"SpawnEnemy","dataPairs":[{"_eventDataKey":"EnemyId","_eventDataValue":"1722"},{"_eventDataKey":"ShouldStartFacingRight","_eventDataValue":"True"},{"_eventDataKey":"ShouldClampToSubdivisions","_eventDataValue":"True"}]},{"startBeatNumber":127.25,"endBeatNumber":128.25,"audioEvents":[],"track":2,"clipin":0,"group":0,"type":"SpawnEnemy","dataPairs":[{"_eventDataKey":"EnemyId","_eventDataValue":"1722"},{"_eventDataKey":"ShouldStartFacingRight","_eventDataValue":"True"},{"_eventDataKey":"ShouldClampToSubdivisions","_eventDataValue":"True"}]},{"startBeatNumber":128,"endBeatNumber":129,"audioEvents":[],"track":1,"clipin":0,"group":0,"type":"SpawnEnemy","dataPairs":[{"_eventDataKey":"EnemyId","_eventDataValue":"1722"},{"_eventDataKey":"ShouldStartFacingRight","_eventDataValue":"True"},{"_eventDataKey":"ShouldClampToSubdivisions","_eventDataValue":"True"}]},{"startBeatNumber":130,"endBeatNumber":131,"track":1,"clipin":0,"group":0,"type":"SpawnEnemy","dataPairs":[{"_eventDataKey":"EnemyId","_eventDataValue":"1234"},{"_eventDataKey":"ShouldStartFacingRight","_eventDataValue":"True"},{"_eventDataKey":"ShouldClampToSubdivisions","_eventDataValue":"True"}]},{"startBeatNumber":131,"endBeatNumber":132,"track":2,"clipin":0,"group":0,"type":"SpawnEnemy","dataPairs":[{"_eventDataKey":"EnemyId","_eventDataValue":"1234"},{"_eventDataKey":"ShouldClampToSubdivisions","_eventDataValue":"True"}]},{"startBeatNumber":132,"endBeatNumber":133,"track":3,"clipin":0,"group":0,"type":"SpawnEnemy","dataPairs":[{"_eventDataKey":"EnemyId","_eventDataValue":"1234"},{"_eventDataKey":"ShouldStartFacingRight","_eventDataValue":"True"},{"_eventDataKey":"ShouldClampToSubdivisions","_eventDataValue":"True"}]},{"startBeatNumber":134.5,"endBeatNumber":135.5,"audioEvents":[],"track":3,"clipin":0,"group":0,"type":"SpawnEnemy","dataPairs":[{"_eventDataKey":"EnemyId","_eventDataValue":"1722"},{"_eventDataKey":"ShouldStartFacingRight","_eventDataValue":"True"},{"_eventDataKey":"ShouldClampToSubdivisions","_eventDataValue":"True"}]},{"startBeatNumber":135.25,"endBeatNumber":136.25,"audioEvents":[],"track":2,"clipin":0,"group":0,"type":"SpawnEnemy","dataPairs":[{"_eventDataKey":"EnemyId","_eventDataValue":"1722"},{"_eventDataKey":"ShouldStartFacingRight","_eventDataValue":"True"},{"_eventDataKey":"ShouldClampToSubdivisions","_eventDataValue":"True"}]},{"startBeatNumber":136,"endBeatNumber":137,"audioEvents":[],"track":3,"clipin":0,"group":0,"type":"SpawnEnemy","dataPairs":[{"_eventDataKey":"EnemyId","_eventDataValue":"1722"},{"_eventDataKey":"ShouldStartFacingRight","_eventDataValue":"True"},{"_eventDataKey":"ShouldClampToSubdivisions","_eventDataValue":"True"}]},{"startBeatNumber":138,"endBeatNumber":140,"track":3,"clipin":0,"group":0,"type":"SpawnEnemy","dataPairs":[{"_eventDataKey":"EnemyId","_eventDataValue":"4355"},{"_eventDataKey":"ShouldClampToSubdivisions","_eventDataValue":"True"}]},{"startBeatNumber":140,"endBeatNumber":141,"track":2,"clipin":0,"group":0,"type":"SpawnEnemy","dataPairs":[{"_eventDataKey":"EnemyId","_eventDataValue":"1722"},{"_eventDataKey":"ShouldClampToSubdivisions","_eventDataValue":"True"}]},{"startBeatNumber":142.5,"endBeatNumber":143.5,"audioEvents":[],"track":1,"clipin":0,"group":0,"type":"SpawnEnemy","dataPairs":[{"_eventDataKey":"EnemyId","_eventDataValue":"1722"},{"_eventDataKey":"ShouldStartFacingRight","_eventDataValue":"True"},{"_eventDataKey":"ShouldClampToSubdivisions","_eventDataValue":"True"}]},{"startBeatNumber":143,"endBeatNumber":144,"track":1,"clipin":0,"group":0,"type":"SpawnTrap","dataPairs":[{"_eventDataKey":"TrapDirection","_eventDataValue":"2"},{"_eventDataKey":"TrapTypeToSpawn","_eventDataValue":"Bounce"},{"_eventDataKey":"TrapDropRow","_eventDataValue":"2"},{"_eventDataKey":"TrapHealthInBeats","_eventDataValue":"21"}]},{"startBeatNumber":143,"endBeatNumber":144,"track":3,"clipin":0,"group":0,"type":"SpawnTrap","dataPairs":[{"_eventDataKey":"TrapDirection","_eventDataValue":"1"},{"_eventDataKey":"TrapTypeToSpawn","_eventDataValue":"Bounce"},{"_eventDataKey":"TrapDropRow","_eventDataValue":"2"},{"_eventDataKey":"TrapHealthInBeats","_eventDataValue":"21"}]},{"startBeatNumber":143.25,"endBeatNumber":144.25,"audioEvents":[],"track":3,"clipin":0,"group":0,"type":"SpawnEnemy","dataPairs":[{"_eventDataKey":"EnemyId","_eventDataValue":"1722"},{"_eventDataKey":"ShouldStartFacingRight","_eventDataValue":"True"},{"_eventDataKey":"ShouldClampToSubdivisions","_eventDataValue":"True"}]},{"startBeatNumber":144,"endBeatNumber":145,"track":2,"clipin":0,"group":0,"type":"SpawnEnemy","dataPairs":[{"_eventDataKey":"EnemyId","_eventDataValue":"7358"},{"_eventDataKey":"ShouldClampToSubdivisions","_eventDataValue":"True"}]},{"startBeatNumber":146.01319,"endBeatNumber":148.01319,"track":1,"clipin":0,"group":0,"type":"SpawnEnemy","dataPairs":[{"_eventDataKey":"EnemyId","_eventDataValue":"4355"},{"_eventDataKey":"ShouldClampToSubdivisions","_eventDataValue":"False"}]},{"startBeatNumber":148.01319,"endBeatNumber":149.01319,"track":2,"clipin":0,"group":0,"type":"SpawnEnemy","dataPairs":[{"_eventDataKey":"EnemyId","_eventDataValue":"1722"},{"_eventDataKey":"ShouldClampToSubdivisions","_eventDataValue":"False"}]},{"startBeatNumber":150.5,"endBeatNumber":151.5,"audioEvents":[],"track":3,"clipin":0,"group":0,"type":"SpawnEnemy","dataPairs":[{"_eventDataKey":"EnemyId","_eventDataValue":"1722"},{"_eventDataKey":"ShouldStartFacingRight","_eventDataValue":"True"},{"_eventDataKey":"ShouldClampToSubdivisions","_eventDataValue":"True"}]},{"startBeatNumber":151.25,"endBeatNumber":152.25,"audioEvents":[],"track":1,"clipin":0,"group":0,"type":"SpawnEnemy","dataPairs":[{"_eventDataKey":"EnemyId","_eventDataValue":"1722"},{"_eventDataKey":"ShouldStartFacingRight","_eventDataValue":"True"},{"_eventDataKey":"ShouldClampToSubdivisions","_eventDataValue":"True"}]},{"startBeatNumber":152,"endBeatNumber":153,"track":2,"clipin":0,"group":0,"type":"SpawnEnemy","dataPairs":[{"_eventDataKey":"EnemyId","_eventDataValue":"7358"},{"_eventDataKey":"ShouldClampToSubdivisions","_eventDataValue":"True"}]},{"startBeatNumber":154,"endBeatNumber":155,"track":3,"clipin":0,"group":0,"type":"SpawnEnemy","dataPairs":[{"_eventDataKey":"EnemyId","_eventDataValue":"1722"},{"_eventDataKey":"ShouldClampToSubdivisions","_eventDataValue":"True"}]},{"startBeatNumber":155,"endBeatNumber":156,"track":2,"clipin":0,"group":0,"type":"SpawnEnemy","dataPairs":[{"_eventDataKey":"EnemyId","_eventDataValue":"1722"},{"_eventDataKey":"ShouldClampToSubdivisions","_eventDataValue":"True"}]},{"startBeatNumber":156,"endBeatNumber":157,"track":1,"clipin":0,"group":0,"type":"SpawnEnemy","dataPairs":[{"_eventDataKey":"EnemyId","_eventDataValue":"1722"},{"_eventDataKey":"ShouldClampToSubdivisions","_eventDataValue":"True"}]},{"startBeatNumber":158,"endBeatNumber":159,"track":1,"clipin":0,"group":0,"type":"SpawnEnemy","dataPairs":[{"_eventDataKey":"EnemyId","_eventDataValue":"1722"},{"_eventDataKey":"ShouldClampToSubdivisions","_eventDataValue":"True"}]},{"startBeatNumber":158,"endBeatNumber":159,"track":2,"clipin":0,"group":0,"type":"SpawnEnemy","dataPairs":[{"_eventDataKey":"EnemyId","_eventDataValue":"1722"},{"_eventDataKey":"ShouldClampToSubdivisions","_eventDataValue":"True"}]},{"startBeatNumber":162,"endBeatNumber":165,"track":2,"clipin":0,"group":0,"type":"SpawnEnemy","dataPairs":[{"_eventDataKey":"EnemyId","_eventDataValue":"8156"},{"_eventDataKey":"ShouldClampToSubdivisions","_eventDataValue":"True"}]},{"startBeatNumber":163.5,"endBeatNumber":164.5,"track":1,"clipin":0,"group":0,"type":"SpawnEnemy","dataPairs":[{"_eventDataKey":"EnemyId","_eventDataValue":"8519"},{"_eventDataKey":"ShouldClampToSubdivisions","_eventDataValue":"True"}]},{"startBeatNumber":165.83334,"endBeatNumber":177,"track":1,"clipin":0,"group":0,"type":"StartVibeChain","dataPairs":[{"_eventDataKey":"RiftedVibeChainShift","_eventDataValue":"165.83333"}]},{"startBeatNumber":166,"endBeatNumber":169,"track":2,"clipin":0,"group":0,"type":"SpawnEnemy","dataPairs":[{"_eventDataKey":"EnemyId","_eventDataValue":"8156"},{"_eventDataKey":"ShouldClampToSubdivisions","_eventDataValue":"True"}]},{"startBeatNumber":167.5,"endBeatNumber":168.5,"track":3,"clipin":0,"group":0,"type":"SpawnEnemy","dataPairs":[{"_eventDataKey":"EnemyId","_eventDataValue":"8519"},{"_eventDataKey":"ShouldClampToSubdivisions","_eventDataValue":"True"}]},{"startBeatNumber":170,"endBeatNumber":173,"track":2,"clipin":0,"group":0,"type":"SpawnEnemy","dataPairs":[{"_eventDataKey":"EnemyId","_eventDataValue":"8156"},{"_eventDataKey":"ShouldClampToSubdivisions","_eventDataValue":"True"}]},{"startBeatNumber":171.5,"endBeatNumber":172.5,"track":1,"clipin":0,"group":0,"type":"SpawnEnemy","dataPairs":[{"_eventDataKey":"EnemyId","_eventDataValue":"8519"},{"_eventDataKey":"ShouldClampToSubdivisions","_eventDataValue":"True"}]},{"startBeatNumber":174,"endBeatNumber":177,"track":2,"clipin":0,"group":0,"type":"SpawnEnemy","dataPairs":[{"_eventDataKey":"EnemyId","_eventDataValue":"8156"},{"_eventDataKey":"ShouldClampToSubdivisions","_eventDataValue":"True"}]},{"startBeatNumber":175.5,"endBeatNumber":176.5,"track":3,"clipin":0,"group":0,"type":"SpawnEnemy","dataPairs":[{"_eventDataKey":"EnemyId","_eventDataValue":"8519"},{"_eventDataKey":"ShouldClampToSubdivisions","_eventDataValue":"True"}]},{"startBeatNumber":178,"endBeatNumber":181,"track":2,"clipin":0,"group":0,"type":"SpawnEnemy","dataPairs":[{"_eventDataKey":"EnemyId","_eventDataValue":"8156"},{"_eventDataKey":"ShouldClampToSubdivisions","_eventDataValue":"True"}]},{"startBeatNumber":178,"endBeatNumber":179,"audioEvents":[],"track":3,"clipin":0,"group":0,"type":"SpawnEnemy","dataPairs":[{"_eventDataKey":"EnemyId","_eventDataValue":"7358"},{"_eventDataKey":"ShouldStartFacingRight","_eventDataValue":"False"},{"_eventDataKey":"ShouldClampToSubdivisions","_eventDataValue":"True"}]},{"startBeatNumber":179.5,"endBeatNumber":180.5,"track":1,"clipin":0,"group":0,"type":"SpawnEnemy","dataPairs":[{"_eventDataKey":"EnemyId","_eventDataValue":"8519"},{"_eventDataKey":"ShouldClampToSubdivisions","_eventDataValue":"True"}]},{"startBeatNumber":182,"endBeatNumber":185,"track":2,"clipin":0,"group":0,"type":"SpawnEnemy","dataPairs":[{"_eventDataKey":"EnemyId","_eventDataValue":"8156"},{"_eventDataKey":"ShouldClampToSubdivisions","_eventDataValue":"True"}]},{"startBeatNumber":183.5,"endBeatNumber":184.5,"track":3,"clipin":0,"group":0,"type":"SpawnEnemy","dataPairs":[{"_eventDataKey":"EnemyId","_eventDataValue":"8519"},{"_eventDataKey":"ShouldClampToSubdivisions","_eventDataValue":"True"}]},{"startBeatNumber":186,"endBeatNumber":189,"track":2,"clipin":0,"group":0,"type":"SpawnEnemy","dataPairs":[{"_eventDataKey":"EnemyId","_eventDataValue":"8156"},{"_eventDataKey":"ShouldClampToSubdivisions","_eventDataValue":"True"}]},{"startBeatNumber":187.5,"endBeatNumber":188.5,"track":1,"clipin":0,"group":0,"type":"SpawnEnemy","dataPairs":[{"_eventDataKey":"EnemyId","_eventDataValue":"8519"},{"_eventDataKey":"ShouldClampToSubdivisions","_eventDataValue":"True"}]},{"startBeatNumber":190,"endBeatNumber":191,"track":1,"clipin":0,"group":0,"type":"SpawnEnemy","dataPairs":[{"_eventDataKey":"EnemyId","_eventDataValue":"8156"},{"_eventDataKey":"ShouldClampToSubdivisions","_eventDataValue":"True"}]},{"startBeatNumber":190,"endBeatNumber":191,"track":2,"clipin":0,"group":0,"type":"SpawnEnemy","dataPairs":[{"_eventDataKey":"EnemyId","_eventDataValue":"8156"},{"_eventDataKey":"ShouldClampToSubdivisions","_eventDataValue":"True"}]},{"startBeatNumber":191,"endBeatNumber":192,"track":3,"clipin":0,"group":0,"type":"SpawnEnemy","dataPairs":[{"_eventDataKey":"EnemyId","_eventDataValue":"8519"},{"_eventDataKey":"ShouldClampToSubdivisions","_eventDataValue":"True"}]},{"startBeatNumber":193,"endBeatNumber":196,"track":3,"clipin":0,"group":0,"type":"SpawnTrap","dataPairs":[{"_eventDataKey":"TrapDirection","_eventDataValue":"1"},{"_eventDataKey":"TrapTypeToSpawn","_eventDataValue":"Bounce"},{"_eventDataKey":"TrapDropRow","_eventDataValue":"2"},{"_eventDataKey":"TrapHealthInBeats","_eventDataValue":"12"}]},{"startBeatNumber":194,"endBeatNumber":195,"track":1,"clipin":0,"group":0,"type":"SpawnEnemy","dataPairs":[{"_eventDataKey":"EnemyId","_eventDataValue":"1722"},{"_eventDataKey":"ShouldClampToSubdivisions","_eventDataValue":"True"}]},{"startBeatNumber":194,"endBeatNumber":195,"track":3,"clipin":0,"group":0,"type":"SpawnEnemy","dataPairs":[{"_eventDataKey":"EnemyId","_eventDataValue":"1722"},{"_eventDataKey":"ShouldClampToSubdivisions","_eventDataValue":"True"}]},{"startBeatNumber":194,"endBeatNumber":197,"track":2,"clipin":0,"group":0,"type":"SpawnTrap","dataPairs":[{"_eventDataKey":"TrapDirection","_eventDataValue":"1"},{"_eventDataKey":"TrapTypeToSpawn","_eventDataValue":"Bounce"},{"_eventDataKey":"TrapDropRow","_eventDataValue":"2"},{"_eventDataKey":"TrapHealthInBeats","_eventDataValue":"11"}]},{"startBeatNumber":195,"endBeatNumber":198,"track":1,"clipin":0,"group":0,"type":"SpawnTrap","dataPairs":[{"_eventDataKey":"TrapDirection","_eventDataValue":"1"},{"_eventDataKey":"TrapTypeToSpawn","_eventDataValue":"Bounce"},{"_eventDataKey":"TrapDropRow","_eventDataValue":"2"},{"_eventDataKey":"TrapHealthInBeats","_eventDataValue":"10"}]},{"startBeatNumber":196,"endBeatNumber":197,"track":2,"clipin":0,"group":0,"type":"SpawnEnemy","dataPairs":[{"_eventDataKey":"EnemyId","_eventDataValue":"1722"},{"_eventDataKey":"ShouldClampToSubdivisions","_eventDataValue":"True"}]},{"startBeatNumber":196,"endBeatNumber":197,"track":3,"clipin":0,"group":0,"type":"SpawnEnemy","dataPairs":[{"_eventDataKey":"EnemyId","_eventDataValue":"1722"},{"_eventDataKey":"ShouldClampToSubdivisions","_eventDataValue":"True"}]},{"startBeatNumber":197.83333,"endBeatNumber":198.83333,"track":1,"clipin":0,"group":0,"type":"SpawnEnemy","dataPairs":[{"_eventDataKey":"EnemyId","_eventDataValue":"1722"},{"_eventDataKey":"ShouldClampToSubdivisions","_eventDataValue":"False"}]},{"startBeatNumber":197.83333,"endBeatNumber":198.83333,"track":2,"clipin":0,"group":0,"type":"SpawnEnemy","dataPairs":[{"_eventDataKey":"EnemyId","_eventDataValue":"1722"},{"_eventDataKey":"ShouldClampToSubdivisions","_eventDataValue":"False"}]},{"startBeatNumber":200,"endBeatNumber":201,"track":2,"clipin":0,"group":0,"type":"SpawnEnemy","dataPairs":[{"_eventDataKey":"EnemyId","_eventDataValue":"8519"},{"_eventDataKey":"ShouldClampToSubdivisions","_eventDataValue":"True"}]},{"startBeatNumber":200,"endBeatNumber":201,"track":3,"clipin":0,"group":0,"type":"SpawnEnemy","dataPairs":[{"_eventDataKey":"EnemyId","_eventDataValue":"8519"},{"_eventDataKey":"ShouldClampToSubdivisions","_eventDataValue":"True"}]},{"startBeatNumber":202,"endBeatNumber":203,"track":2,"clipin":0,"group":0,"type":"SpawnEnemy","dataPairs":[{"_eventDataKey":"EnemyId","_eventDataValue":"1722"},{"_eventDataKey":"ShouldClampToSubdivisions","_eventDataValue":"True"}]},{"startBeatNumber":202,"endBeatNumber":203,"track":3,"clipin":0,"group":0,"type":"SpawnEnemy","dataPairs":[{"_eventDataKey":"EnemyId","_eventDataValue":"1722"},{"_eventDataKey":"ShouldClampToSubdivisions","_eventDataValue":"True"}]},{"startBeatNumber":204,"endBeatNumber":205,"track":1,"clipin":0,"group":0,"type":"SpawnEnemy","dataPairs":[{"_eventDataKey":"EnemyId","_eventDataValue":"1722"},{"_eventDataKey":"ShouldClampToSubdivisions","_eventDataValue":"True"}]},{"startBeatNumber":204,"endBeatNumber":205,"track":2,"clipin":0,"group":0,"type":"SpawnEnemy","dataPairs":[{"_eventDataKey":"EnemyId","_eventDataValue":"1722"},{"_eventDataKey":"ShouldClampToSubdivisions","_eventDataValue":"True"}]},{"startBeatNumber":205.83333,"endBeatNumber":206.83333,"track":1,"clipin":0,"group":0,"type":"SpawnEnemy","dataPairs":[{"_eventDataKey":"EnemyId","_eventDataValue":"1722"},{"_eventDataKey":"ShouldClampToSubdivisions","_eventDataValue":"False"}]},{"startBeatNumber":205.83333,"endBeatNumber":206.83333,"track":3,"clipin":0,"group":0,"type":"SpawnEnemy","dataPairs":[{"_eventDataKey":"EnemyId","_eventDataValue":"1722"},{"_eventDataKey":"ShouldClampToSubdivisions","_eventDataValue":"False"}]},{"startBeatNumber":207,"endBeatNumber":210,"track":1,"clipin":0,"group":0,"type":"SpawnTrap","dataPairs":[{"_eventDataKey":"TrapDirection","_eventDataValue":"2"},{"_eventDataKey":"TrapTypeToSpawn","_eventDataValue":"Bounce"},{"_eventDataKey":"TrapDropRow","_eventDataValue":"2"},{"_eventDataKey":"TrapHealthInBeats","_eventDataValue":"6"}]},{"startBeatNumber":207,"endBeatNumber":210,"track":2,"clipin":0,"group":0,"type":"SpawnTrap","dataPairs":[{"_eventDataKey":"TrapDirection","_eventDataValue":"2"},{"_eventDataKey":"TrapTypeToSpawn","_eventDataValue":"Bounce"},{"_eventDataKey":"TrapDropRow","_eventDataValue":"2"},{"_eventDataKey":"TrapHealthInBeats","_eventDataValue":"6"}]},{"startBeatNumber":207,"endBeatNumber":210,"track":3,"clipin":0,"group":0,"type":"SpawnTrap","dataPairs":[{"_eventDataKey":"TrapDirection","_eventDataValue":"2"},{"_eventDataKey":"TrapTypeToSpawn","_eventDataValue":"Bounce"},{"_eventDataKey":"TrapDropRow","_eventDataValue":"2"},{"_eventDataKey":"TrapHealthInBeats","_eventDataValue":"6"}]},{"startBeatNumber":208,"endBeatNumber":209,"track":1,"clipin":0,"group":0,"type":"SpawnEnemy","dataPairs":[{"_eventDataKey":"EnemyId","_eventDataValue":"8519"},{"_eventDataKey":"ShouldClampToSubdivisions","_eventDataValue":"True"}]},{"startBeatNumber":208,"endBeatNumber":209,"track":3,"clipin":0,"group":0,"type":"SpawnEnemy","dataPairs":[{"_eventDataKey":"EnemyId","_eventDataValue":"8519"},{"_eventDataKey":"ShouldClampToSubdivisions","_eventDataValue":"True"}]},{"startBeatNumber":209.83334,"endBeatNumber":216.83333,"track":1,"clipin":0,"group":0,"type":"StartVibeChain","dataPairs":[{"_eventDataKey":"RiftedVibeChainShift","_eventDataValue":"209.83333"}]},{"startBeatNumber":210,"endBeatNumber":211,"track":1,"clipin":0,"group":0,"type":"SpawnEnemy","dataPairs":[{"_eventDataKey":"EnemyId","_eventDataValue":"1722"},{"_eventDataKey":"ShouldClampToSubdivisions","_eventDataValue":"True"}]},{"startBeatNumber":210,"endBeatNumber":211,"track":3,"clipin":0,"group":0,"type":"SpawnEnemy","dataPairs":[{"_eventDataKey":"EnemyId","_eventDataValue":"1722"},{"_eventDataKey":"ShouldClampToSubdivisions","_eventDataValue":"True"}]},{"startBeatNumber":212,"endBeatNumber":213,"track":2,"clipin":0,"group":0,"type":"SpawnEnemy","dataPairs":[{"_eventDataKey":"EnemyId","_eventDataValue":"1722"},{"_eventDataKey":"ShouldClampToSubdivisions","_eventDataValue":"True"}]},{"startBeatNumber":212,"endBeatNumber":213,"track":3,"clipin":0,"group":0,"type":"SpawnEnemy","dataPairs":[{"_eventDataKey":"EnemyId","_eventDataValue":"1722"},{"_eventDataKey":"ShouldClampToSubdivisions","_eventDataValue":"True"}]},{"startBeatNumber":213.83333,"endBeatNumber":214.83333,"track":1,"clipin":0,"group":0,"type":"SpawnEnemy","dataPairs":[{"_eventDataKey":"EnemyId","_eventDataValue":"1722"},{"_eventDataKey":"ShouldClampToSubdivisions","_eventDataValue":"False"}]},{"startBeatNumber":213.83333,"endBeatNumber":214.83333,"track":2,"clipin":0,"group":0,"type":"SpawnEnemy","dataPairs":[{"_eventDataKey":"EnemyId","_eventDataValue":"1722"},{"_eventDataKey":"ShouldClampToSubdivisions","_eventDataValue":"False"}]},{"startBeatNumber":214,"endBeatNumber":217,"track":1,"clipin":0,"group":0,"type":"SpawnTrap","dataPairs":[{"_eventDataKey":"TrapDirection","_eventDataValue":"1"},{"_eventDataKey":"TrapTypeToSpawn","_eventDataValue":"Bounce"},{"_eventDataKey":"TrapDropRow","_eventDataValue":"2"},{"_eventDataKey":"TrapHealthInBeats","_eventDataValue":"10"}]},{"startBeatNumber":214,"endBeatNumber":217,"track":2,"clipin":0,"group":0,"type":"SpawnTrap","dataPairs":[{"_eventDataKey":"TrapDirection","_eventDataValue":"1"},{"_eventDataKey":"TrapTypeToSpawn","_eventDataValue":"Bounce"},{"_eventDataKey":"TrapDropRow","_eventDataValue":"2"},{"_eventDataKey":"TrapHealthInBeats","_eventDataValue":"9"}]},{"startBeatNumber":214,"endBeatNumber":217,"track":3,"clipin":0,"group":0,"type":"SpawnTrap","dataPairs":[{"_eventDataKey":"TrapDirection","_eventDataValue":"1"},{"_eventDataKey":"TrapTypeToSpawn","_eventDataValue":"Bounce"},{"_eventDataKey":"TrapDropRow","_eventDataValue":"2"},{"_eventDataKey":"TrapHealthInBeats","_eventDataValue":"8"}]},{"startBeatNumber":215.83333,"endBeatNumber":216.83333,"track":1,"clipin":0,"group":0,"type":"SpawnEnemy","dataPairs":[{"_eventDataKey":"EnemyId","_eventDataValue":"8519"},{"_eventDataKey":"ShouldClampToSubdivisions","_eventDataValue":"False"}]},{"startBeatNumber":215.83333,"endBeatNumber":216.83333,"track":2,"clipin":0,"group":0,"type":"SpawnEnemy","dataPairs":[{"_eventDataKey":"EnemyId","_eventDataValue":"8519"},{"_eventDataKey":"ShouldClampToSubdivisions","_eventDataValue":"False"}]},{"startBeatNumber":219,"endBeatNumber":220,"track":3,"clipin":0,"group":0,"type":"SpawnEnemy","dataPairs":[{"_eventDataKey":"EnemyId","_eventDataValue":"7358"},{"_eventDataKey":"ShouldClampToSubdivisions","_eventDataValue":"True"}]},{"startBeatNumber":220,"endBeatNumber":221,"track":2,"clipin":0,"group":0,"type":"SpawnEnemy","dataPairs":[{"_eventDataKey":"EnemyId","_eventDataValue":"8519"},{"_eventDataKey":"ShouldClampToSubdivisions","_eventDataValue":"True"}]},{"startBeatNumber":222,"endBeatNumber":223,"audioEvents":[],"track":1,"clipin":0,"group":0,"type":"SpawnEnemy","dataPairs":[{"_eventDataKey":"EnemyId","_eventDataValue":"8519"},{"_eventDataKey":"ShouldStartFacingRight","_eventDataValue":"True"},{"_eventDataKey":"ShouldClampToSubdivisions","_eventDataValue":"True"}]},{"startBeatNumber":225,"endBeatNumber":226,"track":3,"clipin":0,"group":0,"type":"SpawnEnemy","dataPairs":[{"_eventDataKey":"EnemyId","_eventDataValue":"7358"},{"_eventDataKey":"ShouldClampToSubdivisions","_eventDataValue":"True"}]},{"startBeatNumber":226,"endBeatNumber":227,"track":1,"clipin":0,"group":0,"type":"SpawnEnemy","dataPairs":[{"_eventDataKey":"EnemyId","_eventDataValue":"8156"},{"_eventDataKey":"ShouldClampToSubdivisions","_eventDataValue":"True"}]},{"startBeatNumber":226,"endBeatNumber":227,"track":3,"clipin":0,"group":0,"type":"SpawnEnemy","dataPairs":[{"_eventDataKey":"EnemyId","_eventDataValue":"8156"},{"_eventDataKey":"ShouldClampToSubdivisions","_eventDataValue":"True"}]},{"startBeatNumber":227,"endBeatNumber":228,"track":2,"clipin":0,"group":0,"type":"SpawnEnemy","dataPairs":[{"_eventDataKey":"EnemyId","_eventDataValue":"8519"},{"_eventDataKey":"ShouldClampToSubdivisions","_eventDataValue":"True"}]},{"startBeatNumber":232,"endBeatNumber":233,"audioEvents":[],"track":1,"clipin":0,"group":0,"type":"SpawnEnemy","dataPairs":[{"_eventDataKey":"EnemyId","_eventDataValue":"1722"},{"_eventDataKey":"ShouldStartFacingRight","_eventDataValue":"True"},{"_eventDataKey":"ShouldClampToSubdivisions","_eventDataValue":"True"}]},{"startBeatNumber":233,"endBeatNumber":234,"audioEvents":[],"track":2,"clipin":0,"group":0,"type":"SpawnEnemy","dataPairs":[{"_eventDataKey":"EnemyId","_eventDataValue":"1722"},{"_eventDataKey":"ShouldStartFacingRight","_eventDataValue":"True"},{"_eventDataKey":"ShouldClampToSubdivisions","_eventDataValue":"True"}]},{"startBeatNumber":234,"endBeatNumber":235,"audioEvents":[],"track":3,"clipin":0,"group":0,"type":"SpawnEnemy","dataPairs":[{"_eventDataKey":"EnemyId","_eventDataValue":"1236"},{"_eventDataKey":"ShouldStartFacingRight","_eventDataValue":"False"},{"_eventDataKey":"ShouldClampToSubdivisions","_eventDataValue":"True"}]},{"startBeatNumber":235,"endBeatNumber":236,"audioEvents":[],"track":1,"clipin":0,"group":0,"type":"SpawnEnemy","dataPairs":[{"_eventDataKey":"EnemyId","_eventDataValue":"1236"},{"_eventDataKey":"ShouldStartFacingRight","_eventDataValue":"False"},{"_eventDataKey":"ShouldClampToSubdivisions","_eventDataValue":"True"}]},{"startBeatNumber":236,"endBeatNumber":237,"audioEvents":[],"track":1,"clipin":0,"group":0,"type":"SpawnEnemy","dataPairs":[{"_eventDataKey":"EnemyId","_eventDataValue":"1722"},{"_eventDataKey":"ShouldStartFacingRight","_eventDataValue":"True"},{"_eventDataKey":"ShouldClampToSubdivisions","_eventDataValue":"True"}]},{"startBeatNumber":237,"endBeatNumber":238,"audioEvents":[],"track":2,"clipin":0,"group":0,"type":"SpawnEnemy","dataPairs":[{"_eventDataKey":"EnemyId","_eventDataValue":"1722"},{"_eventDataKey":"ShouldStartFacingRight","_eventDataValue":"True"},{"_eventDataKey":"ShouldClampToSubdivisions","_eventDataValue":"True"}]},{"startBeatNumber":238,"endBeatNumber":239,"audioEvents":[],"track":3,"clipin":0,"group":0,"type":"SpawnEnemy","dataPairs":[{"_eventDataKey":"EnemyId","_eventDataValue":"1236"},{"_eventDataKey":"ShouldStartFacingRight","_eventDataValue":"False"},{"_eventDataKey":"ShouldClampToSubdivisions","_eventDataValue":"True"}]},{"startBeatNumber":239,"endBeatNumber":240,"audioEvents":[],"track":1,"clipin":0,"group":0,"type":"SpawnEnemy","dataPairs":[{"_eventDataKey":"EnemyId","_eventDataValue":"1236"},{"_eventDataKey":"ShouldStartFacingRight","_eventDataValue":"False"},{"_eventDataKey":"ShouldClampToSubdivisions","_eventDataValue":"True"}]},{"startBeatNumber":240,"endBeatNumber":241,"audioEvents":[],"track":3,"clipin":0,"group":0,"type":"SpawnEnemy","dataPairs":[{"_eventDataKey":"EnemyId","_eventDataValue":"1236"},{"_eventDataKey":"ShouldStartFacingRight","_eventDataValue":"False"},{"_eventDataKey":"ShouldClampToSubdivisions","_eventDataValue":"True"}]},{"startBeatNumber":241,"endBeatNumber":242,"audioEvents":[],"track":1,"clipin":0,"group":0,"type":"SpawnEnemy","dataPairs":[{"_eventDataKey":"EnemyId","_eventDataValue":"1236"},{"_eventDataKey":"ShouldStartFacingRight","_eventDataValue":"False"},{"_eventDataKey":"ShouldClampToSubdivisions","_eventDataValue":"True"}]},{"startBeatNumber":242,"endBeatNumber":243,"audioEvents":[],"track":3,"clipin":0,"group":0,"type":"SpawnEnemy","dataPairs":[{"_eventDataKey":"EnemyId","_eventDataValue":"1236"},{"_eventDataKey":"ShouldStartFacingRight","_eventDataValue":"False"},{"_eventDataKey":"ShouldClampToSubdivisions","_eventDataValue":"True"}]},{"startBeatNumber":243,"endBeatNumber":244,"audioEvents":[],"track":1,"clipin":0,"group":0,"type":"SpawnEnemy","dataPairs":[{"_eventDataKey":"EnemyId","_eventDataValue":"1236"},{"_eventDataKey":"ShouldStartFacingRight","_eventDataValue":"False"},{"_eventDataKey":"ShouldClampToSubdivisions","_eventDataValue":"True"}]},{"startBeatNumber":244,"endBeatNumber":245,"audioEvents":[],"track":3,"clipin":0,"group":0,"type":"SpawnEnemy","dataPairs":[{"_eventDataKey":"EnemyId","_eventDataValue":"1236"},{"_eventDataKey":"ShouldStartFacingRight","_eventDataValue":"False"},{"_eventDataKey":"ShouldClampToSubdivisions","_eventDataValue":"True"}]},{"startBeatNumber":245,"endBeatNumber":246,"audioEvents":[],"track":1,"clipin":0,"group":0,"type":"SpawnEnemy","dataPairs":[{"_eventDataKey":"EnemyId","_eventDataValue":"1236"},{"_eventDataKey":"ShouldStartFacingRight","_eventDataValue":"False"},{"_eventDataKey":"ShouldClampToSubdivisions","_eventDataValue":"True"}]},{"startBeatNumber":246,"endBeatNumber":247,"audioEvents":[],"track":3,"clipin":0,"group":0,"type":"SpawnEnemy","dataPairs":[{"_eventDataKey":"EnemyId","_eventDataValue":"1236"},{"_eventDataKey":"ShouldStartFacingRight","_eventDataValue":"False"},{"_eventDataKey":"ShouldClampToSubdivisions","_eventDataValue":"True"}]},{"startBeatNumber":247,"endBeatNumber":248,"audioEvents":[],"track":1,"clipin":0,"group":0,"type":"SpawnEnemy","dataPairs":[{"_eventDataKey":"EnemyId","_eventDataValue":"1236"},{"_eventDataKey":"ShouldStartFacingRight","_eventDataValue":"False"},{"_eventDataKey":"ShouldClampToSubdivisions","_eventDataValue":"True"}]},{"startBeatNumber":248,"endBeatNumber":249,"track":3,"clipin":0,"group":0,"type":"SpawnEnemy","dataPairs":[{"_eventDataKey":"EnemyId","_eventDataValue":"1722"},{"_eventDataKey":"ShouldClampToSubdivisions","_eventDataValue":"True"}]},{"startBeatNumber":248.5,"endBeatNumber":250.5,"track":2,"clipin":0,"group":0,"type":"SpawnEnemy","dataPairs":[{"_eventDataKey":"EnemyId","_eventDataValue":"4355"},{"_eventDataKey":"ShouldClampToSubdivisions","_eventDataValue":"True"}]},{"startBeatNumber":249,"endBeatNumber":250,"track":1,"clipin":0,"group":0,"type":"SpawnEnemy","dataPairs":[{"_eventDataKey":"EnemyId","_eventDataValue":"1722"},{"_eventDataKey":"ShouldClampToSubdivisions","_eventDataValue":"True"}]},{"startBeatNumber":250.5,"endBeatNumber":251.5,"track":1,"clipin":0,"group":0,"type":"SpawnEnemy","dataPairs":[{"_eventDataKey":"EnemyId","_eventDataValue":"1722"},{"_eventDataKey":"ShouldClampToSubdivisions","_eventDataValue":"True"}]},{"startBeatNumber":251.5,"endBeatNumber":253.5,"track":2,"clipin":0,"group":0,"type":"SpawnEnemy","dataPairs":[{"_eventDataKey":"EnemyId","_eventDataValue":"4355"},{"_eventDataKey":"ShouldClampToSubdivisions","_eventDataValue":"True"}]},{"startBeatNumber":252,"endBeatNumber":253,"track":1,"clipin":0,"group":0,"type":"SpawnEnemy","dataPairs":[{"_eventDataKey":"EnemyId","_eventDataValue":"1722"},{"_eventDataKey":"ShouldClampToSubdivisions","_eventDataValue":"True"}]},{"startBeatNumber":255,"endBeatNumber":256,"track":3,"clipin":0,"group":0,"type":"SpawnEnemy","dataPairs":[{"_eventDataKey":"EnemyId","_eventDataValue":"1722"},{"_eventDataKey":"ShouldClampToSubdivisions","_eventDataValue":"True"}]},{"startBeatNumber":255.5,"endBeatNumber":256.5,"track":2,"clipin":0,"group":0,"type":"SpawnEnemy","dataPairs":[{"_eventDataKey":"EnemyId","_eventDataValue":"1722"},{"_eventDataKey":"ShouldClampToSubdivisions","_eventDataValue":"True"}]},{"startBeatNumber":256.5,"endBeatNumber":258.5,"track":2,"clipin":0,"group":0,"type":"SpawnEnemy","dataPairs":[{"_eventDataKey":"EnemyId","_eventDataValue":"4355"},{"_eventDataKey":"ShouldClampToSubdivisions","_eventDataValue":"True"}]},{"startBeatNumber":257,"endBeatNumber":258,"track":1,"clipin":0,"group":0,"type":"SpawnEnemy","dataPairs":[{"_eventDataKey":"EnemyId","_eventDataValue":"1722"},{"_eventDataKey":"ShouldClampToSubdivisions","_eventDataValue":"True"}]},{"startBeatNumber":258.5,"endBeatNumber":259.5,"track":1,"clipin":0,"group":0,"type":"SpawnEnemy","dataPairs":[{"_eventDataKey":"EnemyId","_eventDataValue":"1722"},{"_eventDataKey":"ShouldClampToSubdivisions","_eventDataValue":"True"}]},{"startBeatNumber":259.5,"endBeatNumber":260.5,"track":2,"clipin":0,"group":0,"type":"SpawnEnemy","dataPairs":[{"_eventDataKey":"EnemyId","_eventDataValue":"1722"},{"_eventDataKey":"ShouldClampToSubdivisions","_eventDataValue":"True"}]},{"startBeatNumber":260,"endBeatNumber":261,"track":1,"clipin":0,"group":0,"type":"SpawnEnemy","dataPairs":[{"_eventDataKey":"EnemyId","_eventDataValue":"1722"},{"_eventDataKey":"ShouldClampToSubdivisions","_eventDataValue":"True"}]},{"startBeatNumber":260,"endBeatNumber":261,"track":3,"clipin":0,"group":0,"type":"SpawnEnemy","dataPairs":[{"_eventDataKey":"EnemyId","_eventDataValue":"1722"},{"_eventDataKey":"ShouldClampToSubdivisions","_eventDataValue":"True"}]},{"startBeatNumber":261,"endBeatNumber":262,"track":2,"clipin":0,"group":0,"type":"SpawnEnemy","dataPairs":[{"_eventDataKey":"EnemyId","_eventDataValue":"1722"},{"_eventDataKey":"ShouldClampToSubdivisions","_eventDataValue":"True"}]},{"startBeatNumber":262,"endBeatNumber":263,"track":1,"clipin":0,"group":0,"type":"SpawnEnemy","dataPairs":[{"_eventDataKey":"EnemyId","_eventDataValue":"1722"},{"_eventDataKey":"ShouldClampToSubdivisions","_eventDataValue":"True"}]},{"startBeatNumber":262,"endBeatNumber":263,"track":3,"clipin":0,"group":0,"type":"SpawnEnemy","dataPairs":[{"_eventDataKey":"EnemyId","_eventDataValue":"1722"},{"_eventDataKey":"ShouldClampToSubdivisions","_eventDataValue":"True"}]},{"startBeatNumber":263,"endBeatNumber":264,"track":2,"clipin":0,"group":0,"type":"SpawnEnemy","dataPairs":[{"_eventDataKey":"EnemyId","_eventDataValue":"7358"},{"_eventDataKey":"ShouldClampToSubdivisions","_eventDataValue":"True"}]},{"startBeatNumber":264.5,"endBeatNumber":265.5,"track":3,"clipin":0,"group":0,"type":"SpawnEnemy","dataPairs":[{"_eventDataKey":"EnemyId","_eventDataValue":"1722"},{"_eventDataKey":"ShouldClampToSubdivisions","_eventDataValue":"True"}]},{"startBeatNumber":265,"endBeatNumber":266,"track":2,"clipin":0,"group":0,"type":"SpawnEnemy","dataPairs":[{"_eventDataKey":"EnemyId","_eventDataValue":"1722"},{"_eventDataKey":"ShouldClampToSubdivisions","_eventDataValue":"True"}]},{"startBeatNumber":265.5,"endBeatNumber":266.5,"track":1,"clipin":0,"group":0,"type":"SpawnEnemy","dataPairs":[{"_eventDataKey":"EnemyId","_eventDataValue":"1722"},{"_eventDataKey":"ShouldClampToSubdivisions","_eventDataValue":"True"}]},{"startBeatNumber":266.5,"endBeatNumber":267.5,"track":2,"clipin":0,"group":0,"type":"SpawnEnemy","dataPairs":[{"_eventDataKey":"EnemyId","_eventDataValue":"1722"},{"_eventDataKey":"ShouldClampToSubdivisions","_eventDataValue":"True"}]},{"startBeatNumber":267.5,"endBeatNumber":269.5,"track":2,"clipin":0,"group":0,"type":"SpawnEnemy","dataPairs":[{"_eventDataKey":"EnemyId","_eventDataValue":"4355"},{"_eventDataKey":"ShouldClampToSubdivisions","_eventDataValue":"True"}]},{"startBeatNumber":268,"endBeatNumber":269,"track":1,"clipin":0,"group":0,"type":"SpawnEnemy","dataPairs":[{"_eventDataKey":"EnemyId","_eventDataValue":"1722"},{"_eventDataKey":"ShouldClampToSubdivisions","_eventDataValue":"True"}]},{"startBeatNumber":272,"endBeatNumber":273,"track":3,"clipin":0,"group":0,"type":"SpawnEnemy","dataPairs":[{"_eventDataKey":"EnemyId","_eventDataValue":"1722"},{"_eventDataKey":"ShouldClampToSubdivisions","_eventDataValue":"True"}]},{"startBeatNumber":272.5,"endBeatNumber":274.5,"track":2,"clipin":0,"group":0,"type":"SpawnEnemy","dataPairs":[{"_eventDataKey":"EnemyId","_eventDataValue":"4355"},{"_eventDataKey":"ShouldClampToSubdivisions","_eventDataValue":"True"}]},{"startBeatNumber":273,"endBeatNumber":274,"track":1,"clipin":0,"group":0,"type":"SpawnEnemy","dataPairs":[{"_eventDataKey":"EnemyId","_eventDataValue":"1722"},{"_eventDataKey":"ShouldClampToSubdivisions","_eventDataValue":"True"}]},{"startBeatNumber":274.5,"endBeatNumber":275.5,"track":1,"clipin":0,"group":0,"type":"SpawnEnemy","dataPairs":[{"_eventDataKey":"EnemyId","_eventDataValue":"1722"},{"_eventDataKey":"ShouldClampToSubdivisions","_eventDataValue":"True"}]},{"startBeatNumber":275.5,"endBeatNumber":276.5,"track":2,"clipin":0,"group":0,"type":"SpawnEnemy","dataPairs":[{"_eventDataKey":"EnemyId","_eventDataValue":"1722"},{"_eventDataKey":"ShouldClampToSubdivisions","_eventDataValue":"True"}]},{"startBeatNumber":276,"endBeatNumber":277,"track":1,"clipin":0,"group":0,"type":"SpawnEnemy","dataPairs":[{"_eventDataKey":"EnemyId","_eventDataValue":"1722"},{"_eventDataKey":"ShouldClampToSubdivisions","_eventDataValue":"True"}]},{"startBeatNumber":276,"endBeatNumber":278,"track":3,"clipin":0,"group":0,"type":"SpawnEnemy","dataPairs":[{"_eventDataKey":"EnemyId","_eventDataValue":"4355"},{"_eventDataKey":"ShouldClampToSubdivisions","_eventDataValue":"True"}]},{"startBeatNumber":278,"endBeatNumber":279,"track":2,"clipin":0,"group":0,"type":"SpawnEnemy","dataPairs":[{"_eventDataKey":"EnemyId","_eventDataValue":"1722"},{"_eventDataKey":"ShouldClampToSubdivisions","_eventDataValue":"True"}]},{"startBeatNumber":279,"endBeatNumber":280,"track":3,"clipin":0,"group":0,"type":"SpawnEnemy","dataPairs":[{"_eventDataKey":"EnemyId","_eventDataValue":"1722"},{"_eventDataKey":"ShouldClampToSubdivisions","_eventDataValue":"True"}]},{"startBeatNumber":280,"endBeatNumber":281,"track":2,"clipin":0,"group":0,"type":"SpawnEnemy","dataPairs":[{"_eventDataKey":"EnemyId","_eventDataValue":"8156"},{"_eventDataKey":"ShouldClampToSubdivisions","_eventDataValue":"True"}]},{"startBeatNumber":281,"endBeatNumber":282,"track":1,"clipin":0,"group":0,"type":"SpawnEnemy","dataPairs":[{"_eventDataKey":"EnemyId","_eventDataValue":"8519"},{"_eventDataKey":"ShouldClampToSubdivisions","_eventDataValue":"True"}]},{"startBeatNumber":283,"endBeatNumber":284,"track":1,"clipin":0,"group":0,"type":"SpawnEnemy","dataPairs":[{"_eventDataKey":"EnemyId","_eventDataValue":"8519"},{"_eventDataKey":"ShouldClampToSubdivisions","_eventDataValue":"True"}]},{"startBeatNumber":283,"endBeatNumber":284,"track":3,"clipin":0,"group":0,"type":"SpawnEnemy","dataPairs":[{"_eventDataKey":"EnemyId","_eventDataValue":"8519"},{"_eventDataKey":"ShouldClampToSubdivisions","_eventDataValue":"True"}]},{"startBeatNumber":284,"endBeatNumber":285,"track":2,"clipin":0,"group":0,"type":"SpawnEnemy","dataPairs":[{"_eventDataKey":"EnemyId","_eventDataValue":"8156"},{"_eventDataKey":"ShouldClampToSubdivisions","_eventDataValue":"True"}]},{"startBeatNumber":285,"endBeatNumber":286,"track":3,"clipin":0,"group":0,"type":"SpawnEnemy","dataPairs":[{"_eventDataKey":"EnemyId","_eventDataValue":"8156"},{"_eventDataKey":"ShouldClampToSubdivisions","_eventDataValue":"True"}]},{"startBeatNumber":288,"endBeatNumber":289,"audioEvents":[],"track":2,"clipin":0,"group":0,"type":"SpawnEnemy","dataPairs":[{"_eventDataKey":"EnemyId","_eventDataValue":"1234"},{"_eventDataKey":"ShouldStartFacingRight","_eventDataValue":"False"},{"_eventDataKey":"ShouldClampToSubdivisions","_eventDataValue":"True"}]},{"startBeatNumber":289,"endBeatNumber":290,"audioEvents":[],"track":3,"clipin":0,"group":0,"type":"SpawnEnemy","dataPairs":[{"_eventDataKey":"EnemyId","_eventDataValue":"1722"},{"_eventDataKey":"ShouldStartFacingRight","_eventDataValue":"True"},{"_eventDataKey":"ShouldClampToSubdivisions","_eventDataValue":"True"}]},{"startBeatNumber":290,"endBeatNumber":291,"track":2,"clipin":0,"group":0,"type":"SpawnEnemy","dataPairs":[{"_eventDataKey":"EnemyId","_eventDataValue":"1234"},{"_eventDataKey":"ShouldStartFacingRight","_eventDataValue":"True"},{"_eventDataKey":"ShouldClampToSubdivisions","_eventDataValue":"True"}]},{"startBeatNumber":291,"endBeatNumber":292,"audioEvents":[],"track":1,"clipin":0,"group":0,"type":"SpawnEnemy","dataPairs":[{"_eventDataKey":"EnemyId","_eventDataValue":"1722"},{"_eventDataKey":"ShouldStartFacingRight","_eventDataValue":"True"},{"_eventDataKey":"ShouldClampToSubdivisions","_eventDataValue":"True"}]},{"startBeatNumber":292,"endBeatNumber":293,"audioEvents":[],"track":2,"clipin":0,"group":0,"type":"SpawnEnemy","dataPairs":[{"_eventDataKey":"EnemyId","_eventDataValue":"1234"},{"_eventDataKey":"ShouldStartFacingRight","_eventDataValue":"False"},{"_eventDataKey":"ShouldClampToSubdivisions","_eventDataValue":"True"}]},{"startBeatNumber":293,"endBeatNumber":294,"track":1,"clipin":0,"group":0,"type":"SpawnEnemy","dataPairs":[{"_eventDataKey":"EnemyId","_eventDataValue":"1234"},{"_eventDataKey":"ShouldStartFacingRight","_eventDataValue":"True"},{"_eventDataKey":"ShouldClampToSubdivisions","_eventDataValue":"True"}]},{"startBeatNumber":294,"endBeatNumber":295,"track":2,"clipin":0,"group":0,"type":"SpawnEnemy","dataPairs":[{"_eventDataKey":"EnemyId","_eventDataValue":"1234"},{"_eventDataKey":"ShouldStartFacingRight","_eventDataValue":"True"},{"_eventDataKey":"ShouldClampToSubdivisions","_eventDataValue":"True"}]},{"startBeatNumber":295,"endBeatNumber":296,"track":3,"clipin":0,"group":0,"type":"SpawnEnemy","dataPairs":[{"_eventDataKey":"EnemyId","_eventDataValue":"1234"},{"_eventDataKey":"ShouldStartFacingRight","_eventDataValue":"True"},{"_eventDataKey":"ShouldClampToSubdivisions","_eventDataValue":"True"}]},{"startBeatNumber":296,"endBeatNumber":297,"track":2,"clipin":0,"group":0,"type":"SpawnEnemy","dataPairs":[{"_eventDataKey":"EnemyId","_eventDataValue":"8156"},{"_eventDataKey":"ShouldClampToSubdivisions","_eventDataValue":"True"}]},{"startBeatNumber":297,"endBeatNumber":298,"track":1,"clipin":0,"group":0,"type":"SpawnEnemy","dataPairs":[{"_eventDataKey":"EnemyId","_eventDataValue":"8519"},{"_eventDataKey":"ShouldClampToSubdivisions","_eventDataValue":"True"}]},{"startBeatNumber":299,"endBeatNumber":300,"track":1,"clipin":0,"group":0,"type":"SpawnEnemy","dataPairs":[{"_eventDataKey":"EnemyId","_eventDataValue":"8519"},{"_eventDataKey":"ShouldClampToSubdivisions","_eventDataValue":"True"}]},{"startBeatNumber":299,"endBeatNumber":300,"track":3,"clipin":0,"group":0,"type":"SpawnEnemy","dataPairs":[{"_eventDataKey":"EnemyId","_eventDataValue":"8519"},{"_eventDataKey":"ShouldClampToSubdivisions","_eventDataValue":"True"}]},{"startBeatNumber":300,"endBeatNumber":301,"track":2,"clipin":0,"group":0,"type":"SpawnEnemy","dataPairs":[{"_eventDataKey":"EnemyId","_eventDataValue":"8156"},{"_eventDataKey":"ShouldClampToSubdivisions","_eventDataValue":"True"}]},{"startBeatNumber":301,"endBeatNumber":302,"track":3,"clipin":0,"group":0,"type":"SpawnEnemy","dataPairs":[{"_eventDataKey":"EnemyId","_eventDataValue":"1722"},{"_eventDataKey":"ShouldClampToSubdivisions","_eventDataValue":"True"}]},{"startBeatNumber":303,"endBeatNumber":304,"track":1,"clipin":0,"group":0,"type":"SpawnEnemy","dataPairs":[{"_eventDataKey":"EnemyId","_eventDataValue":"1722"},{"_eventDataKey":"ShouldClampToSubdivisions","_eventDataValue":"True"}]},{"startBeatNumber":304,"endBeatNumber":305,"track":3,"clipin":0,"group":0,"type":"SpawnEnemy","dataPairs":[{"_eventDataKey":"EnemyId","_eventDataValue":"1236"},{"_eventDataKey":"ShouldClampToSubdivisions","_eventDataValue":"True"}]},{"startBeatNumber":305,"endBeatNumber":306,"track":3,"clipin":0,"group":0,"type":"SpawnEnemy","dataPairs":[{"_eventDataKey":"EnemyId","_eventDataValue":"1236"},{"_eventDataKey":"ShouldClampToSubdivisions","_eventDataValue":"True"}]},{"startBeatNumber":306,"endBeatNumber":307,"audioEvents":[],"track":3,"clipin":0,"group":0,"type":"SpawnEnemy","dataPairs":[{"_eventDataKey":"EnemyId","_eventDataValue":"1236"},{"_eventDataKey":"ShouldStartFacingRight","_eventDataValue":"False"},{"_eventDataKey":"ShouldClampToSubdivisions","_eventDataValue":"True"}]},{"startBeatNumber":307,"endBeatNumber":308,"audioEvents":[],"track":2,"clipin":0,"group":0,"type":"SpawnEnemy","dataPairs":[{"_eventDataKey":"EnemyId","_eventDataValue":"1722"},{"_eventDataKey":"ShouldStartFacingRight","_eventDataValue":"True"},{"_eventDataKey":"ShouldClampToSubdivisions","_eventDataValue":"True"}]},{"startBeatNumber":307,"endBeatNumber":308,"audioEvents":[],"track":3,"clipin":0,"group":0,"type":"SpawnEnemy","dataPairs":[{"_eventDataKey":"EnemyId","_eventDataValue":"1722"},{"_eventDataKey":"ShouldStartFacingRight","_eventDataValue":"True"},{"_eventDataKey":"ShouldClampToSubdivisions","_eventDataValue":"True"}]},{"startBeatNumber":308,"endBeatNumber":309,"audioEvents":[],"track":1,"clipin":0,"group":0,"type":"SpawnEnemy","dataPairs":[{"_eventDataKey":"EnemyId","_eventDataValue":"1236"},{"_eventDataKey":"ShouldStartFacingRight","_eventDataValue":"True"},{"_eventDataKey":"ShouldClampToSubdivisions","_eventDataValue":"True"}]},{"startBeatNumber":309,"endBeatNumber":310,"audioEvents":[],"track":1,"clipin":0,"group":0,"type":"SpawnEnemy","dataPairs":[{"_eventDataKey":"EnemyId","_eventDataValue":"1236"},{"_eventDataKey":"ShouldStartFacingRight","_eventDataValue":"True"},{"_eventDataKey":"ShouldClampToSubdivisions","_eventDataValue":"True"}]},{"startBeatNumber":310,"endBeatNumber":311,"audioEvents":[],"track":1,"clipin":0,"group":0,"type":"SpawnEnemy","dataPairs":[{"_eventDataKey":"EnemyId","_eventDataValue":"1236"},{"_eventDataKey":"ShouldStartFacingRight","_eventDataValue":"True"},{"_eventDataKey":"ShouldClampToSubdivisions","_eventDataValue":"True"}]},{"startBeatNumber":311,"endBeatNumber":312,"audioEvents":[],"track":2,"clipin":0,"group":0,"type":"SpawnEnemy","dataPairs":[{"_eventDataKey":"EnemyId","_eventDataValue":"1722"},{"_eventDataKey":"ShouldStartFacingRight","_eventDataValue":"True"},{"_eventDataKey":"ShouldClampToSubdivisions","_eventDataValue":"True"}]},{"startBeatNumber":312,"endBeatNumber":313,"audioEvents":[],"track":1,"clipin":0,"group":0,"type":"SpawnEnemy","dataPairs":[{"_eventDataKey":"EnemyId","_eventDataValue":"1236"},{"_eventDataKey":"ShouldStartFacingRight","_eventDataValue":"True"},{"_eventDataKey":"ShouldClampToSubdivisions","_eventDataValue":"True"}]},{"startBeatNumber":312,"endBeatNumber":313,"audioEvents":[],"track":3,"clipin":0,"group":0,"type":"SpawnEnemy","dataPairs":[{"_eventDataKey":"EnemyId","_eventDataValue":"1236"},{"_eventDataKey":"ShouldStartFacingRight","_eventDataValue":"True"},{"_eventDataKey":"ShouldClampToSubdivisions","_eventDataValue":"True"}]},{"startBeatNumber":312,"endBeatNumber":313,"audioEvents":[],"track":2,"clipin":0,"group":0,"type":"SpawnEnemy","dataPairs":[{"_eventDataKey":"EnemyId","_eventDataValue":"1236"},{"_eventDataKey":"ShouldStartFacingRight","_eventDataValue":"True"},{"_eventDataKey":"ShouldClampToSubdivisions","_eventDataValue":"True"}]},{"startBeatNumber":319.5,"endBeatNumber":320.5,"track":1,"clipin":0,"group":0,"type":"SpawnEnemy","dataPairs":[{"_eventDataKey":"EnemyId","_eventDataValue":"1722"},{"_eventDataKey":"ShouldClampToSubdivisions","_eventDataValue":"True"}]},{"startBeatNumber":322,"endBeatNumber":323,"track":3,"clipin":0,"group":0,"type":"SpawnEnemy","dataPairs":[{"_eventDataKey":"EnemyId","_eventDataValue":"8519"},{"_eventDataKey":"ShouldClampToSubdivisions","_eventDataValue":"True"}]},{"startBeatNumber":324,"endBeatNumber":325,"track":2,"clipin":0,"group":0,"type":"SpawnEnemy","dataPairs":[{"_eventDataKey":"EnemyId","_eventDataValue":"8519"},{"_eventDataKey":"ShouldClampToSubdivisions","_eventDataValue":"True"}]},{"startBeatNumber":326,"endBeatNumber":327,"track":1,"clipin":0,"group":0,"type":"SpawnEnemy","dataPairs":[{"_eventDataKey":"EnemyId","_eventDataValue":"8519"},{"_eventDataKey":"ShouldClampToSubdivisions","_eventDataValue":"True"}]}],"shouldSetBossStanceOnBeatmapStart":false,"bpm":105}