{"coalTrapSpeedUpFactorOverride":0,"name":"Twombtorial_easy_edits_2","beatDivisions":4,"bpm":100,"inputMappingOverrideJson":"","cameraZoomLevel":0,"shouldSetBossStanceOnBeatmapStart":false,"defaultBossStance":0,"events":[{"track":1,"clipin":0,"startBeatNumber":0,"endBeatNumber":1,"dataPairs":[{"_eventDataKey":"EnemyId","_eventDataValue":"1722"},{"_eventDataKey":"ShouldClampToSubdivisions","_eventDataValue":"True"}],"group":0,"type":"SpawnEnemy"},{"track":2,"clipin":0,"startBeatNumber":0,"endBeatNumber":1,"dataPairs":[{"_eventDataKey":"EnemyId","_eventDataValue":"1722"},{"_eventDataKey":"ShouldClampToSubdivisions","_eventDataValue":"True"}],"group":0,"type":"SpawnEnemy"},{"track":3,"clipin":0,"startBeatNumber":0,"endBeatNumber":1,"dataPairs":[{"_eventDataKey":"EnemyId","_eventDataValue":"1722"},{"_eventDataKey":"ShouldClampToSubdivisions","_eventDataValue":"True"}],"group":0,"type":"SpawnEnemy"},{"track":2,"clipin":0,"startBeatNumber":4,"endBeatNumber":5,"dataPairs":[{"_eventDataKey":"EnemyId","_eventDataValue":"2202"},{"_eventDataKey":"ShouldClampToSubdivisions","_eventDataValue":"True"}],"group":0,"type":"SpawnEnemy"},{"track":1,"clipin":0,"startBeatNumber":8,"endBeatNumber":9,"dataPairs":[{"_eventDataKey":"EnemyId","_eventDataValue":"2202"},{"_eventDataKey":"ShouldClampToSubdivisions","_eventDataValue":"True"}],"group":0,"type":"SpawnEnemy"},{"track":2,"clipin":0,"startBeatNumber":8,"endBeatNumber":9,"dataPairs":[{"_eventDataKey":"TrapHealthInBeats","_eventDataValue":"1"},{"_eventDataKey":"EnemyId","_eventDataValue":"2202"},{"_eventDataKey":"ShouldClampToSubdivisions","_eventDataValue":"True"}],"group":0,"type":"SpawnEnemy"},{"track":3,"clipin":0,"startBeatNumber":8,"endBeatNumber":9,"dataPairs":[{"_eventDataKey":"EnemyId","_eventDataValue":"2202"},{"_eventDataKey":"ShouldClampToSubdivisions","_eventDataValue":"True"}],"group":0,"type":"SpawnEnemy"},{"track":1,"clipin":0,"startBeatNumber":12,"endBeatNumber":13,"dataPairs":[{"_eventDataKey":"ShouldStartFacingRight","_eventDataValue":"True"},{"_eventDataKey":"TrapHealthInBeats","_eventDataValue":"1"},{"_eventDataKey":"EnemyId","_eventDataValue":"1722"},{"_eventDataKey":"ShouldClampToSubdivisions","_eventDataValue":"True"}],"group":0,"type":"SpawnEnemy"},{"track":3,"clipin":0,"startBeatNumber":12,"endBeatNumber":17,"dataPairs":[{"_eventDataKey":"EnemyId","_eventDataValue":"7794"},{"_eventDataKey":"ShouldClampToSubdivisions","_eventDataValue":"True"}],"group":0,"type":"SpawnEnemy"},{"track":1,"clipin":0,"startBeatNumber":16,"endBeatNumber":17,"dataPairs":[{"_eventDataKey":"EnemyId","_eventDataValue":"1722"},{"_eventDataKey":"ShouldClampToSubdivisions","_eventDataValue":"True"}],"group":0,"type":"SpawnEnemy"},{"track":2,"clipin":0,"startBeatNumber":18,"endBeatNumber":19,"dataPairs":[{"_eventDataKey":"EnemyId","_eventDataValue":"1722"},{"_eventDataKey":"ShouldClampToSubdivisions","_eventDataValue":"True"}],"group":0,"type":"SpawnEnemy"},{"track":1,"clipin":0,"startBeatNumber":20,"endBeatNumber":25,"dataPairs":[{"_eventDataKey":"EnemyId","_eventDataValue":"7794"},{"_eventDataKey":"ShouldClampToSubdivisions","_eventDataValue":"True"}],"group":0,"type":"SpawnEnemy"},{"track":3,"clipin":0,"startBeatNumber":20,"endBeatNumber":21,"dataPairs":[{"_eventDataKey":"EnemyId","_eventDataValue":"1722"},{"_eventDataKey":"ShouldClampToSubdivisions","_eventDataValue":"True"}],"group":0,"type":"SpawnEnemy"},{"track":3,"clipin":0,"startBeatNumber":24,"endBeatNumber":25,"dataPairs":[{"_eventDataKey":"EnemyId","_eventDataValue":"1722"},{"_eventDataKey":"ShouldClampToSubdivisions","_eventDataValue":"True"}],"group":0,"type":"SpawnEnemy"},{"track":2,"clipin":0,"startBeatNumber":26,"endBeatNumber":27,"dataPairs":[{"_eventDataKey":"EnemyId","_eventDataValue":"1722"},{"_eventDataKey":"ShouldClampToSubdivisions","_eventDataValue":"True"}],"group":0,"type":"SpawnEnemy"},{"track":2,"clipin":0,"startBeatNumber":28,"endBeatNumber":29,"dataPairs":[{"_eventDataKey":"EnemyId","_eventDataValue":"1722"},{"_eventDataKey":"ShouldClampToSubdivisions","_eventDataValue":"True"}],"group":0,"type":"SpawnEnemy"},{"track":2,"clipin":0,"startBeatNumber":30,"endBeatNumber":31,"dataPairs":[{"_eventDataKey":"EnemyId","_eventDataValue":"1722"},{"_eventDataKey":"ShouldClampToSubdivisions","_eventDataValue":"True"}],"group":0,"type":"SpawnEnemy"},{"track":1,"clipin":0,"startBeatNumber":32,"endBeatNumber":33,"dataPairs":[{"_eventDataKey":"EnemyId","_eventDataValue":"2202"},{"_eventDataKey":"ShouldClampToSubdivisions","_eventDataValue":"True"}],"group":0,"type":"SpawnEnemy"},{"track":3,"clipin":0,"startBeatNumber":32,"endBeatNumber":33,"dataPairs":[{"_eventDataKey":"EnemyId","_eventDataValue":"2202"},{"_eventDataKey":"ShouldClampToSubdivisions","_eventDataValue":"True"}],"group":0,"type":"SpawnEnemy"},{"track":1,"clipin":0,"startBeatNumber":34,"endBeatNumber":35,"dataPairs":[{"_eventDataKey":"EnemyId","_eventDataValue":"2202"},{"_eventDataKey":"ShouldClampToSubdivisions","_eventDataValue":"True"}],"group":0,"type":"SpawnEnemy"},{"track":3,"clipin":0,"startBeatNumber":34,"endBeatNumber":35,"dataPairs":[{"_eventDataKey":"EnemyId","_eventDataValue":"2202"},{"_eventDataKey":"ShouldClampToSubdivisions","_eventDataValue":"True"}],"group":0,"type":"SpawnEnemy"},{"track":2,"clipin":0,"startBeatNumber":36,"endBeatNumber":37,"dataPairs":[{"_eventDataKey":"EnemyId","_eventDataValue":"1722"},{"_eventDataKey":"ShouldClampToSubdivisions","_eventDataValue":"True"}],"group":0,"type":"SpawnEnemy"},{"track":2,"clipin":0,"startBeatNumber":38,"endBeatNumber":39,"dataPairs":[{"_eventDataKey":"EnemyId","_eventDataValue":"1722"},{"_eventDataKey":"ShouldClampToSubdivisions","_eventDataValue":"True"}],"group":0,"type":"SpawnEnemy"},{"track":1,"clipin":0,"startBeatNumber":40,"endBeatNumber":41,"dataPairs":[{"_eventDataKey":"EnemyId","_eventDataValue":"2202"},{"_eventDataKey":"ShouldClampToSubdivisions","_eventDataValue":"True"}],"group":0,"type":"SpawnEnemy"},{"track":3,"clipin":0,"startBeatNumber":40,"endBeatNumber":41,"dataPairs":[{"_eventDataKey":"EnemyId","_eventDataValue":"2202"},{"_eventDataKey":"ShouldClampToSubdivisions","_eventDataValue":"True"}],"group":0,"type":"SpawnEnemy"},{"track":1,"clipin":0,"startBeatNumber":42,"endBeatNumber":43,"dataPairs":[{"_eventDataKey":"EnemyId","_eventDataValue":"2202"},{"_eventDataKey":"ShouldClampToSubdivisions","_eventDataValue":"True"}],"group":0,"type":"SpawnEnemy"},{"track":3,"clipin":0,"startBeatNumber":42,"endBeatNumber":43,"dataPairs":[{"_eventDataKey":"EnemyId","_eventDataValue":"2202"},{"_eventDataKey":"ShouldClampToSubdivisions","_eventDataValue":"True"}],"group":0,"type":"SpawnEnemy"},{"track":2,"clipin":0,"startBeatNumber":43.25001,"endBeatNumber":58.25,"dataPairs":[{"_eventDataKey":"RiftedVibeChainShift","_eventDataValue":"43.25"}],"group":0,"type":"StartVibeChain"},{"track":1,"clipin":0,"startBeatNumber":44,"endBeatNumber":45,"dataPairs":[{"_eventDataKey":"EnemyId","_eventDataValue":"1722"},{"_eventDataKey":"ShouldClampToSubdivisions","_eventDataValue":"True"}],"group":0,"type":"SpawnEnemy"},{"track":2,"clipin":0,"startBeatNumber":44,"endBeatNumber":45,"dataPairs":[{"_eventDataKey":"EnemyId","_eventDataValue":"2202"},{"_eventDataKey":"ShouldClampToSubdivisions","_eventDataValue":"True"}],"group":0,"type":"SpawnEnemy"},{"track":2,"clipin":0,"startBeatNumber":48,"endBeatNumber":49,"dataPairs":[{"_eventDataKey":"EnemyId","_eventDataValue":"2202"},{"_eventDataKey":"ShouldClampToSubdivisions","_eventDataValue":"True"}],"group":0,"type":"SpawnEnemy"},{"track":3,"clipin":0,"startBeatNumber":48,"endBeatNumber":49,"dataPairs":[{"_eventDataKey":"EnemyId","_eventDataValue":"1722"},{"_eventDataKey":"ShouldClampToSubdivisions","_eventDataValue":"True"}],"group":0,"type":"SpawnEnemy"},{"track":1,"clipin":0,"startBeatNumber":52,"endBeatNumber":53,"dataPairs":[{"_eventDataKey":"EnemyId","_eventDataValue":"1722"},{"_eventDataKey":"ShouldClampToSubdivisions","_eventDataValue":"True"}],"group":0,"type":"SpawnEnemy"},{"track":2,"clipin":0,"startBeatNumber":52,"endBeatNumber":53,"dataPairs":[{"_eventDataKey":"EnemyId","_eventDataValue":"2202"},{"_eventDataKey":"ShouldClampToSubdivisions","_eventDataValue":"True"}],"group":0,"type":"SpawnEnemy"},{"track":2,"clipin":0,"startBeatNumber":56,"endBeatNumber":57,"dataPairs":[{"_eventDataKey":"EnemyId","_eventDataValue":"2202"},{"_eventDataKey":"ShouldClampToSubdivisions","_eventDataValue":"True"}],"group":0,"type":"SpawnEnemy"},{"track":3,"clipin":0,"startBeatNumber":56,"endBeatNumber":57,"dataPairs":[{"_eventDataKey":"EnemyId","_eventDataValue":"1722"},{"_eventDataKey":"ShouldClampToSubdivisions","_eventDataValue":"True"}],"group":0,"type":"SpawnEnemy"},{"track":1,"clipin":0,"startBeatNumber":58,"endBeatNumber":59,"dataPairs":[{"_eventDataKey":"EnemyId","_eventDataValue":"1722"},{"_eventDataKey":"ShouldClampToSubdivisions","_eventDataValue":"True"}],"group":0,"type":"SpawnEnemy"},{"track":3,"clipin":0,"startBeatNumber":58,"endBeatNumber":59,"dataPairs":[{"_eventDataKey":"EnemyId","_eventDataValue":"1722"},{"_eventDataKey":"ShouldClampToSubdivisions","_eventDataValue":"True"}],"group":0,"type":"SpawnEnemy"},{"track":1,"clipin":0,"startBeatNumber":60,"endBeatNumber":61,"dataPairs":[{"_eventDataKey":"EnemyId","_eventDataValue":"6803"},{"_eventDataKey":"ShouldClampToSubdivisions","_eventDataValue":"True"}],"group":0,"type":"SpawnEnemy"},{"track":3,"clipin":0,"startBeatNumber":62,"endBeatNumber":63,"dataPairs":[{"_eventDataKey":"EnemyId","_eventDataValue":"2202"},{"_eventDataKey":"ShouldClampToSubdivisions","_eventDataValue":"True"}],"group":0,"type":"SpawnEnemy"},{"track":1,"clipin":0,"startBeatNumber":64,"endBeatNumber":65,"dataPairs":[{"_eventDataKey":"EnemyId","_eventDataValue":"6803"},{"_eventDataKey":"ShouldClampToSubdivisions","_eventDataValue":"True"}],"group":0,"type":"SpawnEnemy"},{"track":2,"clipin":0,"startBeatNumber":66,"endBeatNumber":67,"dataPairs":[{"_eventDataKey":"EnemyId","_eventDataValue":"2202"},{"_eventDataKey":"ShouldClampToSubdivisions","_eventDataValue":"True"}],"group":0,"type":"SpawnEnemy"},{"track":1,"clipin":0,"startBeatNumber":68,"endBeatNumber":69,"dataPairs":[{"_eventDataKey":"EnemyId","_eventDataValue":"2202"},{"_eventDataKey":"ShouldClampToSubdivisions","_eventDataValue":"True"}],"group":0,"type":"SpawnEnemy"},{"track":3,"clipin":0,"startBeatNumber":68,"endBeatNumber":69,"dataPairs":[{"_eventDataKey":"EnemyId","_eventDataValue":"6803"},{"_eventDataKey":"ShouldClampToSubdivisions","_eventDataValue":"True"}],"group":0,"type":"SpawnEnemy"},{"track":2,"clipin":0,"startBeatNumber":70,"endBeatNumber":71,"dataPairs":[{"_eventDataKey":"EnemyId","_eventDataValue":"2202"},{"_eventDataKey":"ShouldClampToSubdivisions","_eventDataValue":"True"}],"group":0,"type":"SpawnEnemy"},{"track":1,"clipin":0,"startBeatNumber":72,"endBeatNumber":73,"dataPairs":[{"_eventDataKey":"EnemyId","_eventDataValue":"6803"},{"_eventDataKey":"ShouldClampToSubdivisions","_eventDataValue":"True"}],"group":0,"type":"SpawnEnemy"},{"track":3,"clipin":0,"startBeatNumber":72,"endBeatNumber":73,"dataPairs":[{"_eventDataKey":"EnemyId","_eventDataValue":"2202"},{"_eventDataKey":"ShouldClampToSubdivisions","_eventDataValue":"True"}],"group":0,"type":"SpawnEnemy"},{"track":1,"clipin":0,"startBeatNumber":76,"endBeatNumber":77,"dataPairs":[{"_eventDataKey":"EnemyId","_eventDataValue":"2716"},{"_eventDataKey":"ShouldClampToSubdivisions","_eventDataValue":"True"}],"group":0,"type":"SpawnEnemy"},{"track":1,"clipin":0,"startBeatNumber":80,"endBeatNumber":81,"dataPairs":[{"_eventDataKey":"EnemyId","_eventDataValue":"2716"},{"_eventDataKey":"ShouldClampToSubdivisions","_eventDataValue":"True"}],"group":0,"type":"SpawnEnemy"},{"track":1,"clipin":0,"startBeatNumber":84,"endBeatNumber":85,"dataPairs":[{"_eventDataKey":"EnemyId","_eventDataValue":"2202"},{"_eventDataKey":"ShouldClampToSubdivisions","_eventDataValue":"True"}],"group":0,"type":"SpawnEnemy"},{"track":2,"clipin":0,"startBeatNumber":84,"endBeatNumber":85,"dataPairs":[{"_eventDataKey":"EnemyId","_eventDataValue":"2716"},{"_eventDataKey":"ShouldClampToSubdivisions","_eventDataValue":"True"}],"group":0,"type":"SpawnEnemy"},{"track":2,"clipin":0,"startBeatNumber":88,"endBeatNumber":89,"dataPairs":[{"_eventDataKey":"EnemyId","_eventDataValue":"2716"},{"_eventDataKey":"ShouldClampToSubdivisions","_eventDataValue":"True"}],"group":0,"type":"SpawnEnemy"},{"track":1,"clipin":0,"startBeatNumber":93,"endBeatNumber":94,"dataPairs":[{"_eventDataKey":"EnemyId","_eventDataValue":"7358"},{"_eventDataKey":"ShouldClampToSubdivisions","_eventDataValue":"True"}],"group":0,"type":"SpawnEnemy"},{"track":2,"clipin":0,"startBeatNumber":93,"endBeatNumber":94,"dataPairs":[{"_eventDataKey":"EnemyId","_eventDataValue":"7358"},{"_eventDataKey":"ShouldClampToSubdivisions","_eventDataValue":"True"}],"group":0,"type":"SpawnEnemy"},{"track":3,"clipin":0,"startBeatNumber":93,"endBeatNumber":94,"dataPairs":[{"_eventDataKey":"EnemyId","_eventDataValue":"7358"},{"_eventDataKey":"ShouldClampToSubdivisions","_eventDataValue":"True"}],"group":0,"type":"SpawnEnemy"},{"track":2,"clipin":0,"startBeatNumber":95,"endBeatNumber":96,"dataPairs":[{"_eventDataKey":"EnemyId","_eventDataValue":"1234"},{"_eventDataKey":"ShouldClampToSubdivisions","_eventDataValue":"True"}],"group":0,"type":"SpawnEnemy"},{"track":2,"clipin":0,"startBeatNumber":97,"endBeatNumber":98,"audioEvents":[],"dataPairs":[{"_eventDataKey":"ShouldClampToSubdivisions","_eventDataValue":"True"},{"_eventDataKey":"EnemyId","_eventDataValue":"1234"},{"_eventDataKey":"ShouldStartFacingRight","_eventDataValue":"True"}],"group":0,"type":"SpawnEnemy"},{"track":2,"clipin":0,"startBeatNumber":99,"endBeatNumber":100,"dataPairs":[{"_eventDataKey":"EnemyId","_eventDataValue":"1234"},{"_eventDataKey":"ShouldClampToSubdivisions","_eventDataValue":"True"}],"group":0,"type":"SpawnEnemy"},{"track":3,"clipin":0,"startBeatNumber":101,"endBeatNumber":102,"audioEvents":[],"dataPairs":[{"_eventDataKey":"ShouldClampToSubdivisions","_eventDataValue":"True"},{"_eventDataKey":"EnemyId","_eventDataValue":"1234"},{"_eventDataKey":"ShouldStartFacingRight","_eventDataValue":"True"}],"group":0,"type":"SpawnEnemy"},{"track":1,"clipin":0,"startBeatNumber":103,"endBeatNumber":104,"audioEvents":[],"dataPairs":[{"_eventDataKey":"ShouldClampToSubdivisions","_eventDataValue":"True"},{"_eventDataKey":"EnemyId","_eventDataValue":"1234"},{"_eventDataKey":"ShouldStartFacingRight","_eventDataValue":"False"}],"group":0,"type":"SpawnEnemy"},{"track":3,"clipin":0,"startBeatNumber":105,"endBeatNumber":106,"audioEvents":[],"dataPairs":[{"_eventDataKey":"ShouldClampToSubdivisions","_eventDataValue":"True"},{"_eventDataKey":"EnemyId","_eventDataValue":"1234"},{"_eventDataKey":"ShouldStartFacingRight","_eventDataValue":"True"}],"group":0,"type":"SpawnEnemy"},{"track":1,"clipin":0,"startBeatNumber":107,"endBeatNumber":108,"audioEvents":[],"dataPairs":[{"_eventDataKey":"ShouldClampToSubdivisions","_eventDataValue":"True"},{"_eventDataKey":"EnemyId","_eventDataValue":"1234"},{"_eventDataKey":"ShouldStartFacingRight","_eventDataValue":"False"}],"group":0,"type":"SpawnEnemy"},{"track":2,"clipin":0,"startBeatNumber":108,"endBeatNumber":109,"audioEvents":[],"dataPairs":[{"_eventDataKey":"ShouldClampToSubdivisions","_eventDataValue":"True"},{"_eventDataKey":"EnemyId","_eventDataValue":"7358"},{"_eventDataKey":"ShouldStartFacingRight","_eventDataValue":"False"}],"group":0,"type":"SpawnEnemy"},{"track":3,"clipin":0,"startBeatNumber":108,"endBeatNumber":109,"audioEvents":[],"dataPairs":[{"_eventDataKey":"ShouldClampToSubdivisions","_eventDataValue":"True"},{"_eventDataKey":"EnemyId","_eventDataValue":"7358"},{"_eventDataKey":"ShouldStartFacingRight","_eventDataValue":"False"}],"group":0,"type":"SpawnEnemy"},{"track":3,"clipin":0,"startBeatNumber":109,"endBeatNumber":110,"dataPairs":[{"_eventDataKey":"ShouldStartFacingRight","_eventDataValue":"True"},{"_eventDataKey":"EnemyId","_eventDataValue":"1236"},{"_eventDataKey":"ShouldClampToSubdivisions","_eventDataValue":"True"}],"group":0,"type":"SpawnEnemy"},{"track":3,"clipin":0,"startBeatNumber":111,"endBeatNumber":112,"dataPairs":[{"_eventDataKey":"ShouldStartFacingRight","_eventDataValue":"True"},{"_eventDataKey":"EnemyId","_eventDataValue":"1236"},{"_eventDataKey":"ShouldClampToSubdivisions","_eventDataValue":"True"}],"group":0,"type":"SpawnEnemy"},{"track":1,"clipin":0,"startBeatNumber":113,"endBeatNumber":114,"dataPairs":[{"_eventDataKey":"ShouldStartFacingRight","_eventDataValue":"True"},{"_eventDataKey":"EnemyId","_eventDataValue":"1236"},{"_eventDataKey":"ShouldClampToSubdivisions","_eventDataValue":"True"}],"group":0,"type":"SpawnEnemy"},{"track":1,"clipin":0,"startBeatNumber":115,"endBeatNumber":116,"dataPairs":[{"_eventDataKey":"ShouldStartFacingRight","_eventDataValue":"True"},{"_eventDataKey":"EnemyId","_eventDataValue":"1236"},{"_eventDataKey":"ShouldClampToSubdivisions","_eventDataValue":"True"}],"group":0,"type":"SpawnEnemy"},{"track":1,"clipin":0,"startBeatNumber":117,"endBeatNumber":118,"dataPairs":[{"_eventDataKey":"EnemyId","_eventDataValue":"1236"},{"_eventDataKey":"ShouldClampToSubdivisions","_eventDataValue":"True"}],"group":0,"type":"SpawnEnemy"},{"track":1,"clipin":0,"startBeatNumber":119,"endBeatNumber":120,"dataPairs":[{"_eventDataKey":"EnemyId","_eventDataValue":"1236"},{"_eventDataKey":"ShouldClampToSubdivisions","_eventDataValue":"True"}],"group":0,"type":"SpawnEnemy"},{"track":3,"clipin":0,"startBeatNumber":121,"endBeatNumber":122,"dataPairs":[{"_eventDataKey":"EnemyId","_eventDataValue":"1236"},{"_eventDataKey":"ShouldClampToSubdivisions","_eventDataValue":"True"}],"group":0,"type":"SpawnEnemy"},{"track":3,"clipin":0,"startBeatNumber":123,"endBeatNumber":124,"dataPairs":[{"_eventDataKey":"EnemyId","_eventDataValue":"1236"},{"_eventDataKey":"ShouldClampToSubdivisions","_eventDataValue":"True"}],"group":0,"type":"SpawnEnemy"},{"track":2,"clipin":0,"startBeatNumber":124,"endBeatNumber":125,"audioEvents":[],"dataPairs":[{"_eventDataKey":"ShouldClampToSubdivisions","_eventDataValue":"True"},{"_eventDataKey":"EnemyId","_eventDataValue":"7358"},{"_eventDataKey":"ShouldStartFacingRight","_eventDataValue":"False"}],"group":0,"type":"SpawnEnemy"},{"track":1,"clipin":0,"startBeatNumber":125,"endBeatNumber":126,"audioEvents":[],"dataPairs":[{"_eventDataKey":"ShouldClampToSubdivisions","_eventDataValue":"True"},{"_eventDataKey":"EnemyId","_eventDataValue":"8519"},{"_eventDataKey":"ShouldStartFacingRight","_eventDataValue":"True"}],"group":0,"type":"SpawnEnemy"},{"track":2,"clipin":0,"startBeatNumber":125,"endBeatNumber":126,"dataPairs":[{"_eventDataKey":"EnemyId","_eventDataValue":"8519"},{"_eventDataKey":"ShouldClampToSubdivisions","_eventDataValue":"True"}],"group":0,"type":"SpawnEnemy"},{"track":3,"clipin":0,"startBeatNumber":125,"endBeatNumber":126,"audioEvents":[],"dataPairs":[{"_eventDataKey":"ShouldClampToSubdivisions","_eventDataValue":"True"},{"_eventDataKey":"EnemyId","_eventDataValue":"8519"},{"_eventDataKey":"ShouldStartFacingRight","_eventDataValue":"True"}],"group":0,"type":"SpawnEnemy"},{"track":1,"clipin":0,"startBeatNumber":128,"endBeatNumber":129,"dataPairs":[{"_eventDataKey":"EnemyId","_eventDataValue":"8519"},{"_eventDataKey":"ShouldClampToSubdivisions","_eventDataValue":"True"}],"group":0,"type":"SpawnEnemy"},{"track":3,"clipin":0,"startBeatNumber":128,"endBeatNumber":129,"dataPairs":[{"_eventDataKey":"EnemyId","_eventDataValue":"8519"},{"_eventDataKey":"ShouldClampToSubdivisions","_eventDataValue":"True"}],"group":0,"type":"SpawnEnemy"},{"track":2,"clipin":0,"startBeatNumber":131.14584333333,"endBeatNumber":137.14583333333,"dataPairs":[{"_eventDataKey":"RiftedVibeChainShift","_eventDataValue":"131.14583333333"}],"group":0,"type":"StartVibeChain"},{"track":2,"clipin":0,"startBeatNumber":132,"endBeatNumber":133,"dataPairs":[{"_eventDataKey":"EnemyId","_eventDataValue":"8519"},{"_eventDataKey":"ShouldClampToSubdivisions","_eventDataValue":"True"}],"group":0,"type":"SpawnEnemy"},{"track":1,"clipin":0,"startBeatNumber":136,"endBeatNumber":137,"dataPairs":[{"_eventDataKey":"EnemyId","_eventDataValue":"8519"},{"_eventDataKey":"ShouldClampToSubdivisions","_eventDataValue":"True"}],"group":0,"type":"SpawnEnemy"},{"track":3,"clipin":0,"startBeatNumber":136,"endBeatNumber":137,"dataPairs":[{"_eventDataKey":"EnemyId","_eventDataValue":"8519"},{"_eventDataKey":"ShouldClampToSubdivisions","_eventDataValue":"True"}],"group":0,"type":"SpawnEnemy"},{"track":2,"clipin":0,"startBeatNumber":144,"endBeatNumber":145,"dataPairs":[{"_eventDataKey":"EnemyId","_eventDataValue":"3826"},{"_eventDataKey":"ShouldClampToSubdivisions","_eventDataValue":"True"}],"group":0,"type":"SpawnEnemy"},{"track":1,"clipin":0,"startBeatNumber":148,"endBeatNumber":149,"dataPairs":[{"_eventDataKey":"EnemyId","_eventDataValue":"8156"},{"_eventDataKey":"ShouldClampToSubdivisions","_eventDataValue":"True"}],"group":0,"type":"SpawnEnemy"},{"track":2,"clipin":0,"startBeatNumber":148,"endBeatNumber":149,"dataPairs":[{"_eventDataKey":"EnemyId","_eventDataValue":"3826"},{"_eventDataKey":"ShouldClampToSubdivisions","_eventDataValue":"True"}],"group":0,"type":"SpawnEnemy"},{"track":3,"clipin":0,"startBeatNumber":152.01041666667,"endBeatNumber":153.01041666667,"dataPairs":[{"_eventDataKey":"EnemyId","_eventDataValue":"8156"},{"_eventDataKey":"ShouldClampToSubdivisions","_eventDataValue":"True"}],"group":0,"type":"SpawnEnemy"},{"track":3,"clipin":0,"startBeatNumber":156,"endBeatNumber":157,"dataPairs":[{"_eventDataKey":"EnemyId","_eventDataValue":"7358"},{"_eventDataKey":"ShouldClampToSubdivisions","_eventDataValue":"True"}],"group":0,"type":"SpawnEnemy"},{"track":2,"clipin":0,"startBeatNumber":158,"endBeatNumber":159,"dataPairs":[{"_eventDataKey":"EnemyId","_eventDataValue":"2054"},{"_eventDataKey":"ShouldClampToSubdivisions","_eventDataValue":"True"}],"group":0,"type":"SpawnEnemy"},{"track":1,"clipin":0,"startBeatNumber":160,"endBeatNumber":161,"dataPairs":[{"_eventDataKey":"EnemyId","_eventDataValue":"7358"},{"_eventDataKey":"ShouldClampToSubdivisions","_eventDataValue":"True"}],"group":0,"type":"SpawnEnemy"},{"track":3,"clipin":0,"startBeatNumber":162,"endBeatNumber":163,"dataPairs":[{"_eventDataKey":"EnemyId","_eventDataValue":"7358"},{"_eventDataKey":"ShouldClampToSubdivisions","_eventDataValue":"True"}],"group":0,"type":"SpawnEnemy"},{"track":2,"clipin":0,"startBeatNumber":164,"endBeatNumber":168,"dataPairs":[{"_eventDataKey":"EnemyId","_eventDataValue":"7794"},{"_eventDataKey":"ShouldClampToSubdivisions","_eventDataValue":"True"}],"group":0,"type":"SpawnEnemy"},{"track":1,"clipin":0,"startBeatNumber":168,"endBeatNumber":172,"dataPairs":[{"_eventDataKey":"EnemyId","_eventDataValue":"7794"},{"_eventDataKey":"ShouldClampToSubdivisions","_eventDataValue":"True"}],"group":0,"type":"SpawnEnemy"},{"track":3,"clipin":0,"startBeatNumber":168,"endBeatNumber":172,"dataPairs":[{"_eventDataKey":"EnemyId","_eventDataValue":"7794"},{"_eventDataKey":"ShouldClampToSubdivisions","_eventDataValue":"True"}],"group":0,"type":"SpawnEnemy"},{"track":2,"clipin":0,"startBeatNumber":171.43751,"endBeatNumber":178.4375,"dataPairs":[{"_eventDataKey":"RiftedVibeChainShift","_eventDataValue":"171.4375"}],"group":0,"type":"StartVibeChain"},{"track":2,"clipin":0,"startBeatNumber":172,"endBeatNumber":173,"dataPairs":[{"_eventDataKey":"EnemyId","_eventDataValue":"4355"},{"_eventDataKey":"ShouldClampToSubdivisions","_eventDataValue":"True"}],"group":0,"type":"SpawnEnemy"},{"track":2,"clipin":0,"startBeatNumber":174,"endBeatNumber":175,"dataPairs":[{"_eventDataKey":"EnemyId","_eventDataValue":"4355"},{"_eventDataKey":"ShouldClampToSubdivisions","_eventDataValue":"True"}],"group":0,"type":"SpawnEnemy"},{"track":3,"clipin":0,"startBeatNumber":176,"endBeatNumber":177,"dataPairs":[{"_eventDataKey":"EnemyId","_eventDataValue":"4355"},{"_eventDataKey":"ShouldClampToSubdivisions","_eventDataValue":"True"}],"group":0,"type":"SpawnEnemy"},{"track":3,"clipin":0,"startBeatNumber":178,"endBeatNumber":179,"dataPairs":[{"_eventDataKey":"EnemyId","_eventDataValue":"4355"},{"_eventDataKey":"ShouldClampToSubdivisions","_eventDataValue":"True"}],"group":0,"type":"SpawnEnemy"},{"track":1,"clipin":0,"startBeatNumber":180,"endBeatNumber":181,"dataPairs":[{"_eventDataKey":"EnemyId","_eventDataValue":"9189"},{"_eventDataKey":"ShouldClampToSubdivisions","_eventDataValue":"True"}],"group":0,"type":"SpawnEnemy"},{"track":1,"clipin":0,"startBeatNumber":183,"endBeatNumber":184,"dataPairs":[{"_eventDataKey":"EnemyId","_eventDataValue":"1722"},{"_eventDataKey":"ShouldClampToSubdivisions","_eventDataValue":"True"}],"group":0,"type":"SpawnEnemy"},{"track":3,"clipin":0,"startBeatNumber":184,"endBeatNumber":185,"dataPairs":[{"_eventDataKey":"EnemyId","_eventDataValue":"9189"},{"_eventDataKey":"ShouldClampToSubdivisions","_eventDataValue":"True"}],"group":0,"type":"SpawnEnemy"},{"track":3,"clipin":0,"startBeatNumber":187,"endBeatNumber":188,"dataPairs":[{"_eventDataKey":"EnemyId","_eventDataValue":"1722"},{"_eventDataKey":"ShouldClampToSubdivisions","_eventDataValue":"True"}],"group":0,"type":"SpawnEnemy"},{"track":2,"clipin":0,"startBeatNumber":188,"endBeatNumber":189,"dataPairs":[{"_eventDataKey":"EnemyId","_eventDataValue":"4355"},{"_eventDataKey":"ShouldClampToSubdivisions","_eventDataValue":"True"}],"group":0,"type":"SpawnEnemy"},{"track":2,"clipin":0,"startBeatNumber":190,"endBeatNumber":191,"dataPairs":[{"_eventDataKey":"EnemyId","_eventDataValue":"4355"},{"_eventDataKey":"ShouldClampToSubdivisions","_eventDataValue":"True"}],"group":0,"type":"SpawnEnemy"},{"track":1,"clipin":0,"startBeatNumber":192,"endBeatNumber":193,"dataPairs":[{"_eventDataKey":"EnemyId","_eventDataValue":"4355"},{"_eventDataKey":"ShouldClampToSubdivisions","_eventDataValue":"True"}],"group":0,"type":"SpawnEnemy"},{"track":1,"clipin":0,"startBeatNumber":194,"endBeatNumber":195,"dataPairs":[{"_eventDataKey":"EnemyId","_eventDataValue":"4355"},{"_eventDataKey":"ShouldClampToSubdivisions","_eventDataValue":"True"}],"group":0,"type":"SpawnEnemy"},{"track":3,"clipin":0,"startBeatNumber":196,"endBeatNumber":197,"dataPairs":[{"_eventDataKey":"EnemyId","_eventDataValue":"9189"},{"_eventDataKey":"ShouldClampToSubdivisions","_eventDataValue":"True"}],"group":0,"type":"SpawnEnemy"},{"track":1,"clipin":0,"startBeatNumber":199,"endBeatNumber":200,"dataPairs":[{"_eventDataKey":"EnemyId","_eventDataValue":"1722"},{"_eventDataKey":"ShouldClampToSubdivisions","_eventDataValue":"True"}],"group":0,"type":"SpawnEnemy"},{"track":2,"clipin":0,"startBeatNumber":200,"endBeatNumber":201,"dataPairs":[{"_eventDataKey":"EnemyId","_eventDataValue":"9189"},{"_eventDataKey":"ShouldClampToSubdivisions","_eventDataValue":"True"}],"group":0,"type":"SpawnEnemy"},{"track":2,"clipin":0,"startBeatNumber":203,"endBeatNumber":204,"dataPairs":[{"_eventDataKey":"EnemyId","_eventDataValue":"1722"},{"_eventDataKey":"ShouldClampToSubdivisions","_eventDataValue":"True"}],"group":0,"type":"SpawnEnemy"},{"track":2,"clipin":0,"startBeatNumber":205,"endBeatNumber":206,"dataPairs":[{"_eventDataKey":"BlademasterAttackRow","_eventDataValue":"2"},{"_eventDataKey":"EnemyId","_eventDataValue":"929"},{"_eventDataKey":"ShouldClampToSubdivisions","_eventDataValue":"True"}],"group":0,"type":"SpawnEnemy"},{"track":1,"clipin":0,"startBeatNumber":206,"endBeatNumber":207,"dataPairs":[{"_eventDataKey":"EnemyId","_eventDataValue":"4355"},{"_eventDataKey":"ShouldClampToSubdivisions","_eventDataValue":"True"}],"group":0,"type":"SpawnEnemy"},{"track":2,"clipin":0,"startBeatNumber":209,"endBeatNumber":210,"dataPairs":[{"_eventDataKey":"BlademasterAttackRow","_eventDataValue":"2"},{"_eventDataKey":"EnemyId","_eventDataValue":"929"},{"_eventDataKey":"ShouldClampToSubdivisions","_eventDataValue":"True"}],"group":0,"type":"SpawnEnemy"},{"track":3,"clipin":0,"startBeatNumber":210,"endBeatNumber":211,"dataPairs":[{"_eventDataKey":"EnemyId","_eventDataValue":"4355"},{"_eventDataKey":"ShouldClampToSubdivisions","_eventDataValue":"True"}],"group":0,"type":"SpawnEnemy"},{"track":1,"clipin":0,"startBeatNumber":212,"endBeatNumber":213,"dataPairs":[{"_eventDataKey":"EnemyId","_eventDataValue":"8519"},{"_eventDataKey":"ShouldClampToSubdivisions","_eventDataValue":"True"}],"group":0,"type":"SpawnEnemy"},{"track":3,"clipin":0,"startBeatNumber":212,"endBeatNumber":213,"dataPairs":[{"_eventDataKey":"EnemyId","_eventDataValue":"8519"},{"_eventDataKey":"ShouldClampToSubdivisions","_eventDataValue":"True"}],"group":0,"type":"SpawnEnemy"},{"track":2,"clipin":0,"startBeatNumber":214,"endBeatNumber":215,"dataPairs":[{"_eventDataKey":"EnemyId","_eventDataValue":"8675309"},{"_eventDataKey":"ShouldClampToSubdivisions","_eventDataValue":"True"}],"group":0,"type":"SpawnEnemy"},{"track":2,"clipin":0,"startBeatNumber":215.18751,"endBeatNumber":219.1875,"dataPairs":[{"_eventDataKey":"RiftedVibeChainShift","_eventDataValue":"215.1875"}],"group":0,"type":"StartVibeChain"},{"track":1,"clipin":0,"startBeatNumber":216,"endBeatNumber":217,"dataPairs":[{"_eventDataKey":"ShouldStartFacingRight","_eventDataValue":"True"},{"_eventDataKey":"EnemyId","_eventDataValue":"8675309"},{"_eventDataKey":"ShouldClampToSubdivisions","_eventDataValue":"True"}],"group":0,"type":"SpawnEnemy"},{"track":1,"clipin":0,"startBeatNumber":218,"endBeatNumber":219,"audioEvents":[],"dataPairs":[{"_eventDataKey":"ShouldClampToSubdivisions","_eventDataValue":"True"},{"_eventDataKey":"EnemyId","_eventDataValue":"717"},{"_eventDataKey":"ShouldStartFacingRight","_eventDataValue":"True"}],"group":0,"type":"SpawnEnemy"},{"track":2,"clipin":0,"startBeatNumber":222,"endBeatNumber":223,"audioEvents":[],"dataPairs":[{"_eventDataKey":"ShouldClampToSubdivisions","_eventDataValue":"True"},{"_eventDataKey":"EnemyId","_eventDataValue":"8675309"},{"_eventDataKey":"ShouldStartFacingRight","_eventDataValue":"False"}],"group":0,"type":"SpawnEnemy"},{"track":2,"clipin":0,"startBeatNumber":223,"endBeatNumber":224,"dataPairs":[{"_eventDataKey":"EnemyId","_eventDataValue":"7358"},{"_eventDataKey":"ShouldClampToSubdivisions","_eventDataValue":"True"}],"group":0,"type":"SpawnEnemy"},{"track":2,"clipin":0,"startBeatNumber":224,"endBeatNumber":225,"dataPairs":[{"_eventDataKey":"ShouldStartFacingRight","_eventDataValue":"True"},{"_eventDataKey":"EnemyId","_eventDataValue":"911"},{"_eventDataKey":"ShouldClampToSubdivisions","_eventDataValue":"True"}],"group":0,"type":"SpawnEnemy"},{"track":1,"clipin":0,"startBeatNumber":227,"endBeatNumber":228,"dataPairs":[{"_eventDataKey":"EnemyId","_eventDataValue":"7358"},{"_eventDataKey":"ShouldClampToSubdivisions","_eventDataValue":"True"}],"group":0,"type":"SpawnEnemy"},{"track":3,"clipin":0,"startBeatNumber":227,"endBeatNumber":228,"dataPairs":[{"_eventDataKey":"EnemyId","_eventDataValue":"7358"},{"_eventDataKey":"ShouldClampToSubdivisions","_eventDataValue":"True"}],"group":0,"type":"SpawnEnemy"},{"track":1,"clipin":0,"startBeatNumber":228,"endBeatNumber":229,"dataPairs":[{"_eventDataKey":"ShouldStartFacingRight","_eventDataValue":"True"},{"_eventDataKey":"EnemyId","_eventDataValue":"717"},{"_eventDataKey":"ShouldClampToSubdivisions","_eventDataValue":"True"}],"group":0,"type":"SpawnEnemy"},{"track":2,"clipin":0,"startBeatNumber":231,"endBeatNumber":232,"dataPairs":[{"_eventDataKey":"EnemyId","_eventDataValue":"2202"},{"_eventDataKey":"ShouldClampToSubdivisions","_eventDataValue":"True"}],"group":0,"type":"SpawnEnemy"},{"track":3,"clipin":0,"startBeatNumber":232,"endBeatNumber":233,"audioEvents":[],"dataPairs":[{"_eventDataKey":"ShouldClampToSubdivisions","_eventDataValue":"True"},{"_eventDataKey":"EnemyId","_eventDataValue":"8675309"},{"_eventDataKey":"ShouldStartFacingRight","_eventDataValue":"False"}],"group":0,"type":"SpawnEnemy"},{"track":1,"clipin":0,"startBeatNumber":234,"endBeatNumber":235,"audioEvents":[],"dataPairs":[{"_eventDataKey":"ShouldClampToSubdivisions","_eventDataValue":"True"},{"_eventDataKey":"EnemyId","_eventDataValue":"8675309"},{"_eventDataKey":"ShouldStartFacingRight","_eventDataValue":"True"}],"group":0,"type":"SpawnEnemy"},{"track":1,"clipin":0,"startBeatNumber":237,"endBeatNumber":238,"dataPairs":[{"_eventDataKey":"EnemyId","_eventDataValue":"1722"},{"_eventDataKey":"ShouldClampToSubdivisions","_eventDataValue":"True"}],"group":0,"type":"SpawnEnemy"},{"track":2,"clipin":0,"startBeatNumber":237,"endBeatNumber":238,"dataPairs":[{"_eventDataKey":"EnemyId","_eventDataValue":"2716"},{"_eventDataKey":"ShouldClampToSubdivisions","_eventDataValue":"True"}],"group":0,"type":"SpawnEnemy"},{"track":3,"clipin":0,"startBeatNumber":237,"endBeatNumber":238,"dataPairs":[{"_eventDataKey":"EnemyId","_eventDataValue":"1722"},{"_eventDataKey":"ShouldClampToSubdivisions","_eventDataValue":"True"}],"group":0,"type":"SpawnEnemy"},{"track":2,"clipin":0,"startBeatNumber":240,"endBeatNumber":241,"dataPairs":[{"_eventDataKey":"EnemyId","_eventDataValue":"4355"},{"_eventDataKey":"ShouldClampToSubdivisions","_eventDataValue":"True"}],"group":0,"type":"SpawnEnemy"},{"track":1,"clipin":0,"startBeatNumber":241,"endBeatNumber":242,"dataPairs":[{"_eventDataKey":"EnemyId","_eventDataValue":"2202"},{"_eventDataKey":"ShouldClampToSubdivisions","_eventDataValue":"True"}],"group":0,"type":"SpawnEnemy"},{"track":2,"clipin":0,"startBeatNumber":242,"endBeatNumber":243,"dataPairs":[{"_eventDataKey":"EnemyId","_eventDataValue":"4355"},{"_eventDataKey":"ShouldClampToSubdivisions","_eventDataValue":"True"}],"group":0,"type":"SpawnEnemy"},{"track":3,"clipin":0,"startBeatNumber":243,"endBeatNumber":244,"dataPairs":[{"_eventDataKey":"EnemyId","_eventDataValue":"6803"},{"_eventDataKey":"ShouldClampToSubdivisions","_eventDataValue":"True"}],"group":0,"type":"SpawnEnemy"},{"track":1,"clipin":0,"startBeatNumber":245,"endBeatNumber":246,"dataPairs":[{"_eventDataKey":"EnemyId","_eventDataValue":"2202"},{"_eventDataKey":"ShouldClampToSubdivisions","_eventDataValue":"True"}],"group":0,"type":"SpawnEnemy"},{"track":1,"clipin":0,"startBeatNumber":246,"endBeatNumber":247,"dataPairs":[{"_eventDataKey":"EnemyId","_eventDataValue":"6803"},{"_eventDataKey":"ShouldClampToSubdivisions","_eventDataValue":"True"}],"group":0,"type":"SpawnEnemy"},{"track":3,"clipin":0,"startBeatNumber":246,"endBeatNumber":247,"dataPairs":[{"_eventDataKey":"EnemyId","_eventDataValue":"2202"},{"_eventDataKey":"ShouldClampToSubdivisions","_eventDataValue":"True"}],"group":0,"type":"SpawnEnemy"},{"track":1,"clipin":0,"startBeatNumber":248,"endBeatNumber":249,"dataPairs":[{"_eventDataKey":"EnemyId","_eventDataValue":"2202"},{"_eventDataKey":"ShouldClampToSubdivisions","_eventDataValue":"True"}],"group":0,"type":"SpawnEnemy"},{"track":3,"clipin":0,"startBeatNumber":248,"endBeatNumber":249,"dataPairs":[{"_eventDataKey":"EnemyId","_eventDataValue":"8675309"},{"_eventDataKey":"ShouldClampToSubdivisions","_eventDataValue":"True"}],"group":0,"type":"SpawnEnemy"},{"track":1,"clipin":0,"startBeatNumber":250,"endBeatNumber":251,"dataPairs":[{"_eventDataKey":"ShouldStartFacingRight","_eventDataValue":"True"},{"_eventDataKey":"EnemyId","_eventDataValue":"8675309"},{"_eventDataKey":"ShouldClampToSubdivisions","_eventDataValue":"True"}],"group":0,"type":"SpawnEnemy"},{"track":2,"clipin":0,"startBeatNumber":253,"endBeatNumber":254,"dataPairs":[{"_eventDataKey":"BlademasterAttackRow","_eventDataValue":"2"},{"_eventDataKey":"EnemyId","_eventDataValue":"929"},{"_eventDataKey":"ShouldClampToSubdivisions","_eventDataValue":"True"}],"group":0,"type":"SpawnEnemy"},{"track":1,"clipin":0,"startBeatNumber":254,"endBeatNumber":255,"dataPairs":[{"_eventDataKey":"ShouldStartFacingRight","_eventDataValue":"True"},{"_eventDataKey":"EnemyId","_eventDataValue":"911"},{"_eventDataKey":"ShouldClampToSubdivisions","_eventDataValue":"True"}],"group":0,"type":"SpawnEnemy"},{"track":1,"clipin":0,"startBeatNumber":257,"endBeatNumber":258,"audioEvents":[],"dataPairs":[{"_eventDataKey":"ShouldClampToSubdivisions","_eventDataValue":"True"},{"_eventDataKey":"EnemyId","_eventDataValue":"1236"},{"_eventDataKey":"ShouldStartFacingRight","_eventDataValue":"True"}],"group":0,"type":"SpawnEnemy"},{"track":3,"clipin":0,"startBeatNumber":259,"endBeatNumber":260,"audioEvents":[],"dataPairs":[{"_eventDataKey":"ShouldClampToSubdivisions","_eventDataValue":"True"},{"_eventDataKey":"EnemyId","_eventDataValue":"1236"},{"_eventDataKey":"ShouldStartFacingRight","_eventDataValue":"False"}],"group":0,"type":"SpawnEnemy"},{"track":1,"clipin":0,"startBeatNumber":261,"endBeatNumber":262,"audioEvents":[],"dataPairs":[{"_eventDataKey":"ShouldClampToSubdivisions","_eventDataValue":"True"},{"_eventDataKey":"EnemyId","_eventDataValue":"2202"},{"_eventDataKey":"ShouldStartFacingRight","_eventDataValue":"False"}],"group":0,"type":"SpawnEnemy"},{"track":2,"clipin":0,"startBeatNumber":261,"endBeatNumber":262,"audioEvents":[],"dataPairs":[{"_eventDataKey":"ShouldClampToSubdivisions","_eventDataValue":"True"},{"_eventDataKey":"EnemyId","_eventDataValue":"2202"},{"_eventDataKey":"ShouldStartFacingRight","_eventDataValue":"False"}],"group":0,"type":"SpawnEnemy"},{"track":3,"clipin":0,"startBeatNumber":261,"endBeatNumber":262,"audioEvents":[],"dataPairs":[{"_eventDataKey":"ShouldClampToSubdivisions","_eventDataValue":"True"},{"_eventDataKey":"EnemyId","_eventDataValue":"2202"},{"_eventDataKey":"ShouldStartFacingRight","_eventDataValue":"False"}],"group":0,"type":"SpawnEnemy"},{"track":3,"clipin":0,"startBeatNumber":262,"endBeatNumber":263,"audioEvents":[],"dataPairs":[{"_eventDataKey":"ShouldClampToSubdivisions","_eventDataValue":"True"},{"_eventDataKey":"EnemyId","_eventDataValue":"2202"},{"_eventDataKey":"ShouldStartFacingRight","_eventDataValue":"False"}],"group":0,"type":"SpawnEnemy"},{"track":3,"clipin":0,"startBeatNumber":263,"endBeatNumber":264,"dataPairs":[{"_eventDataKey":"ShouldStartFacingRight","_eventDataValue":"True"},{"_eventDataKey":"EnemyId","_eventDataValue":"1234"},{"_eventDataKey":"ShouldClampToSubdivisions","_eventDataValue":"True"}],"group":0,"type":"SpawnEnemy"},{"track":3,"clipin":0,"startBeatNumber":264,"endBeatNumber":265,"dataPairs":[{"_eventDataKey":"ShouldStartFacingRight","_eventDataValue":"True"},{"_eventDataKey":"EnemyId","_eventDataValue":"1234"},{"_eventDataKey":"ShouldClampToSubdivisions","_eventDataValue":"True"}],"group":0,"type":"SpawnEnemy"},{"track":1,"clipin":0,"startBeatNumber":265,"endBeatNumber":266,"dataPairs":[{"_eventDataKey":"EnemyId","_eventDataValue":"8156"},{"_eventDataKey":"ShouldClampToSubdivisions","_eventDataValue":"True"}],"group":0,"type":"SpawnEnemy"},{"track":2,"clipin":0,"startBeatNumber":268,"endBeatNumber":269,"dataPairs":[{"_eventDataKey":"EnemyId","_eventDataValue":"1722"},{"_eventDataKey":"ShouldClampToSubdivisions","_eventDataValue":"True"}],"group":0,"type":"SpawnEnemy"}],"playbackOffset":-0}